Workbook

Sheet PT_62
C2: GUAICARAMO S.A.S.
C4: CLIENTE: | D4: GUAICARAMO S.A.S. | N4: PREPARADO: | O4: REVISADO: | P4: Ref. PT
C5: NIT: | D5: 860.040.584-0 | P5: 62 / 64
C6: PERIODO: | D6: 1-ene-2026 a 31-jul-2026 | N6: Fecha: | O6: Fecha:
C7: FECHA DE CORTE: | D7: =Resumen!C5 -> 46234 | N7: Iniciales y fecha del preparador / revisor
C8: NOMBRE P/T: | D8: OBLIGACIONES FINANCIERAS (cuenta 21 – papel 62/64)
C9: MARCO TÉCNICO: | D9: NIIF Plenas (Grupo 1): NIIF 9, NIIF 16, NIC 1, NIIF 7, NIC 23, NIC 24
C10: MONEDA: | D10: Pesos colombianos (COP)
C12: CÓMO LEER ESTE PAPEL (guía rápida)
C13: 1. Esta hoja resume TODO el trabajo: qué se revisó, cómo y qué se encontró. Las hojas de soporte están enlazadas al final (clic en el nombre).
C14: 2. Celdas BLANCAS = información del cliente, del balance o del banco. Celdas AMARILLAS = cálculos y recálculos hechos por auditoría.
C15: 3. 'OK' = la cifra cuadra. 'DIFERENCIA' = hay que revisar (la explicación está en la hoja 'Hallazgos'). [P] = falta un soporte (hoja 'Pendientes').
C16: 4. Orden sugerido de lectura: Conclusión (al final) → secciones 1 a 5 → hoja 'Pruebas_Auditoria' → hoja 'Tablas_Amortizacion' → 'Hallazgos'.
C18: OBJETIVO GENERAL
C19: Obtener evidencia suficiente y apropiada sobre la razonabilidad de los saldos de obligaciones financieras (créditos y pasivos por arrendamiento financiero) e intereses por pagar al 31-jul-2026, y del gasto financiero asociado, verificando integridad, existencia, exactitud, valuación a costo amortizado (método del interés efectivo – NIIF 9 §4.2.1 y B5.4; NIIF 16 §36), corte y clasificación corriente/no corriente (NIC 1 §69-76), con base en el balance de prueba, el auxiliar contable, el detalle 62, las tablas de amortización (papel 64) y los extractos/certificados bancarios.
C21: LIMITACIONES AL ALCANCE
C22: ="Se emite con "&Pendientes!$D$20&" pendientes de soporte (hoja Pendientes): certificados de saldo al 31-jul-26 de leasings Davivienda y Bancolombia, confirmaciones BBVA y Banco Popular, certificado del crédito Bogotá 1159383796, tablas del leasing 386735/GECOLSA y materialidad del encargo. Las conclusiones afectadas se marcan [P]." -> Se emite con 14 pendientes de soporte (hoja Pendientes): certificados de saldo al 31-jul-26 de leasings Davivienda y Bancolombia, confirmaciones BBVA y Banco Popular, certificado del crédito Bogotá 1159383796, tablas del leasing 386735/GECOLSA y materialidad del encargo. Las conclusiones afectadas se marcan [P].
C24: ASEVERACIONES
C25: Aseveración | D25: Procedimiento principal | E25: Hoja soporte | I25: Resultado
C26: Existencia / Ocurrencia | D26: Cotejo con certificados y extractos bancarios; pagos certificados vs comprobantes. | E26: Pruebas_Auditoria (bloque 2) | I26: ="Cobertura con extracto 2026: "&TEXT(Pruebas_Auditoria!$K$87,"0%")&"; diferencias de pagos: "&TEXT(Pruebas_Auditoria!J131,"#,##0") -> Cobertura con extracto 2026: 85%; diferencias de pagos: 11,975,072
C27: Integridad | D27: Movimiento vs balance; detalle 62 vs mayor por obligación; obligaciones del mayor no incluidas en el detalle. | E27: Pruebas_Auditoria (bloque 3) | I27: ="Mayor vs balance: "&Resumen!F11&". Leasing mayor − detalle 62: "&TEXT(Cruce_Detalle_Mayor!F7,"#,##0")&" (386735 y GECOLSA no están en el detalle)." -> Mayor vs balance: OK. Leasing mayor − detalle 62: 1,018,266,177 (386735 y GECOLSA no están en el detalle).
C28: Exactitud / Valuación | D28: Recálculo de intereses, de las tablas de amortización y de la causación al corte (NIIF 9 B5.4, NIIF 16 §36). | E28: Pruebas_Auditoria (bloque 4) / Tablas_Amortizacion (resumen) | I28: ="Causación no registrada al 31-jul: "&TEXT(Pruebas_Auditoria!K236,"#,##0")&"; tablas con error: 362095, Hoja2 (1159383796), costo amortizado Davivienda." -> Causación no registrada al 31-jul: 187,705,390; tablas con error: 362095, Hoja2 (1159383796), costo amortizado Davivienda.
C29: Corte | D29: Causación de intereses entre el último pago y el 31-jul; prórrogas y desembolsos cercanos al cierre. | E29: Pruebas_Auditoria (bloque 4) | I29: ="AJE-1 por "&TEXT(Pruebas_Auditoria!K236,"#,##0") -> AJE-1 por 187,705,390
C30: Derechos y obligaciones | D30: Titularidad de las obligaciones (NIT Guaicaramo) y obligaciones de terceros incluidas en el archivo de tablas. | E30: Tablas_Amortizacion (resumen) | I30: ="Crédito DYPSIS $72.300 MM en el archivo de tablas no está en el mayor: confirmar titular/garantías [P]." -> Crédito DYPSIS $72.300 MM en el archivo de tablas no está en el mayor: confirmar titular/garantías [P].
C31: Clasificación y presentación | D31: Porción corriente según tablas y vencimientos (NIC 1 §69); agrupación de tarjetas de crédito. | E31: Clasif_CP_LP | I31: ="Reclasificación LP→CP propuesta: "&TEXT(Clasif_CP_LP!B11+Clasif_CP_LP!B12,"#,##0") -> Reclasificación LP→CP propuesta: 1,576,635,656
C32: Revelación | D32: Datos para NIIF 7 (vencimientos, tasas variables IBR/DTF) y NIIF 16 (pasivos por arrendamiento). | E32: Detalle_62 / Tablas_Amortizacion (resumen) | I32: ="Tasas y vencimientos del detalle 62 difieren de los certificados en varias obligaciones (hallazgos 7 y 14)." -> Tasas y vencimientos del detalle 62 difieren de los certificados en varias obligaciones (hallazgos 7 y 14).
C34: TÉCNICAS DE AUDITORÍA APLICADAS
C35: ☑ Análisis ☑ Recálculo ☑ Inspección documental (extractos/certificados) ☑ Comparación (mayor ↔ detalle ↔ tabla ↔ banco) ☑ Prueba analítica sustantiva ☐ Confirmación externa (pendiente)
C37: PROCEDIMIENTOS
B38: # | C38: Procedimiento | I38: Ref. hoja | L38: Resultado
B39: 1 | C39: Cruzar el auxiliar de la cuenta 21 contra el balance de prueba (débitos, créditos y saldos) y comparar las dos versiones del balance. | I39: Pruebas_Auditoria (bloque 1) | L39: =Resumen!F11 -> OK
B40: 2 | C40: Reconstruir el saldo del mayor por obligación (detalle 31-dic-25 + movimientos 2026) y cruzarlo con el detalle 62. | I40: Pruebas_Auditoria (bloque 3) | L40: =IF(ABS(Pruebas_Auditoria!H177)+ABS(Pruebas_Auditoria!H181)<=Resumen!$C$6,"Por obligación cuadra con balance","Revisar") -> Por obligación cuadra con balance
B41: 3 | C41: Cotejar saldos, tasas, vencimientos y pagos con extractos/certificados bancarios. | I41: Pruebas_Auditoria (bloque 2) | L41: =Resumen!F16 -> DIFERENCIA
B42: 4 | C42: Revisar y recalcular las tablas de amortización del cliente (papel 64): aritmética, TIR, saldo al corte, porción corriente. | I42: Tablas_Amortizacion | L42: ="Tablas con hallazgos: 362095, Hoja2 (1159383796), costo amortizado Davivienda; "&COUNTIF(Tablas_Amortizacion!R12:R36,"N/D")&" sin saldo banco" -> Tablas con hallazgos: 362095, Hoja2 (1159383796), costo amortizado Davivienda; 4 sin saldo banco
B43: 5 | C43: Recalcular intereses liquidados por los bancos y la causación al 31-jul (costo amortizado). | I43: Pruebas_Auditoria (bloque 4) / Intereses_x_Obligacion | L43: =Resumen!F18 -> DIFERENCIA
B44: 6 | C44: Cruzar las cuentas de gasto financiero (5305) y de intereses por pagar (2130) contra la suma por obligación. | I44: Intereses_x_Obligacion | L44: =IF(ABS(Intereses_x_Obligacion!E38)<=Resumen!$C$6,"2130 cuadra por obligación","Revisar") -> 2130 cuadra por obligación
B45: 7 | C45: Prueba analítica sustantiva del gasto por intereses. | I45: Gasto_Intereses | L45: =Gasto_Intereses!B20 -> Gasto razonable dentro del umbral
B46: 8 | C46: Evaluar la clasificación corriente / no corriente y la presentación. | I46: Clasif_CP_LP | L46: ="Ver reclasificación AJE-2" -> Ver reclasificación AJE-2
B47: 9 | C47: Concluir y documentar hallazgos, ajustes y pendientes. | I47: Hallazgos / Pendientes | L47: =Pendientes!$D$20&" pendientes abiertos" -> 14 pendientes abiertos
C49: FUENTES DE INFORMACIÓN
C50: [A] Balance de prueba NIIF a jul-2026 (Balance_2026_GUUU.xlsx – 24-ago-26 – y Obl_Financieros.xlsx/Hoja1 – 29-sep-26).
C51: [A] Auxiliar cuenta 21 ene–jul 2026 (Obl_Financieros.xlsx/Sheet1).
C52: [A] Detalle de obligaciones financieras a jul-26 (62._Obligaciones_Financieras.xlsx).
C53: [A] Tablas de amortización (64._Tabla_amortización_obligaciones_financieras.xlsm).
C54: [A] PT Obligaciones Financieras al 31-dic-2025 (ejemplo.xlsx): detalle del mayor por obligación y saldos de extractos a dic-25.
C55: [C] Extractos/certificados bancarios (ilovepdf_merged_1.pdf; LEASING_1275-3/9441-2/9448-3_DAVIVIENDA.pdf).
C57: ******* 1 ******* Prueba de auditoría – Cuentas del balance vs detalle 62 vs saldo por obligación
C58: CUENTA | D58: DESCRIPCIÓN | E58: SALDO BALANCE 31/07/2026 | F58: SALDO DETALLE 62 | G58: SALDO POR OBLIGACIÓN (mayor) | H58: DIF. BALANCE − DETALLE 62 | I58: DIF. BALANCE − POR OBLIGACIÓN | J58: MARCA
C59: 210501 + 210502 | D59: Créditos (sin tarjetas de crédito) | E59: =-(Balance_21!$F$16+Balance_21!$F$18) -> 38300666666 | F59: =SUMIFS(Detalle_62!$F$14:$F$35,Detalle_62!$D$14:$D$35,"Crédito") -> 3.8300667e+10 | G59: =Pruebas_Auditoria!H175 -> 38300666666 | H59: =IF(AND(ISNUMBER(E59),ISNUMBER(F59)),E59-F59,"N/A") -> 0.66666412 | I59: =IF(AND(ISNUMBER(E59),ISNUMBER(G59)),E59-G59,"N/A") -> 0 | J59: [D] [A]
C60: 212020 + 212021 | D60: Leasing financiero (NIIF 16) | E60: =-(Balance_21!$F$22+Balance_21!$F$24) -> 7.9035116e+09 | F60: =SUMIFS(Detalle_62!$F$14:$F$35,Detalle_62!$D$14:$D$35,"Leasing") -> 6.8852455e+09 | G60: =Pruebas_Auditoria!H179 -> 7.9035116e+09 | H60: =IF(AND(ISNUMBER(E60),ISNUMBER(F60)),E60-F60,"N/A") -> 1.0182662e+09 | I60: =IF(AND(ISNUMBER(E60),ISNUMBER(G60)),E60-G60,"N/A") -> 0 | J60: [D] [A]
C61: 213001 | D61: Intereses financieros por pagar | E61: =-Balance_21!$F$25 -> 4.2738902e+08 | F61: No incluido | G61: =Intereses_x_Obligacion!F32 -> 4.2738902e+08 | H61: =IF(AND(ISNUMBER(E61),ISNUMBER(F61)),E61-F61,"N/A") -> N/A | I61: =IF(AND(ISNUMBER(E61),ISNUMBER(G61)),E61-G61,"N/A") -> -1.22 | J61: [D] [A]
C62: 21050301 | D62: Tarjetas de crédito por pagar | E62: =-Balance_21!$F$19 -> 31135732 | F62: No incluido | G62: N/A | H62: =IF(AND(ISNUMBER(E62),ISNUMBER(F62)),E62-F62,"N/A") -> N/A | I62: =IF(AND(ISNUMBER(E62),ISNUMBER(G62)),E62-G62,"N/A") -> N/A | J62: [D] [A]
D63: TOTAL | E63: =SUM(E59:E62) -> 4.6662703e+10 | F63: =SUM(F59:F62) -> 4.5185912e+10 | G63: =SUM(G59:G62) -> 4.6631567e+10 | H63: =SUM(H59:H62) -> 1.0182662e+09 | I63: =SUM(I59:I62) -> -1.22
C65: ******* 2 ******* Validación por terceros y número de obligación financiera (saldo mayor vs detalle vs tabla vs extracto)
C66: Banco Davivienda
C67: N° obligación (ID) | D67: Descripción | E67: Saldo mayor 31-jul | F67: Saldo detalle 62 | G67: Saldo tabla amort. | H67: Saldo extracto/banco | I67: Dif. mayor − banco | J67: Tipo tasa | K67: Frecuencia | L67: Fecha venc. | M67: Tasa EA banco | N67: Intereses 2026 registrados | O67: Int. por pagar 2130 | P67: Causación recalc. 31-jul | Q67: Marca
C68: DAV-8906 | D68: =Pruebas_Auditoria!D148 -> Crédito tesorería 457300748906 (cancelado 28-ene-26) | E68: =Pruebas_Auditoria!H148 -> 0 | F68: =Pruebas_Auditoria!I148 -> 0 | G68: =Pruebas_Auditoria!J148 -> Sin tabla | H68: =Pruebas_Auditoria!L148 -> 0 | I68: =Pruebas_Auditoria!O148 -> 0 | J68: =IFERROR(INDEX(Detalle_62!$H$14:$H$35,MATCH(C68,Detalle_62!$C$14:$C$35,0)),"—") -> — | K68: =IFERROR(INDEX(Detalle_62!$L$14:$L$35,MATCH(C68,Detalle_62!$C$14:$C$35,0)),"—") -> — | L68: =IFERROR(INDEX(Detalle_62!$P$14:$P$35,MATCH(C68,Detalle_62!$C$14:$C$35,0)),"—") -> — | M68: =IFERROR(INDEX(Pruebas_Auditoria!$M$53:$M$137,MATCH(C68,Pruebas_Auditoria!$E$53:$E$137,0)),"—") -> — | N68: =INDEX(Intereses_x_Obligacion!$I:$I,MATCH(C68,Intereses_x_Obligacion!$A:$A,0)) -> 66026667 | O68: =INDEX(Intereses_x_Obligacion!$F:$F,MATCH(C68,Intereses_x_Obligacion!$A:$A,0)) -> 0 | P68: =INDEX(Intereses_x_Obligacion!$L:$L,MATCH(C68,Intereses_x_Obligacion!$A:$A,0)) -> 0 | Q68: =IF(LEFT(Pruebas_Auditoria!M148,3)="[C]","[C] [B]",IF(LEFT(Pruebas_Auditoria!M148,3)="[E]","[E] [B]","[P]")) -> [E] [B]
C69: DAV-569032 | D69: =Pruebas_Auditoria!D149 -> 457300569032 – CRED TESORERIA | E69: =Pruebas_Auditoria!H149 -> 3000000000 | F69: =Pruebas_Auditoria!I149 -> 3000000000 | G69: =Pruebas_Auditoria!J149 -> 3000000000 | H69: =Pruebas_Auditoria!L149 -> 2999995157 | I69: =Pruebas_Auditoria!O149 -> 4843 | J69: =IFERROR(INDEX(Detalle_62!$H$14:$H$35,MATCH(C69,Detalle_62!$C$14:$C$35,0)),"—") -> IBR 6 MESES | K69: =IFERROR(INDEX(Detalle_62!$L$14:$L$35,MATCH(C69,Detalle_62!$C$14:$C$35,0)),"—") -> SEMESTRAL | L69: =IFERROR(INDEX(Detalle_62!$P$14:$P$35,MATCH(C69,Detalle_62!$C$14:$C$35,0)),"—") -> 51710 | M69: =IFERROR(INDEX(Pruebas_Auditoria!$M$53:$M$137,MATCH(C69,Pruebas_Auditoria!$E$53:$E$137,0)),"—") -> 0.1258 | N69: =INDEX(Intereses_x_Obligacion!$I:$I,MATCH(C69,Intereses_x_Obligacion!$A:$A,0)) -> 234581000 | O69: =INDEX(Intereses_x_Obligacion!$F:$F,MATCH(C69,Intereses_x_Obligacion!$A:$A,0)) -> 0 | P69: =INDEX(Intereses_x_Obligacion!$L:$L,MATCH(C69,Intereses_x_Obligacion!$A:$A,0)) -> 3666117.8 | Q69: =IF(LEFT(Pruebas_Auditoria!M149,3)="[C]","[C] [B]",IF(LEFT(Pruebas_Auditoria!M149,3)="[E]","[E] [B]","[P]")) -> [C] [B]
C70: DAV-830624 | D70: =Pruebas_Auditoria!D150 -> 457300830624 – CRED TESORERIA | E70: =Pruebas_Auditoria!H150 -> 7500000000 | F70: =Pruebas_Auditoria!I150 -> 7500000000 | G70: =Pruebas_Auditoria!J150 -> 7500000000 | H70: =Pruebas_Auditoria!L150 -> 7.4999985e+09 | I70: =Pruebas_Auditoria!O150 -> 1496.75 | J70: =IFERROR(INDEX(Detalle_62!$H$14:$H$35,MATCH(C70,Detalle_62!$C$14:$C$35,0)),"—") -> IBR 6 MESES | K70: =IFERROR(INDEX(Detalle_62!$L$14:$L$35,MATCH(C70,Detalle_62!$C$14:$C$35,0)),"—") -> SEMESTRAL | L70: =IFERROR(INDEX(Detalle_62!$P$14:$P$35,MATCH(C70,Detalle_62!$C$14:$C$35,0)),"—") -> 52677 | M70: =IFERROR(INDEX(Pruebas_Auditoria!$M$53:$M$137,MATCH(C70,Pruebas_Auditoria!$E$53:$E$137,0)),"—") -> 0.1551 | N70: =INDEX(Intereses_x_Obligacion!$I:$I,MATCH(C70,Intereses_x_Obligacion!$A:$A,0)) -> 586251750 | O70: =INDEX(Intereses_x_Obligacion!$F:$F,MATCH(C70,Intereses_x_Obligacion!$A:$A,0)) -> 372400000 | P70: =INDEX(Intereses_x_Obligacion!$L:$L,MATCH(C70,Intereses_x_Obligacion!$A:$A,0)) -> 4.0145817e+08 | Q70: =IF(LEFT(Pruebas_Auditoria!M150,3)="[C]","[C] [B]",IF(LEFT(Pruebas_Auditoria!M150,3)="[E]","[E] [B]","[P]")) -> [C] [B]
C71: DAV-607691 | D71: =Pruebas_Auditoria!D151 -> 457300607691 – CRED TESORERIA | E71: =Pruebas_Auditoria!H151 -> 3960000000 | F71: =Pruebas_Auditoria!I151 -> 3960000000 | G71: =Pruebas_Auditoria!J151 -> 3960000000 | H71: =Pruebas_Auditoria!L151 -> 3.9599978e+09 | I71: =Pruebas_Auditoria!O151 -> 2182.05 | J71: =IFERROR(INDEX(Detalle_62!$H$14:$H$35,MATCH(C71,Detalle_62!$C$14:$C$35,0)),"—") -> IBR 6 MESES | K71: =IFERROR(INDEX(Detalle_62!$L$14:$L$35,MATCH(C71,Detalle_62!$C$14:$C$35,0)),"—") -> SEMESTRAL | L71: =IFERROR(INDEX(Detalle_62!$P$14:$P$35,MATCH(C71,Detalle_62!$C$14:$C$35,0)),"—") -> 51710 | M71: =IFERROR(INDEX(Pruebas_Auditoria!$M$53:$M$137,MATCH(C71,Pruebas_Auditoria!$E$53:$E$137,0)),"—") -> 0.1258 | N71: =INDEX(Intereses_x_Obligacion!$I:$I,MATCH(C71,Intereses_x_Obligacion!$A:$A,0)) -> 309646400 | O71: =INDEX(Intereses_x_Obligacion!$F:$F,MATCH(C71,Intereses_x_Obligacion!$A:$A,0)) -> 0 | P71: =INDEX(Intereses_x_Obligacion!$L:$L,MATCH(C71,Intereses_x_Obligacion!$A:$A,0)) -> 4839280.6 | Q71: =IF(LEFT(Pruebas_Auditoria!M151,3)="[C]","[C] [B]",IF(LEFT(Pruebas_Auditoria!M151,3)="[E]","[E] [B]","[P]")) -> [C] [B]
C72: DAV-L1019441 | D72: =Pruebas_Auditoria!D152 -> LEASING 1019441 – CAMION LZT 927 | E72: =Pruebas_Auditoria!H152 -> 399387154 | F72: =Pruebas_Auditoria!I152 -> 3.9858217e+08 | G72: =Pruebas_Auditoria!J152 -> 3.9858217e+08 | H72: =Pruebas_Auditoria!L152 -> 399387154 | I72: =Pruebas_Auditoria!O152 -> 0 | J72: =IFERROR(INDEX(Detalle_62!$H$14:$H$35,MATCH(C72,Detalle_62!$C$14:$C$35,0)),"—") -> IBR | K72: =IFERROR(INDEX(Detalle_62!$L$14:$L$35,MATCH(C72,Detalle_62!$C$14:$C$35,0)),"—") -> MENSUAL | L72: =IFERROR(INDEX(Detalle_62!$P$14:$P$35,MATCH(C72,Detalle_62!$C$14:$C$35,0)),"—") -> 47037 | M72: =IFERROR(INDEX(Pruebas_Auditoria!$M$53:$M$137,MATCH(C72,Pruebas_Auditoria!$E$53:$E$137,0)),"—") -> 0.1603 | N72: =INDEX(Intereses_x_Obligacion!$I:$I,MATCH(C72,Intereses_x_Obligacion!$A:$A,0)) -> 31222019 | O72: =INDEX(Intereses_x_Obligacion!$F:$F,MATCH(C72,Intereses_x_Obligacion!$A:$A,0)) -> 0 | P72: =INDEX(Intereses_x_Obligacion!$L:$L,MATCH(C72,Intereses_x_Obligacion!$A:$A,0)) -> 2939106.3 | Q72: =IF(LEFT(Pruebas_Auditoria!M152,3)="[C]","[C] [B]",IF(LEFT(Pruebas_Auditoria!M152,3)="[E]","[E] [B]","[P]")) -> [E] [B]
C73: DAV-L1019448 | D73: =Pruebas_Auditoria!D153 -> LEASING 1019448 – CAMION LZT 926 | E73: =Pruebas_Auditoria!H153 -> 332999135 | F73: =Pruebas_Auditoria!I153 -> 3.2352969e+08 | G73: =Pruebas_Auditoria!J153 -> 3.2352969e+08 | H73: =Pruebas_Auditoria!L153 -> 332999135 | I73: =Pruebas_Auditoria!O153 -> 0 | J73: =IFERROR(INDEX(Detalle_62!$H$14:$H$35,MATCH(C73,Detalle_62!$C$14:$C$35,0)),"—") -> IBR | K73: =IFERROR(INDEX(Detalle_62!$L$14:$L$35,MATCH(C73,Detalle_62!$C$14:$C$35,0)),"—") -> MENSUAL | L73: =IFERROR(INDEX(Detalle_62!$P$14:$P$35,MATCH(C73,Detalle_62!$C$14:$C$35,0)),"—") -> 47098 | M73: =IFERROR(INDEX(Pruebas_Auditoria!$M$53:$M$137,MATCH(C73,Pruebas_Auditoria!$E$53:$E$137,0)),"—") -> 0.1593 | N73: =INDEX(Intereses_x_Obligacion!$I:$I,MATCH(C73,Intereses_x_Obligacion!$A:$A,0)) -> 25643813 | O73: =INDEX(Intereses_x_Obligacion!$F:$F,MATCH(C73,Intereses_x_Obligacion!$A:$A,0)) -> 0 | P73: =INDEX(Intereses_x_Obligacion!$L:$L,MATCH(C73,Intereses_x_Obligacion!$A:$A,0)) -> 3388544.1 | Q73: =IF(LEFT(Pruebas_Auditoria!M153,3)="[C]","[C] [B]",IF(LEFT(Pruebas_Auditoria!M153,3)="[E]","[E] [B]","[P]")) -> [E] [B]
C74: DAV-L1021275 | D74: =Pruebas_Auditoria!D154 -> LEASING 10212753 – CALDERAS-SISTEMA DE ALIMENTACION BIOMASA | E74: =Pruebas_Auditoria!H154 -> 1876684264 | F74: =Pruebas_Auditoria!I154 -> 1.8837122e+09 | G74: =Pruebas_Auditoria!J154 -> 1.8837122e+09 | H74: =Pruebas_Auditoria!L154 -> 1876684264 | I74: =Pruebas_Auditoria!O154 -> 0 | J74: =IFERROR(INDEX(Detalle_62!$H$14:$H$35,MATCH(C74,Detalle_62!$C$14:$C$35,0)),"—") -> IBR 3 MESES | K74: =IFERROR(INDEX(Detalle_62!$L$14:$L$35,MATCH(C74,Detalle_62!$C$14:$C$35,0)),"—") -> TRIMESTRAL | L74: =IFERROR(INDEX(Detalle_62!$P$14:$P$35,MATCH(C74,Detalle_62!$C$14:$C$35,0)),"—") -> 48235 | M74: =IFERROR(INDEX(Pruebas_Auditoria!$M$53:$M$137,MATCH(C74,Pruebas_Auditoria!$E$53:$E$137,0)),"—") -> 0.1441 | N74: =INDEX(Intereses_x_Obligacion!$I:$I,MATCH(C74,Intereses_x_Obligacion!$A:$A,0)) -> 138538864 | O74: =INDEX(Intereses_x_Obligacion!$F:$F,MATCH(C74,Intereses_x_Obligacion!$A:$A,0)) -> 0 | P74: =INDEX(Intereses_x_Obligacion!$L:$L,MATCH(C74,Intereses_x_Obligacion!$A:$A,0)) -> 5545405.4 | Q74: =IF(LEFT(Pruebas_Auditoria!M154,3)="[C]","[C] [B]",IF(LEFT(Pruebas_Auditoria!M154,3)="[E]","[E] [B]","[P]")) -> [E] [B]
C75: DAV-LGECOLSA | D75: =Pruebas_Auditoria!D155 -> Leasing 2 motogeneradores GECOLSA (no está en detalle 62) | E75: =Pruebas_Auditoria!H155 -> 213861900 | F75: =Pruebas_Auditoria!I155 -> 0 | G75: =Pruebas_Auditoria!J155 -> Sin tabla | H75: =Pruebas_Auditoria!L155 -> N/D | I75: =Pruebas_Auditoria!O155 -> N/D | J75: =IFERROR(INDEX(Detalle_62!$H$14:$H$35,MATCH(C75,Detalle_62!$C$14:$C$35,0)),"—") -> — | K75: =IFERROR(INDEX(Detalle_62!$L$14:$L$35,MATCH(C75,Detalle_62!$C$14:$C$35,0)),"—") -> — | L75: =IFERROR(INDEX(Detalle_62!$P$14:$P$35,MATCH(C75,Detalle_62!$C$14:$C$35,0)),"—") -> — | M75: =IFERROR(INDEX(Pruebas_Auditoria!$M$53:$M$137,MATCH(C75,Pruebas_Auditoria!$E$53:$E$137,0)),"—") -> — | N75: =INDEX(Intereses_x_Obligacion!$I:$I,MATCH(C75,Intereses_x_Obligacion!$A:$A,0)) -> 0 | O75: =INDEX(Intereses_x_Obligacion!$F:$F,MATCH(C75,Intereses_x_Obligacion!$A:$A,0)) -> 0 | P75: =INDEX(Intereses_x_Obligacion!$L:$L,MATCH(C75,Intereses_x_Obligacion!$A:$A,0)) -> 0 | Q75: =IF(LEFT(Pruebas_Auditoria!M155,3)="[C]","[C] [B]",IF(LEFT(Pruebas_Auditoria!M155,3)="[E]","[E] [B]","[P]")) -> [P]
D76: Subtotal | E76: =SUM(E68:E75) -> 17282932453 | F76: =SUM(F68:F75) -> 1.7065824e+10 | G76: =SUM(G68:G75) -> 1.7065824e+10 | H76: =SUM(H68:H75) -> 1.7069062e+10 | I76: =SUM(I68:I75) -> 8521.8 | N76: =SUM(N68:N75) -> 1391910513 | O76: =SUM(O68:O75) -> 372400000 | P76: =SUM(P68:P75) -> 4.2183663e+08
C78: Banco De Bogota
C79: N° obligación (ID) | D79: Descripción | E79: Saldo mayor 31-jul | F79: Saldo detalle 62 | G79: Saldo tabla amort. | H79: Saldo extracto/banco | I79: Dif. mayor − banco | J79: Tipo tasa | K79: Frecuencia | L79: Fecha venc. | M79: Tasa EA banco | N79: Intereses 2026 registrados | O79: Int. por pagar 2130 | P79: Causación recalc. 31-jul | Q79: Marca
C80: BOG-453436746 | D80: =Pruebas_Auditoria!D156 -> 453436746 – CRED TESORERIA | E80: =Pruebas_Auditoria!H156 -> 2937500000 | F80: =Pruebas_Auditoria!I156 -> 2937500000 | G80: =Pruebas_Auditoria!J156 -> 2937500000 | H80: =Pruebas_Auditoria!L156 -> 2.9375e+09 | I80: =Pruebas_Auditoria!O156 -> 22.61 | J80: =IFERROR(INDEX(Detalle_62!$H$14:$H$35,MATCH(C80,Detalle_62!$C$14:$C$35,0)),"—") -> IBR | K80: =IFERROR(INDEX(Detalle_62!$L$14:$L$35,MATCH(C80,Detalle_62!$C$14:$C$35,0)),"—") -> MENSUAL | L80: =IFERROR(INDEX(Detalle_62!$P$14:$P$35,MATCH(C80,Detalle_62!$C$14:$C$35,0)),"—") -> 47651 | M80: =IFERROR(INDEX(Pruebas_Auditoria!$M$53:$M$137,MATCH(C80,Pruebas_Auditoria!$E$53:$E$137,0)),"—") -> 0.1696 | N80: =INDEX(Intereses_x_Obligacion!$I:$I,MATCH(C80,Intereses_x_Obligacion!$A:$A,0)) -> 2.3229766e+08 | O80: =INDEX(Intereses_x_Obligacion!$F:$F,MATCH(C80,Intereses_x_Obligacion!$A:$A,0)) -> 0 | P80: =INDEX(Intereses_x_Obligacion!$L:$L,MATCH(C80,Intereses_x_Obligacion!$A:$A,0)) -> 17704418 | Q80: =IF(LEFT(Pruebas_Auditoria!M156,3)="[C]","[C] [B]",IF(LEFT(Pruebas_Auditoria!M156,3)="[E]","[E] [B]","[P]")) -> [C] [B]
C81: BOG-856670629 | D81: =Pruebas_Auditoria!D157 -> 856670629 – CRED TESORERIA | E81: =Pruebas_Auditoria!H157 -> 1457333332 | F81: =Pruebas_Auditoria!I157 -> 1457333332 | G81: =Pruebas_Auditoria!J157 -> 1457333336 | H81: =Pruebas_Auditoria!L157 -> 1.4573333e+09 | I81: =Pruebas_Auditoria!O157 -> 6.4100001 | J81: =IFERROR(INDEX(Detalle_62!$H$14:$H$35,MATCH(C81,Detalle_62!$C$14:$C$35,0)),"—") -> IBR 3 MESES | K81: =IFERROR(INDEX(Detalle_62!$L$14:$L$35,MATCH(C81,Detalle_62!$C$14:$C$35,0)),"—") -> TRIMESTRAL | L81: =IFERROR(INDEX(Detalle_62!$P$14:$P$35,MATCH(C81,Detalle_62!$C$14:$C$35,0)),"—") -> 46925 | M81: =IFERROR(INDEX(Pruebas_Auditoria!$M$53:$M$137,MATCH(C81,Pruebas_Auditoria!$E$53:$E$137,0)),"—") -> 0.1494 | N81: =INDEX(Intereses_x_Obligacion!$I:$I,MATCH(C81,Intereses_x_Obligacion!$A:$A,0)) -> 133305619 | O81: =INDEX(Intereses_x_Obligacion!$F:$F,MATCH(C81,Intereses_x_Obligacion!$A:$A,0)) -> 17825616 | P81: =INDEX(Intereses_x_Obligacion!$L:$L,MATCH(C81,Intereses_x_Obligacion!$A:$A,0)) -> 22721890 | Q81: =IF(LEFT(Pruebas_Auditoria!M157,3)="[C]","[C] [B]",IF(LEFT(Pruebas_Auditoria!M157,3)="[E]","[E] [B]","[P]")) -> [C] [B]
C82: BOG-858177259 | D82: =Pruebas_Auditoria!D158 -> 858177259 – CRED TESORERIA | E82: =Pruebas_Auditoria!H158 -> 1125000000 | F82: =Pruebas_Auditoria!I158 -> 1125000000 | G82: =Pruebas_Auditoria!J158 -> 1125000000 | H82: =Pruebas_Auditoria!L158 -> 1.125e+09 | I82: =Pruebas_Auditoria!O158 -> 3.5899999 | J82: =IFERROR(INDEX(Detalle_62!$H$14:$H$35,MATCH(C82,Detalle_62!$C$14:$C$35,0)),"—") -> IBR 3 MESES | K82: =IFERROR(INDEX(Detalle_62!$L$14:$L$35,MATCH(C82,Detalle_62!$C$14:$C$35,0)),"—") -> TRIMESTRAL | L82: =IFERROR(INDEX(Detalle_62!$P$14:$P$35,MATCH(C82,Detalle_62!$C$14:$C$35,0)),"—") -> 46990 | M82: =IFERROR(INDEX(Pruebas_Auditoria!$M$53:$M$137,MATCH(C82,Pruebas_Auditoria!$E$53:$E$137,0)),"—") -> 0.1665 | N82: =INDEX(Intereses_x_Obligacion!$I:$I,MATCH(C82,Intereses_x_Obligacion!$A:$A,0)) -> 108941341 | O82: =INDEX(Intereses_x_Obligacion!$F:$F,MATCH(C82,Intereses_x_Obligacion!$A:$A,0)) -> 30088126 | P82: =INDEX(Intereses_x_Obligacion!$L:$L,MATCH(C82,Intereses_x_Obligacion!$A:$A,0)) -> 32711950 | Q82: =IF(LEFT(Pruebas_Auditoria!M158,3)="[C]","[C] [B]",IF(LEFT(Pruebas_Auditoria!M158,3)="[E]","[E] [B]","[P]")) -> [C] [B]
C83: BOG-1159383796 | D83: =Pruebas_Auditoria!D159 -> Crédito 1155297469 → prorrogado 1159383796 | E83: =Pruebas_Auditoria!H159 -> 10000000000 | F83: =Pruebas_Auditoria!I159 -> 10000000000 | G83: =Pruebas_Auditoria!J159 -> 10000000000 | H83: =Pruebas_Auditoria!L159 -> 10000000000 | I83: =Pruebas_Auditoria!O159 -> 0 | J83: =IFERROR(INDEX(Detalle_62!$H$14:$H$35,MATCH(C83,Detalle_62!$C$14:$C$35,0)),"—") -> IBR 3 MESES | K83: =IFERROR(INDEX(Detalle_62!$L$14:$L$35,MATCH(C83,Detalle_62!$C$14:$C$35,0)),"—") -> SEMESTRAL | L83: =IFERROR(INDEX(Detalle_62!$P$14:$P$35,MATCH(C83,Detalle_62!$C$14:$C$35,0)),"—") -> 46409 | M83: =IFERROR(INDEX(Pruebas_Auditoria!$M$53:$M$137,MATCH(C83,Pruebas_Auditoria!$E$53:$E$137,0)),"—") -> 0.1239 | N83: =INDEX(Intereses_x_Obligacion!$I:$I,MATCH(C83,Intereses_x_Obligacion!$A:$A,0)) -> 554228055 | O83: =INDEX(Intereses_x_Obligacion!$F:$F,MATCH(C83,Intereses_x_Obligacion!$A:$A,0)) -> 0 | P83: =INDEX(Intereses_x_Obligacion!$L:$L,MATCH(C83,Intereses_x_Obligacion!$A:$A,0)) -> 30518761 | Q83: =IF(LEFT(Pruebas_Auditoria!M159,3)="[C]","[C] [B]",IF(LEFT(Pruebas_Auditoria!M159,3)="[E]","[E] [B]","[P]")) -> [C] [B]
C84: BOG-L556449224 | D84: =Pruebas_Auditoria!D160 -> LEASING 556449224 – POZO # 1 | E84: =Pruebas_Auditoria!H160 -> 3.9611203e+08 | F84: =Pruebas_Auditoria!I160 -> 3.8184539e+08 | G84: =Pruebas_Auditoria!J160 -> 3.8184539e+08 | H84: =Pruebas_Auditoria!L160 -> 3.9611203e+08 | I84: =Pruebas_Auditoria!O160 -> 0.32999998 | J84: =IFERROR(INDEX(Detalle_62!$H$14:$H$35,MATCH(C84,Detalle_62!$C$14:$C$35,0)),"—") -> DTF | K84: =IFERROR(INDEX(Detalle_62!$L$14:$L$35,MATCH(C84,Detalle_62!$C$14:$C$35,0)),"—") -> TRIMESTRAL | L84: =IFERROR(INDEX(Detalle_62!$P$14:$P$35,MATCH(C84,Detalle_62!$C$14:$C$35,0)),"—") -> 47503 | M84: =IFERROR(INDEX(Pruebas_Auditoria!$M$53:$M$137,MATCH(C84,Pruebas_Auditoria!$E$53:$E$137,0)),"—") -> 0.1422 | N84: =INDEX(Intereses_x_Obligacion!$I:$I,MATCH(C84,Intereses_x_Obligacion!$A:$A,0)) -> 31068671 | O84: =INDEX(Intereses_x_Obligacion!$F:$F,MATCH(C84,Intereses_x_Obligacion!$A:$A,0)) -> 0 | P84: =INDEX(Intereses_x_Obligacion!$L:$L,MATCH(C84,Intereses_x_Obligacion!$A:$A,0)) -> 1155997.2 | Q84: =IF(LEFT(Pruebas_Auditoria!M160,3)="[C]","[C] [B]",IF(LEFT(Pruebas_Auditoria!M160,3)="[E]","[E] [B]","[P]")) -> [C] [B]
C85: BOG-L556449180 | D85: =Pruebas_Auditoria!D161 -> LEASING 556449180 – POZO # 2 | E85: =Pruebas_Auditoria!H161 -> 3.9611203e+08 | F85: =Pruebas_Auditoria!I161 -> 3.8184539e+08 | G85: =Pruebas_Auditoria!J161 -> 3.8184539e+08 | H85: =Pruebas_Auditoria!L161 -> 3.9611203e+08 | I85: =Pruebas_Auditoria!O161 -> 0.21999997 | J85: =IFERROR(INDEX(Detalle_62!$H$14:$H$35,MATCH(C85,Detalle_62!$C$14:$C$35,0)),"—") -> DTF | K85: =IFERROR(INDEX(Detalle_62!$L$14:$L$35,MATCH(C85,Detalle_62!$C$14:$C$35,0)),"—") -> TRIMESTRAL | L85: =IFERROR(INDEX(Detalle_62!$P$14:$P$35,MATCH(C85,Detalle_62!$C$14:$C$35,0)),"—") -> 47503 | M85: =IFERROR(INDEX(Pruebas_Auditoria!$M$53:$M$137,MATCH(C85,Pruebas_Auditoria!$E$53:$E$137,0)),"—") -> 0.1422 | N85: =INDEX(Intereses_x_Obligacion!$I:$I,MATCH(C85,Intereses_x_Obligacion!$A:$A,0)) -> 31068672 | O85: =INDEX(Intereses_x_Obligacion!$F:$F,MATCH(C85,Intereses_x_Obligacion!$A:$A,0)) -> 0 | P85: =INDEX(Intereses_x_Obligacion!$L:$L,MATCH(C85,Intereses_x_Obligacion!$A:$A,0)) -> 1155997.2 | Q85: =IF(LEFT(Pruebas_Auditoria!M161,3)="[C]","[C] [B]",IF(LEFT(Pruebas_Auditoria!M161,3)="[E]","[E] [B]","[P]")) -> [C] [B]
C86: BOG-L556449117 | D86: =Pruebas_Auditoria!D162 -> LEASING 556449117 – POZO # 3 | E86: =Pruebas_Auditoria!H162 -> 2.536721e+08 | F86: =Pruebas_Auditoria!I162 -> 1.9672018e+08 | G86: =Pruebas_Auditoria!J162 -> 1.9672018e+08 | H86: =Pruebas_Auditoria!L162 -> 2.5367211e+08 | I86: =Pruebas_Auditoria!O162 -> -0.060000032 | J86: =IFERROR(INDEX(Detalle_62!$H$14:$H$35,MATCH(C86,Detalle_62!$C$14:$C$35,0)),"—") -> DTF | K86: =IFERROR(INDEX(Detalle_62!$L$14:$L$35,MATCH(C86,Detalle_62!$C$14:$C$35,0)),"—") -> TRIMESTRAL | L86: =IFERROR(INDEX(Detalle_62!$P$14:$P$35,MATCH(C86,Detalle_62!$C$14:$C$35,0)),"—") -> 46870 | M86: =IFERROR(INDEX(Pruebas_Auditoria!$M$53:$M$137,MATCH(C86,Pruebas_Auditoria!$E$53:$E$137,0)),"—") -> 0.1425 | N86: =INDEX(Intereses_x_Obligacion!$I:$I,MATCH(C86,Intereses_x_Obligacion!$A:$A,0)) -> 28058555 | O86: =INDEX(Intereses_x_Obligacion!$F:$F,MATCH(C86,Intereses_x_Obligacion!$A:$A,0)) -> 0 | P86: =INDEX(Intereses_x_Obligacion!$L:$L,MATCH(C86,Intereses_x_Obligacion!$A:$A,0)) -> 370614.63 | Q86: =IF(LEFT(Pruebas_Auditoria!M162,3)="[C]","[C] [B]",IF(LEFT(Pruebas_Auditoria!M162,3)="[E]","[E] [B]","[P]")) -> [C] [B]
C87: BOG-L556449064 | D87: =Pruebas_Auditoria!D163 -> LEASING 556449064 – POZO # 4 | E87: =Pruebas_Auditoria!H163 -> 2.536721e+08 | F87: =Pruebas_Auditoria!I163 -> 1.9672018e+08 | G87: =Pruebas_Auditoria!J163 -> 1.9672018e+08 | H87: =Pruebas_Auditoria!L163 -> 2.536721e+08 | I87: =Pruebas_Auditoria!O163 -> -0.78000003 | J87: =IFERROR(INDEX(Detalle_62!$H$14:$H$35,MATCH(C87,Detalle_62!$C$14:$C$35,0)),"—") -> DTF | K87: =IFERROR(INDEX(Detalle_62!$L$14:$L$35,MATCH(C87,Detalle_62!$C$14:$C$35,0)),"—") -> TRIMESTRAL | L87: =IFERROR(INDEX(Detalle_62!$P$14:$P$35,MATCH(C87,Detalle_62!$C$14:$C$35,0)),"—") -> 46870 | M87: =IFERROR(INDEX(Pruebas_Auditoria!$M$53:$M$137,MATCH(C87,Pruebas_Auditoria!$E$53:$E$137,0)),"—") -> 0.1425 | N87: =INDEX(Intereses_x_Obligacion!$I:$I,MATCH(C87,Intereses_x_Obligacion!$A:$A,0)) -> 28058555 | O87: =INDEX(Intereses_x_Obligacion!$F:$F,MATCH(C87,Intereses_x_Obligacion!$A:$A,0)) -> 0 | P87: =INDEX(Intereses_x_Obligacion!$L:$L,MATCH(C87,Intereses_x_Obligacion!$A:$A,0)) -> 370614.63 | Q87: =IF(LEFT(Pruebas_Auditoria!M163,3)="[C]","[C] [B]",IF(LEFT(Pruebas_Auditoria!M163,3)="[E]","[E] [B]","[P]")) -> [C] [B]
C88: BOG-L556449288 | D88: =Pruebas_Auditoria!D164 -> LEASING 556449288 – POZO # 5 | E88: =Pruebas_Auditoria!H164 -> 3.9619394e+08 | F88: =Pruebas_Auditoria!I164 -> 3.8264924e+08 | G88: =Pruebas_Auditoria!J164 -> 3.8264924e+08 | H88: =Pruebas_Auditoria!L164 -> 3.9619394e+08 | I88: =Pruebas_Auditoria!O164 -> 1.32 | J88: =IFERROR(INDEX(Detalle_62!$H$14:$H$35,MATCH(C88,Detalle_62!$C$14:$C$35,0)),"—") -> DTF | K88: =IFERROR(INDEX(Detalle_62!$L$14:$L$35,MATCH(C88,Detalle_62!$C$14:$C$35,0)),"—") -> TRIMESTRAL | L88: =IFERROR(INDEX(Detalle_62!$P$14:$P$35,MATCH(C88,Detalle_62!$C$14:$C$35,0)),"—") -> 47503 | M88: =IFERROR(INDEX(Pruebas_Auditoria!$M$53:$M$137,MATCH(C88,Pruebas_Auditoria!$E$53:$E$137,0)),"—") -> 0.1422 | N88: =INDEX(Intereses_x_Obligacion!$I:$I,MATCH(C88,Intereses_x_Obligacion!$A:$A,0)) -> 30902950 | O88: =INDEX(Intereses_x_Obligacion!$F:$F,MATCH(C88,Intereses_x_Obligacion!$A:$A,0)) -> 0.16 | P88: =INDEX(Intereses_x_Obligacion!$L:$L,MATCH(C88,Intereses_x_Obligacion!$A:$A,0)) -> 1590694.3 | Q88: =IF(LEFT(Pruebas_Auditoria!M164,3)="[C]","[C] [B]",IF(LEFT(Pruebas_Auditoria!M164,3)="[E]","[E] [B]","[P]")) -> [C] [B]
C89: BOG-L557285005 | D89: =Pruebas_Auditoria!D165 -> LEASING 557285005 – PLANTA ELECTRICA JENBACHER | E89: =Pruebas_Auditoria!H165 -> 9.8424689e+08 | F89: =Pruebas_Auditoria!I165 -> 9.6862047e+08 | G89: =Pruebas_Auditoria!J165 -> 9.6862047e+08 | H89: =Pruebas_Auditoria!L165 -> 9.8424689e+08 | I89: =Pruebas_Auditoria!O165 -> 0.30000019 | J89: =IFERROR(INDEX(Detalle_62!$H$14:$H$35,MATCH(C89,Detalle_62!$C$14:$C$35,0)),"—") -> IBR 3 MESES | K89: =IFERROR(INDEX(Detalle_62!$L$14:$L$35,MATCH(C89,Detalle_62!$C$14:$C$35,0)),"—") -> TRIMESTRAL | L89: =IFERROR(INDEX(Detalle_62!$P$14:$P$35,MATCH(C89,Detalle_62!$C$14:$C$35,0)),"—") -> 47321 | M89: =IFERROR(INDEX(Pruebas_Auditoria!$M$53:$M$137,MATCH(C89,Pruebas_Auditoria!$E$53:$E$137,0)),"—") -> 0.1604 | N89: =INDEX(Intereses_x_Obligacion!$I:$I,MATCH(C89,Intereses_x_Obligacion!$A:$A,0)) -> 89512386 | O89: =INDEX(Intereses_x_Obligacion!$F:$F,MATCH(C89,Intereses_x_Obligacion!$A:$A,0)) -> 0 | P89: =INDEX(Intereses_x_Obligacion!$L:$L,MATCH(C89,Intereses_x_Obligacion!$A:$A,0)) -> 3617017.2 | Q89: =IF(LEFT(Pruebas_Auditoria!M165,3)="[C]","[C] [B]",IF(LEFT(Pruebas_Auditoria!M165,3)="[E]","[E] [B]","[P]")) -> [C] [B]
D90: Subtotal | E90: =SUM(E80:E89) -> 1.8199842e+10 | F90: =SUM(F80:F89) -> 1.8028234e+10 | G90: =SUM(G80:G89) -> 1.8028234e+10 | H90: =SUM(H80:H89) -> 1.8199842e+10 | I90: =SUM(I80:I89) -> 33.94 | N90: =SUM(N80:N89) -> 1.2674425e+09 | O90: =SUM(O80:O89) -> 47913742 | P90: =SUM(P80:P89) -> 1.1191795e+08
C92: Banco Popular
C93: N° obligación (ID) | D93: Descripción | E93: Saldo mayor 31-jul | F93: Saldo detalle 62 | G93: Saldo tabla amort. | H93: Saldo extracto/banco | I93: Dif. mayor − banco | J93: Tipo tasa | K93: Frecuencia | L93: Fecha venc. | M93: Tasa EA banco | N93: Intereses 2026 registrados | O93: Int. por pagar 2130 | P93: Causación recalc. 31-jul | Q93: Marca
C94: POP-631309940 | D94: =Pruebas_Auditoria!D166 -> 631309940-2 – CRED TESORERIA | E94: =Pruebas_Auditoria!H166 -> 287500000 | F94: =Pruebas_Auditoria!I166 -> 287500000 | G94: =Pruebas_Auditoria!J166 -> 287500000 | H94: =Pruebas_Auditoria!L166 -> 287500000 | I94: =Pruebas_Auditoria!O166 -> 0 | J94: =IFERROR(INDEX(Detalle_62!$H$14:$H$35,MATCH(C94,Detalle_62!$C$14:$C$35,0)),"—") -> IBR 3 MESES | K94: =IFERROR(INDEX(Detalle_62!$L$14:$L$35,MATCH(C94,Detalle_62!$C$14:$C$35,0)),"—") -> TRIMESTRAL | L94: =IFERROR(INDEX(Detalle_62!$P$14:$P$35,MATCH(C94,Detalle_62!$C$14:$C$35,0)),"—") -> 46373 | M94: =IFERROR(INDEX(Pruebas_Auditoria!$M$53:$M$137,MATCH(C94,Pruebas_Auditoria!$E$53:$E$137,0)),"—") -> 0 | N94: =INDEX(Intereses_x_Obligacion!$I:$I,MATCH(C94,Intereses_x_Obligacion!$A:$A,0)) -> 34304862 | O94: =INDEX(Intereses_x_Obligacion!$F:$F,MATCH(C94,Intereses_x_Obligacion!$A:$A,0)) -> 3324939 | P94: =INDEX(Intereses_x_Obligacion!$L:$L,MATCH(C94,Intereses_x_Obligacion!$A:$A,0)) -> 4866039.7 | Q94: =IF(LEFT(Pruebas_Auditoria!M166,3)="[C]","[C] [B]",IF(LEFT(Pruebas_Auditoria!M166,3)="[E]","[E] [B]","[P]")) -> [E] [B]
D95: Subtotal | E95: =SUM(E94:E94) -> 287500000 | F95: =SUM(F94:F94) -> 287500000 | G95: =SUM(G94:G94) -> 287500000 | H95: =SUM(H94:H94) -> 287500000 | I95: =SUM(I94:I94) -> 0 | N95: =SUM(N94:N94) -> 34304862 | O95: =SUM(O94:O94) -> 3324939 | P95: =SUM(P94:P94) -> 4866039.7
C97: Bbva
C98: N° obligación (ID) | D98: Descripción | E98: Saldo mayor 31-jul | F98: Saldo detalle 62 | G98: Saldo tabla amort. | H98: Saldo extracto/banco | I98: Dif. mayor − banco | J98: Tipo tasa | K98: Frecuencia | L98: Fecha venc. | M98: Tasa EA banco | N98: Intereses 2026 registrados | O98: Int. por pagar 2130 | P98: Causación recalc. 31-jul | Q98: Marca
C99: BBVA-0141 | D99: =Pruebas_Auditoria!D167 -> 252059 – CRED TESORERIA | E99: =Pruebas_Auditoria!H167 -> 4700000000 | F99: =Pruebas_Auditoria!I167 -> 4700000000 | G99: =Pruebas_Auditoria!J167 -> Sin tabla | H99: =Pruebas_Auditoria!L167 -> 4700000000 | I99: =Pruebas_Auditoria!O167 -> 0 | J99: =IFERROR(INDEX(Detalle_62!$H$14:$H$35,MATCH(C99,Detalle_62!$C$14:$C$35,0)),"—") -> IBR 6 MESES/tri INT | K99: =IFERROR(INDEX(Detalle_62!$L$14:$L$35,MATCH(C99,Detalle_62!$C$14:$C$35,0)),"—") -> SEMESTRAL | L99: =IFERROR(INDEX(Detalle_62!$P$14:$P$35,MATCH(C99,Detalle_62!$C$14:$C$35,0)),"—") -> 46367 | M99: =IFERROR(INDEX(Pruebas_Auditoria!$M$53:$M$137,MATCH(C99,Pruebas_Auditoria!$E$53:$E$137,0)),"—") -> 0 | N99: =INDEX(Intereses_x_Obligacion!$I:$I,MATCH(C99,Intereses_x_Obligacion!$A:$A,0)) -> 258396078 | O99: =INDEX(Intereses_x_Obligacion!$F:$F,MATCH(C99,Intereses_x_Obligacion!$A:$A,0)) -> 0.22 | P99: =INDEX(Intereses_x_Obligacion!$L:$L,MATCH(C99,Intereses_x_Obligacion!$A:$A,0)) -> 50972240 | Q99: =IF(LEFT(Pruebas_Auditoria!M167,3)="[C]","[C] [B]",IF(LEFT(Pruebas_Auditoria!M167,3)="[E]","[E] [B]","[P]")) -> [E] [B]
D100: Subtotal | E100: =SUM(E99:E99) -> 4700000000 | F100: =SUM(F99:F99) -> 4700000000 | G100: =SUM(G99:G99) -> 0 | H100: =SUM(H99:H99) -> 4700000000 | I100: =SUM(I99:I99) -> 0 | N100: =SUM(N99:N99) -> 258396078 | O100: =SUM(O99:O99) -> 0.22 | P100: =SUM(P99:P99) -> 50972240
C102: Bancolombia S.A.
C103: N° obligación (ID) | D103: Descripción | E103: Saldo mayor 31-jul | F103: Saldo detalle 62 | G103: Saldo tabla amort. | H103: Saldo extracto/banco | I103: Dif. mayor − banco | J103: Tipo tasa | K103: Frecuencia | L103: Fecha venc. | M103: Tasa EA banco | N103: Intereses 2026 registrados | O103: Int. por pagar 2130 | P103: Causación recalc. 31-jul | Q103: Marca
C104: BCL-1260105867 | D104: =Pruebas_Auditoria!D168 -> 1260105867 – CAPITAL DE TRABAJO | E104: =Pruebas_Auditoria!H168 -> 3333333334 | F104: =Pruebas_Auditoria!I168 -> 3.3333333e+09 | G104: =Pruebas_Auditoria!J168 -> 3.3333333e+09 | H104: =Pruebas_Auditoria!L168 -> 3333333334 | I104: =Pruebas_Auditoria!O168 -> 0 | J104: =IFERROR(INDEX(Detalle_62!$H$14:$H$35,MATCH(C104,Detalle_62!$C$14:$C$35,0)),"—") -> IBR 3 MESES | K104: =IFERROR(INDEX(Detalle_62!$L$14:$L$35,MATCH(C104,Detalle_62!$C$14:$C$35,0)),"—") -> TRIMESTRAL | L104: =IFERROR(INDEX(Detalle_62!$P$14:$P$35,MATCH(C104,Detalle_62!$C$14:$C$35,0)),"—") -> 46864 | M104: =IFERROR(INDEX(Pruebas_Auditoria!$M$53:$M$137,MATCH(C104,Pruebas_Auditoria!$E$53:$E$137,0)),"—") -> 0.1417 | N104: =INDEX(Intereses_x_Obligacion!$I:$I,MATCH(C104,Intereses_x_Obligacion!$A:$A,0)) -> 287833704 | O104: =INDEX(Intereses_x_Obligacion!$F:$F,MATCH(C104,Intereses_x_Obligacion!$A:$A,0)) -> 0 | P104: =INDEX(Intereses_x_Obligacion!$L:$L,MATCH(C104,Intereses_x_Obligacion!$A:$A,0)) -> 10909736 | Q104: =IF(LEFT(Pruebas_Auditoria!M168,3)="[C]","[C] [B]",IF(LEFT(Pruebas_Auditoria!M168,3)="[E]","[E] [B]","[P]")) -> [C] [B]
C105: BCL-L362095 | D105: =Pruebas_Auditoria!D169 -> LEASING 362095 – EXCAVADORA PC130-8 KOMATSU | E105: =Pruebas_Auditoria!H169 -> 448477372 | F105: =Pruebas_Auditoria!I169 -> 497241599 | G105: =Pruebas_Auditoria!J169 -> 5.2451929e+08 | H105: =Pruebas_Auditoria!L169 -> 448477372 | I105: =Pruebas_Auditoria!O169 -> 0 | J105: =IFERROR(INDEX(Detalle_62!$H$14:$H$35,MATCH(C105,Detalle_62!$C$14:$C$35,0)),"—") -> IBR 3 MESES | K105: =IFERROR(INDEX(Detalle_62!$L$14:$L$35,MATCH(C105,Detalle_62!$C$14:$C$35,0)),"—") -> TRIMESTRAL | L105: =IFERROR(INDEX(Detalle_62!$P$14:$P$35,MATCH(C105,Detalle_62!$C$14:$C$35,0)),"—") -> 47528 | M105: =IFERROR(INDEX(Pruebas_Auditoria!$M$53:$M$137,MATCH(C105,Pruebas_Auditoria!$E$53:$E$137,0)),"—") -> 0 | N105: =INDEX(Intereses_x_Obligacion!$I:$I,MATCH(C105,Intereses_x_Obligacion!$A:$A,0)) -> 32199918 | O105: =INDEX(Intereses_x_Obligacion!$F:$F,MATCH(C105,Intereses_x_Obligacion!$A:$A,0)) -> 3750337 | P105: =INDEX(Intereses_x_Obligacion!$L:$L,MATCH(C105,Intereses_x_Obligacion!$A:$A,0)) -> 5568623.4 | Q105: =IF(LEFT(Pruebas_Auditoria!M169,3)="[C]","[C] [B]",IF(LEFT(Pruebas_Auditoria!M169,3)="[E]","[E] [B]","[P]")) -> [E] [B]
C106: BCL-L336817 | D106: =Pruebas_Auditoria!D170 -> LEASING 336817 – TURBINA - TURBOKRAFT | E106: =Pruebas_Auditoria!H170 -> 787729700 | F106: =Pruebas_Auditoria!I170 -> 7.7008543e+08 | G106: =Pruebas_Auditoria!J170 -> 7.7008543e+08 | H106: =Pruebas_Auditoria!L170 -> 787729700 | I106: =Pruebas_Auditoria!O170 -> 0 | J106: =IFERROR(INDEX(Detalle_62!$H$14:$H$35,MATCH(C106,Detalle_62!$C$14:$C$35,0)),"—") -> IBR | K106: =IFERROR(INDEX(Detalle_62!$L$14:$L$35,MATCH(C106,Detalle_62!$C$14:$C$35,0)),"—") -> MENSUAL | L106: =IFERROR(INDEX(Detalle_62!$P$14:$P$35,MATCH(C106,Detalle_62!$C$14:$C$35,0)),"—") -> 47995 | M106: =IFERROR(INDEX(Pruebas_Auditoria!$M$53:$M$137,MATCH(C106,Pruebas_Auditoria!$E$53:$E$137,0)),"—") -> 0 | N106: =INDEX(Intereses_x_Obligacion!$I:$I,MATCH(C106,Intereses_x_Obligacion!$A:$A,0)) -> 28583500 | O106: =INDEX(Intereses_x_Obligacion!$F:$F,MATCH(C106,Intereses_x_Obligacion!$A:$A,0)) -> 0 | P106: =INDEX(Intereses_x_Obligacion!$L:$L,MATCH(C106,Intereses_x_Obligacion!$A:$A,0)) -> 3807112.9 | Q106: =IF(LEFT(Pruebas_Auditoria!M170,3)="[C]","[C] [B]",IF(LEFT(Pruebas_Auditoria!M170,3)="[E]","[E] [B]","[P]")) -> [E] [B]
C107: BCL-L331330 | D107: =Pruebas_Auditoria!D171 -> LEASING 331330 – PLANTA ELECTRICA CATERPILLAR C32-910 | E107: =Pruebas_Auditoria!H171 -> 488525504 | F107: =Pruebas_Auditoria!I171 -> 503693510 | G107: =Pruebas_Auditoria!J171 -> 503693510 | H107: =Pruebas_Auditoria!L171 -> 488525504 | I107: =Pruebas_Auditoria!O171 -> 0 | J107: =IFERROR(INDEX(Detalle_62!$H$14:$H$35,MATCH(C107,Detalle_62!$C$14:$C$35,0)),"—") -> IBR | K107: =IFERROR(INDEX(Detalle_62!$L$14:$L$35,MATCH(C107,Detalle_62!$C$14:$C$35,0)),"—") -> MENSUAL | L107: =IFERROR(INDEX(Detalle_62!$P$14:$P$35,MATCH(C107,Detalle_62!$C$14:$C$35,0)),"—") -> 46960 | M107: =IFERROR(INDEX(Pruebas_Auditoria!$M$53:$M$137,MATCH(C107,Pruebas_Auditoria!$E$53:$E$137,0)),"—") -> 0 | N107: =INDEX(Intereses_x_Obligacion!$I:$I,MATCH(C107,Intereses_x_Obligacion!$A:$A,0)) -> 26060708 | O107: =INDEX(Intereses_x_Obligacion!$F:$F,MATCH(C107,Intereses_x_Obligacion!$A:$A,0)) -> 0 | P107: =INDEX(Intereses_x_Obligacion!$L:$L,MATCH(C107,Intereses_x_Obligacion!$A:$A,0)) -> 4498704.7 | Q107: =IF(LEFT(Pruebas_Auditoria!M171,3)="[C]","[C] [B]",IF(LEFT(Pruebas_Auditoria!M171,3)="[E]","[E] [B]","[P]")) -> [E] [B]
C108: BCL-L386735 | D108: =Pruebas_Auditoria!D172 -> Leasing 386735 camión VW Constellation (nuevo 28-jul-26) | E108: =Pruebas_Auditoria!H172 -> 675837500 | F108: =Pruebas_Auditoria!I172 -> 0 | G108: =Pruebas_Auditoria!J172 -> Sin tabla | H108: =Pruebas_Auditoria!L172 -> N/D | I108: =Pruebas_Auditoria!O172 -> N/D | J108: =IFERROR(INDEX(Detalle_62!$H$14:$H$35,MATCH(C108,Detalle_62!$C$14:$C$35,0)),"—") -> — | K108: =IFERROR(INDEX(Detalle_62!$L$14:$L$35,MATCH(C108,Detalle_62!$C$14:$C$35,0)),"—") -> — | L108: =IFERROR(INDEX(Detalle_62!$P$14:$P$35,MATCH(C108,Detalle_62!$C$14:$C$35,0)),"—") -> — | M108: =IFERROR(INDEX(Pruebas_Auditoria!$M$53:$M$137,MATCH(C108,Pruebas_Auditoria!$E$53:$E$137,0)),"—") -> 0 | N108: =INDEX(Intereses_x_Obligacion!$I:$I,MATCH(C108,Intereses_x_Obligacion!$A:$A,0)) -> 0 | O108: =INDEX(Intereses_x_Obligacion!$F:$F,MATCH(C108,Intereses_x_Obligacion!$A:$A,0)) -> 0 | P108: =INDEX(Intereses_x_Obligacion!$L:$L,MATCH(C108,Intereses_x_Obligacion!$A:$A,0)) -> 717369.3 | Q108: =IF(LEFT(Pruebas_Auditoria!M172,3)="[C]","[C] [B]",IF(LEFT(Pruebas_Auditoria!M172,3)="[E]","[E] [B]","[P]")) -> [P]
D109: Subtotal | E109: =SUM(E104:E108) -> 5733903410 | F109: =SUM(F104:F108) -> 5.1043539e+09 | G109: =SUM(G104:G108) -> 5.1316316e+09 | H109: =SUM(H104:H108) -> 5058065910 | I109: =SUM(I104:I108) -> 0 | N109: =SUM(N104:N108) -> 374677830 | O109: =SUM(O104:O108) -> 3750337 | P109: =SUM(P104:P108) -> 25501546
C111: Partidas Ajenas En 2120 (Neto Cero)
C112: N° obligación (ID) | D112: Descripción | E112: Saldo mayor 31-jul | F112: Saldo detalle 62 | G112: Saldo tabla amort. | H112: Saldo extracto/banco | I112: Dif. mayor − banco | J112: Tipo tasa | K112: Frecuencia | L112: Fecha venc. | M112: Tasa EA banco | N112: Intereses 2026 registrados | O112: Int. por pagar 2130 | P112: Causación recalc. 31-jul | Q112: Marca
C113: N/A-COMISION | D113: =Pruebas_Auditoria!D173 -> Comisiones Valley Trading registradas y reclasificadas en 21202040 | E113: =Pruebas_Auditoria!H173 -> 0 | F113: =Pruebas_Auditoria!I173 -> 0 | G113: =Pruebas_Auditoria!J173 -> Sin tabla | H113: =Pruebas_Auditoria!L173 -> N/D | I113: =Pruebas_Auditoria!O173 -> N/D | J113: =IFERROR(INDEX(Detalle_62!$H$14:$H$35,MATCH(C113,Detalle_62!$C$14:$C$35,0)),"—") -> — | K113: =IFERROR(INDEX(Detalle_62!$L$14:$L$35,MATCH(C113,Detalle_62!$C$14:$C$35,0)),"—") -> — | L113: =IFERROR(INDEX(Detalle_62!$P$14:$P$35,MATCH(C113,Detalle_62!$C$14:$C$35,0)),"—") -> — | M113: =IFERROR(INDEX(Pruebas_Auditoria!$M$53:$M$137,MATCH(C113,Pruebas_Auditoria!$E$53:$E$137,0)),"—") -> — | N113: =INDEX(Intereses_x_Obligacion!$I:$I,MATCH(C113,Intereses_x_Obligacion!$A:$A,0)) -> 0 | O113: =INDEX(Intereses_x_Obligacion!$F:$F,MATCH(C113,Intereses_x_Obligacion!$A:$A,0)) -> 0 | P113: =INDEX(Intereses_x_Obligacion!$L:$L,MATCH(C113,Intereses_x_Obligacion!$A:$A,0)) -> 0 | Q113: =IF(LEFT(Pruebas_Auditoria!M173,3)="[C]","[C] [B]",IF(LEFT(Pruebas_Auditoria!M173,3)="[E]","[E] [B]","[P]")) -> [P]
C114: N/A-CRUCE | D114: =Pruebas_Auditoria!D174 -> NI-4731 cruce anticipo calderas en 21202140 | E114: =Pruebas_Auditoria!H174 -> 0 | F114: =Pruebas_Auditoria!I174 -> 0 | G114: =Pruebas_Auditoria!J174 -> Sin tabla | H114: =Pruebas_Auditoria!L174 -> N/D | I114: =Pruebas_Auditoria!O174 -> N/D | J114: =IFERROR(INDEX(Detalle_62!$H$14:$H$35,MATCH(C114,Detalle_62!$C$14:$C$35,0)),"—") -> — | K114: =IFERROR(INDEX(Detalle_62!$L$14:$L$35,MATCH(C114,Detalle_62!$C$14:$C$35,0)),"—") -> — | L114: =IFERROR(INDEX(Detalle_62!$P$14:$P$35,MATCH(C114,Detalle_62!$C$14:$C$35,0)),"—") -> — | M114: =IFERROR(INDEX(Pruebas_Auditoria!$M$53:$M$137,MATCH(C114,Pruebas_Auditoria!$E$53:$E$137,0)),"—") -> — | N114: =INDEX(Intereses_x_Obligacion!$I:$I,MATCH(C114,Intereses_x_Obligacion!$A:$A,0)) -> 0 | O114: =INDEX(Intereses_x_Obligacion!$F:$F,MATCH(C114,Intereses_x_Obligacion!$A:$A,0)) -> 0 | P114: =INDEX(Intereses_x_Obligacion!$L:$L,MATCH(C114,Intereses_x_Obligacion!$A:$A,0)) -> 0 | Q114: =IF(LEFT(Pruebas_Auditoria!M174,3)="[C]","[C] [B]",IF(LEFT(Pruebas_Auditoria!M174,3)="[E]","[E] [B]","[P]")) -> [P]
D115: Subtotal | E115: =SUM(E113:E114) -> 0 | F115: =SUM(F113:F114) -> 0 | G115: =SUM(G113:G114) -> 0 | H115: =SUM(H113:H114) -> 0 | I115: =SUM(I113:I114) -> 0 | N115: =SUM(N113:N114) -> 0 | O115: =SUM(O113:O114) -> 0 | P115: =SUM(P113:P114) -> 0
C117: ******* 3 ******* Cuentas de intereses del balance vs suma por obligación (causación, pagos y gasto)
...

Sheet Resumen
A1: GUAICARAMO S.A.S. – Auditoría de Obligaciones Financieras (cuenta 21 / papel 62) – corte 31-jul-2026
A2: Cruce movimiento ↔ detalle 62 ↔ certificados bancarios ↔ balance de prueba; recálculo de intereses (NIIF 9 costo amortizado, NIIF 16, NIC 1). Cifras en pesos colombianos. Azul = dato de la fuente; negro = fórmula; verde = vínculo a otra hoja; amarillo = cifra clave.
B4: Parámetros | E4: Estado del papel
B5: Fecha de corte | C5: 46234 | E5: ="Emitido con " & Pendientes!$D$20 & " pendientes" -> Emitido con 14 pendientes
B6: Umbral de diferencia trivial / redondeo (COP) | C6: 1000 | E6: Ver hoja 'Pendientes'
B7: Tolerancia recálculo de intereses (%) | C7: 0.02
B9: Resultados por prueba
B10: Prueba | C10: Valor A | D10: Valor B | E10: Diferencia | F10: Estado
B11: 1. Integridad: movimiento auxiliar vs balance – SF cuenta 21 | C11: =Pruebas_Auditoria!F21 -> -4.6662703e+10 | D11: =Pruebas_Auditoria!G21 -> -4.6662703e+10 | E11: =C11-D11 -> 0 | F11: =IF(ABS(E11)<=$C$6,"OK","DIFERENCIA") -> OK
B12: 2. Integridad: balance 29-sep vs balance 24-ago – nº cuentas con diferencias | C12: =Balance_21!$C$40 -> 0 | D12: =0 -> 0 | E12: =C12-D12 -> 0 | F12: =IF(ABS(E12)<=$C$6,"OK","DIFERENCIA") -> OK
B13: 3. Detalle 62: suma recalculada vs 'Total obligaciones' del cliente | C13: =Detalle_62!F36 -> 4.5185912e+10 | D13: =Detalle_62!F37 -> 4.5185912e+10 | E13: =C13-D13 -> 0 | F13: =IF(ABS(E13)<=$C$6,"OK","DIFERENCIA") -> OK
B14: 4. Créditos: detalle 62 vs mayor (21050100 + 21050201) | C14: =Cruce_Detalle_Mayor!D6 -> 3.8300667e+10 | D14: =Cruce_Detalle_Mayor!E6 -> 38300666666 | E14: =C14-D14 -> -0.66666412 | F14: =IF(ABS(E14)<=$C$6,"OK","DIFERENCIA") -> OK
B15: 5. Leasing: detalle 62 vs mayor (21202040 + 21202140) | C15: =Cruce_Detalle_Mayor!D7 -> 6.8852455e+09 | D15: =Cruce_Detalle_Mayor!E7 -> 7.9035116e+09 | E15: =C15-D15 -> -1.0182662e+09 | F15: =IF(ABS(E15)<=$C$6,"OK","DIFERENCIA") -> DIFERENCIA
B16: 6. Certificados: capital banco 31-jul vs detalle 62 (obligaciones con saldo certificado) | C16: =SUMIFS(Pruebas_Auditoria!J57:J73,Pruebas_Auditoria!H57:H73,"<>") -> 3.5993167e+10 | D16: =SUMIFS(Pruebas_Auditoria!K57:K73,Pruebas_Auditoria!H57:H73,"<>") -> 3.5821568e+10 | E16: =C16-D16 -> 1.715997e+08 | F16: =IF(ABS(E16)<=$C$6,"OK","DIFERENCIA") -> DIFERENCIA
B17: 7. Certificados: pagos/intereses certificados vs registrados (comprobantes) | C17: =Pruebas_Auditoria!H131 -> 3.3299172e+09 | D17: =Pruebas_Auditoria!I131 -> 3.3418922e+09 | E17: =C17-D17 -> -11975072 | F17: =IF(ABS(E17)<=$C$6,"OK","DIFERENCIA") -> DIFERENCIA
B18: 8. Recálculo de intereses liquidados por el banco (Parte 1) | C18: =Pruebas_Auditoria!J209+Pruebas_Auditoria!K209 -> 1.561142e+09 | D18: =Pruebas_Auditoria!J209 -> 1.6129345e+09 | E18: =C18-D18 -> -51792495 | F18: =IF(ABS(E18)<=$C$6,"OK","DIFERENCIA") -> DIFERENCIA
B19: 9. Intereses causados al 31-jul: recalculado vs registrado en 2130 | C19: =Pruebas_Auditoria!I236 -> 6.1509441e+08 | D19: =Pruebas_Auditoria!J236 -> 427389017 | E19: =C19-D19 -> 1.8770539e+08 | F19: =IF(ABS(E19)<=$C$6,"OK","DIFERENCIA") -> DIFERENCIA
B20: 10. Intereses por pagar: suma por obligación vs balance 2130 | C20: =Pruebas_Auditoria!J236 -> 427389017 | D20: =-Balance_21!$F$25 -> 4.2738902e+08 | E20: =C20-D20 -> -0.16000003 | F20: =IF(ABS(E20)<=$C$6,"OK","DIFERENCIA") -> OK
B22: Indicadores clave
B23: Saldo de capital según mayor 31-jul (2105 sin TC + 2120) | C23: =Gasto_Intereses!B5 -> 4.6204178e+10
B24: Saldo según detalle 62 | C24: =Detalle_62!F36 -> 4.5185912e+10
B25: Leasing 386735 omitido en el detalle 62 | C25: =Cruce_Detalle_Mayor!F14 -> 675837500
B26: Leasing GECOLSA (Davivienda) omitido en el detalle 62 | C26: =Cruce_Detalle_Mayor!F15 -> 213861900
B27: Leasings Bogotá: detalle 62 por debajo del mayor/certificados | C27: =Cruce_Detalle_Mayor!F16 -> 1.7160826e+08
B28: Diferencia de leasing sin explicar (residual) | C28: =Cruce_Detalle_Mayor!F19 -> 0
B29: % del saldo del detalle 62 cubierto con certificados | C29: =Pruebas_Auditoria!$K$87 -> 0.85042859
B30: Intereses no causados al 31-jul (AJE-1) | C30: =Pruebas_Auditoria!K236 -> 1.8770539e+08
B31: Reclasificación LP → CP propuesta (créditos + leasing) | C31: =Clasif_CP_LP!B11+Clasif_CP_LP!B12 -> 1.5766357e+09
B32: Gasto de intereses: desviación vs expectativa | C32: =Gasto_Intereses!$B$18 -> -0.071262153
B33: Conclusión prueba analítica | C33: =Gasto_Intereses!$B$20 -> Gasto razonable dentro del umbral
B35: Conclusión
B36: INTEGRIDAD – Mayor vs balance: el movimiento auxiliar de la cuenta 21 cuadra exactamente (débitos, créditos y saldos) con los dos balances de prueba, que son idénticos entre sí. Sin excepción.
B37: INTEGRIDAD – Detalle 62 vs mayor: los créditos cuadran (diferencia de redondeo $0,67). El leasing NO cuadra ($1.018 MM): leasing Bancolombia 386735 y leasing GECOLSA omitidos y saldos de tablas teóricas en el detalle; la diferencia queda explicada por obligación (Pruebas_Auditoria (bloque 3)).
B38: EXACTITUD – Certificados: los créditos cuadran con los extractos salvo redondeos de abonos a capital (< $5.000). Los leasings de Banco de Bogotá están subvalorados en el detalle 62. Los pagos registrados coinciden con los extractos, salvo el canon 032 del leasing 1019441.
B39: RECÁLCULO – La liquidación bancaria es razonable en base 365 (Bogotá Finagro en base 360), excepto Davivienda 607691/569032, cuya tasa declarada no reconcilia. Hay intereses causados no registrados al 31-jul (AJE-1) por la política de causación del cliente.
B40: PRESENTACIÓN – Se requiere reclasificar la porción corriente (NIC 1.69) y corregir los errores CP/LP del detalle 62. Ver la hoja 'Hallazgos'.
B41: PENDIENTES – El papel se emite sin certificados de saldo de leasings Davivienda/Bancolombia, sin confirmaciones de BBVA, Banco Popular y del crédito Bogotá 1159383796, sin tablas de amortización y sin materialidad del encargo. Las conclusiones afectadas quedan 'Pendiente de soporte' (ver hoja 'Pendientes').
B43: Hojas del libro
B44: Mayor_Mov | C44: Movimiento auxiliar ene–jul con el ID de obligación asignado por auditoría
B45: Balance_21 | C45: Cuentas 21/5305 de ambos balances de prueba y su comparación
B46: Pruebas_Auditoria | C46: Bloques 1–4: movimiento vs balance, certificados bancarios, saldo por obligación y recálculo de intereses (cálculos en amarillo)
B47: Tablas_Amortizacion | C47: Revisión y recálculo de las 25 tablas de amortización del cliente (recálculo en amarillo)
B48: Detalle_62 | C48: Detalle del cliente con recálculo de tasas, subtotales y CP/LP
B49: Cruce_Detalle_Mayor | C49: Detalle 62 vs mayor y roll-forward de capital por obligación
B50: Gasto_Intereses | C50: Prueba analítica del gasto por intereses
B51: Clasif_CP_LP | C51: Clasificación corriente/no corriente (NIC 1)
B52: Hallazgos | C52: Hallazgos, normas y ajustes propuestos
B53: Pendientes | C53: Información pendiente de soporte y tratamiento provisional
B54: PT_62 | C54: Papel de trabajo principal (formato PT): aseveraciones, procedimientos, secciones 1–5 y conclusión
B55: Mayor_Dic25 | C55: Detalle del mayor al 31-dic-25 (PT 2025) por obligación
... B57: Int_Glosas | C57: Intereses pagados directo al gasto según glosas

Sheet Pruebas_Auditoria
A1: PRUEBAS DE AUDITORÍA – OBLIGACIONES FINANCIERAS – corte 31-jul-2026
A2: Cómo leer esta hoja: celdas BLANCAS = datos tomados del cliente, del balance o del banco; celdas AMARILLAS = cálculo o recálculo hecho por auditoría.
A3: 'OK' = la cifra cuadra; 'DIFERENCIA' = revisar (explicación en la columna de comentarios o en la hoja Hallazgos). Cifras en pesos colombianos.
A4: Contenido: BLOQUE 1 Movimiento vs balance · BLOQUE 2 Certificados bancarios · BLOQUE 3 Saldo por obligación · BLOQUE 4 Recálculo de intereses
A6: BLOQUE 1 – ¿El auxiliar contable de la cuenta 21 cuadra con el balance?
A7: Qué se hizo: se sumaron todos los débitos y créditos del auxiliar (ene–jul 2026) y se compararon con el balance de prueba.
A8: Cómo se lee: saldo inicial + débitos − créditos = saldo final calculado (amarillo), que se compara con el saldo final del balance.
A9: ="Resultado: "&M21&" – diferencia total en saldos: "&TEXT(H21,"#,##0") -> Resultado: OK – diferencia total en saldos: 0
A10: Cruce movimiento auxiliar (cuenta 21) vs balance de prueba – Integridad
A11: SI balance + Débitos movimiento − Créditos movimiento = SF calculado; se compara con SF del balance. Signo: crédito negativo.
A13: Cuenta | B13: Descripción | C13: Saldo inicial balance | D13: Débitos movimiento | E13: Créditos movimiento | F13: SF calculado | G13: SF balance | H13: Diferencia SF | I13: Débitos balance | J13: Dif. débitos | K13: Créditos balance | L13: Dif. créditos | M13: Estado
A14: 21050100 | B14: =INDEX(Balance_21!$B$6:$B$36,MATCH(A14,Balance_21!$A$6:$A$36,0)) -> Obl.Financiera Corto Plazo | C14: =Balance_21!$C$16 -> -17938333333 | D14: =SUMIFS(Mayor_Mov!$E$5:$E$445,Mayor_Mov!$B$5:$B$445,A14) -> 24700000000 | E14: =SUMIFS(Mayor_Mov!$F$5:$F$445,Mayor_Mov!$B$5:$B$445,A14) -> 24700000000 | F14: =C14+D14-E14 -> -17938333333 | G14: =Balance_21!$F$16 -> -17938333333 | H14: =F14-G14 -> 0 | I14: =Balance_21!$D$16 -> 24700000000 | J14: =D14-I14 -> 0 | K14: =Balance_21!$E$16 -> 24700000000 | L14: =E14-K14 -> 0 | M14: =IF(MAX(ABS(H14),ABS(J14),ABS(L14))<=Resumen!$C$6,"OK","DIFERENCIA") -> OK
A15: 21050201 | B15: =INDEX(Balance_21!$B$6:$B$36,MATCH(A15,Balance_21!$A$6:$A$36,0)) -> Obg.Financiera Largo Plazo | C15: =Balance_21!$C$18 -> -23368333333 | D15: =SUMIFS(Mayor_Mov!$E$5:$E$445,Mayor_Mov!$B$5:$B$445,A15) -> 3006000000 | E15: =SUMIFS(Mayor_Mov!$F$5:$F$445,Mayor_Mov!$B$5:$B$445,A15) -> 0 | F15: =C15+D15-E15 -> -20362333333 | G15: =Balance_21!$F$18 -> -20362333333 | H15: =F15-G15 -> 0 | I15: =Balance_21!$D$18 -> 3006000000 | J15: =D15-I15 -> 0 | K15: =Balance_21!$E$18 -> 0 | L15: =E15-K15 -> 0 | M15: =IF(MAX(ABS(H15),ABS(J15),ABS(L15))<=Resumen!$C$6,"OK","DIFERENCIA") -> OK
A16: 21050301 | B16: =INDEX(Balance_21!$B$6:$B$36,MATCH(A16,Balance_21!$A$6:$A$36,0)) -> Tarjeta de Credito por Pagar | C16: =Balance_21!$C$19 -> -25364582 | D16: =SUMIFS(Mayor_Mov!$E$5:$E$445,Mayor_Mov!$B$5:$B$445,A16) -> 1.1793557e+08 | E16: =SUMIFS(Mayor_Mov!$F$5:$F$445,Mayor_Mov!$B$5:$B$445,A16) -> 1.2370672e+08 | F16: =C16+D16-E16 -> -31135732 | G16: =Balance_21!$F$19 -> -31135732 | H16: =F16-G16 -> 0 | I16: =Balance_21!$D$19 -> 1.1793557e+08 | J16: =D16-I16 -> 0 | K16: =Balance_21!$E$19 -> 1.2370672e+08 | L16: =E16-K16 -> 0 | M16: =IF(MAX(ABS(H16),ABS(J16),ABS(L16))<=Resumen!$C$6,"OK","DIFERENCIA") -> OK
A17: 21202040 | B17: =INDEX(Balance_21!$B$6:$B$36,MATCH(A17,Balance_21!$A$6:$A$36,0)) -> Leasing Corto Plazo | C17: =Balance_21!$C$22 -> -5.8588019e+08 | D17: =SUMIFS(Mayor_Mov!$E$5:$E$445,Mayor_Mov!$B$5:$B$445,A17) -> 35428634 | E17: =SUMIFS(Mayor_Mov!$F$5:$F$445,Mayor_Mov!$B$5:$B$445,A17) -> 607791830 | F17: =C17+D17-E17 -> -1.1582434e+09 | G17: =Balance_21!$F$22 -> -1.1582434e+09 | H17: =F17-G17 -> 0 | I17: =Balance_21!$D$22 -> 35428634 | J17: =D17-I17 -> 0 | K17: =Balance_21!$E$22 -> 607791830 | L17: =E17-K17 -> 0 | M17: =IF(MAX(ABS(H17),ABS(J17),ABS(L17))<=Resumen!$C$6,"OK","DIFERENCIA") -> OK
A18: 21202140 | B18: =INDEX(Balance_21!$B$6:$B$36,MATCH(A18,Balance_21!$A$6:$A$36,0)) -> Leasing Largo Plazo | C18: =Balance_21!$C$24 -> -7.5446146e+09 | D18: =SUMIFS(Mayor_Mov!$E$5:$E$445,Mayor_Mov!$B$5:$B$445,A18) -> 9.110819e+08 | E18: =SUMIFS(Mayor_Mov!$F$5:$F$445,Mayor_Mov!$B$5:$B$445,A18) -> 111735587 | F18: =C18+D18-E18 -> -6.7452682e+09 | G18: =Balance_21!$F$24 -> -6.7452682e+09 | H18: =F18-G18 -> 0 | I18: =Balance_21!$D$24 -> 9.110819e+08 | J18: =D18-I18 -> 0 | K18: =Balance_21!$E$24 -> 111735587 | L18: =E18-K18 -> 0 | M18: =IF(MAX(ABS(H18),ABS(J18),ABS(L18))<=Resumen!$C$6,"OK","DIFERENCIA") -> OK
A19: 21300101 | B19: =INDEX(Balance_21!$B$6:$B$36,MATCH(A19,Balance_21!$A$6:$A$36,0)) -> Intereses Financieros por Pagar O.F. | C19: =Balance_21!$C$27 -> -1107168370 | D19: =SUMIFS(Mayor_Mov!$E$5:$E$445,Mayor_Mov!$B$5:$B$445,A19) -> 3257045166 | E19: =SUMIFS(Mayor_Mov!$F$5:$F$445,Mayor_Mov!$B$5:$B$445,A19) -> 2573515476 | F19: =C19+D19-E19 -> -423638680 | G19: =Balance_21!$F$27 -> -423638680 | H19: =F19-G19 -> 0 | I19: =Balance_21!$D$27 -> 3257045166 | J19: =D19-I19 -> 0 | K19: =Balance_21!$E$27 -> 2573515476 | L19: =E19-K19 -> 0 | M19: =IF(MAX(ABS(H19),ABS(J19),ABS(L19))<=Resumen!$C$6,"OK","DIFERENCIA") -> OK
A20: 21300102 | B20: =INDEX(Balance_21!$B$6:$B$36,MATCH(A20,Balance_21!$A$6:$A$36,0)) -> Intereses Leasing por Pagar | C20: =Balance_21!$C$28 -> -93054514 | D20: =SUMIFS(Mayor_Mov!$E$5:$E$445,Mayor_Mov!$B$5:$B$445,A20) -> 4.9871275e+08 | E20: =SUMIFS(Mayor_Mov!$F$5:$F$445,Mayor_Mov!$B$5:$B$445,A20) -> 409408571 | F20: =C20+D20-E20 -> -3750337.2 | G20: =Balance_21!$F$28 -> -3750337.2 | H20: =F20-G20 -> -2.6077032e-08 | I20: =Balance_21!$D$28 -> 4.9871275e+08 | J20: =D20-I20 -> 0 | K20: =Balance_21!$E$28 -> 409408571 | L20: =E20-K20 -> 0 | M20: =IF(MAX(ABS(H20),ABS(J20),ABS(L20))<=Resumen!$C$6,"OK","DIFERENCIA") -> OK
B21: TOTAL CUENTA 21 | C21: =SUM(C14:C20) -> -5.0662749e+10 | D21: =SUM(D14:D20) -> 3.2526204e+10 | E21: =SUM(E14:E20) -> 2.8526158e+10 | F21: =SUM(F14:F20) -> -4.6662703e+10 | G21: =SUM(G14:G20) -> -4.6662703e+10 | H21: =SUM(H14:H20) -> -2.6077032e-08 | I21: =SUM(I14:I20) -> 3.2526204e+10 | J21: =SUM(J14:J20) -> 0 | ... L21: =SUM(L14:L20) -> 0 | M21: =IF(MAX(ABS(H21),ABS(J21),ABS(L21))<=Resumen!$C$6,"OK","DIFERENCIA") -> OK
B22: Total cuenta 21 según balance (mayor) | C22: =Balance_21!$C$13 -> -5.0662749e+10 | G22: =Balance_21!$F$13 -> -4.6662703e+10 | I22: =Balance_21!$D$13 -> 3.2526204e+10 | K22: =Balance_21!$E$13 -> 2.8526158e+10
B23: Diferencia suma de auxiliares vs cuenta 21 | C23: =C21-C22 -> 0 | G23: =G21-G22 -> 0 | I23: =I21-I22 -> 0 | K23: =K21-K22 -> 0
A25: B. Integridad del archivo de movimiento ('Gran total' del reporte vs suma de líneas)
B26: Concepto | C26: Gran total reporte | D26: Suma líneas | E26: Diferencia
B27: Débitos | C27: 3.2526204e+10 | D27: =Mayor_Mov!E446 -> 3.2526204e+10 | E27: =C27-D27 -> 0
B28: Créditos | C28: 2.8526158e+10 | D28: =Mayor_Mov!F446 -> 2.8526158e+10 | E28: =C28-D28 -> 0
B29: Neto | C29: 4.0000458e+09 | D29: =Mayor_Mov!G446 -> 4.0000458e+09 | E29: =C29-D29 -> 0
B30: Nº de líneas del movimiento | D30: =COUNTA(Mayor_Mov!$B$5:$B$445) -> 441
A32: C. Consistencia jerárquica del balance y relación pasivo–gasto
B33: Prueba | C33: Valor A | D33: Valor B | E33: Diferencia | G33: Comentario
B34: SF 21 = 2105 + 2120 + 2130 | C34: =Balance_21!$F$13 -> -4.6662703e+10 | D34: =Balance_21!$F$14+Balance_21!$F$20+Balance_21!$F$25 -> -4.6662703e+10 | E34: =C34-D34 -> 0
B35: SF 2105 = 210501 + 210502 | C35: =Balance_21!$F$14 -> -3.8331802e+10 | D35: =Balance_21!$F$15+Balance_21!$F$17 -> -3.8331802e+10 | E35: =C35-D35 -> 0
B36: SF 210502 = 21050201 + 21050301 (tarjeta de crédito agrupada en LP) | C36: =Balance_21!$F$17 -> -2.0393469e+10 | D36: =Balance_21!$F$18+Balance_21!$F$19 -> -2.0393469e+10 | E36: =C36-D36 -> 0 | G36: Tarjeta de crédito (pasivo corriente) agrupada dentro de 'Obligaciones financieras a largo plazo' – ver hallazgo de clasificación.
B37: SF 2120 = 21202040 + 21202140 | C37: =Balance_21!$F$20 -> -7.9035116e+09 | D37: =Balance_21!$F$22+Balance_21!$F$24 -> -7.9035116e+09 | E37: =C37-D37 -> 0
B38: SF 2130 = 21300101 + 21300102 | C38: =Balance_21!$F$25 -> -4.2738902e+08 | D38: =Balance_21!$F$27+Balance_21!$F$28 -> -4.2738902e+08 | E38: =C38-D38 -> 0
B39: Ecuación: Activo + Pasivo + Patrimonio + Resultado (4+5+6+7) = 0 | C39: =Balance_21!$F$6+Balance_21!$F$7+Balance_21!$F$8 -> 1.8399439e+10 | D39: =-(Balance_21!$F$9+Balance_21!$F$10+Balance_21!$F$11+Balance_21!$F$12) -> 1.8399439e+10 | E39: =C39-D39 -> 0 | G39: Resultado del periodo ene–jul incluido vía clases 4 a 7.
B40: Intereses OF por pagar (21300101) = gasto causado neto (53052030) | C40: =-Balance_21!$F$27 -> 423638680 | D40: =Balance_21!$F$35 -> 423638680 | E40: =C40-D40 -> 0 | G40: El cliente reversa la causación al pagar y lleva el pago a 53052020; el saldo de 53052030 debe igualar el pasivo.
B41: Intereses leasing por pagar (21300102) = gasto causado neto (53052040) | C41: =-Balance_21!$F$28 -> 3750337.2 | D41: =Balance_21!$F$36 -> 3750337.3 | E41: =C41-D41 -> -0.16
B42: SI 21300101 = créditos 53052020 (reclasificación apertura) | C42: =-Balance_21!$C$27 -> 1107168370 | D42: =Balance_21!$E$34 -> 1107168370 | E42: =C42-D42 -> 0 | G42: Asiento de apertura: Db 53052030 / Cr 53052020 por el saldo inicial causado.
B43: SI 21300102 = créditos 53052010 (reclasificación apertura) | C43: =-Balance_21!$C$28 -> 93054514 | D43: =Balance_21!$E$33 -> 93054514 | E43: =C43-D43 -> 0
A45: D. Comparación de versiones del balance
B46: Cuentas con diferencias entre balance 24-ago y 29-sep | C46: =Balance_21!$C$40 -> 0 | D46: =IF(C46=0,"Sin cambios posteriores al cierre de jul-26","Revisar ajustes posteriores") -> Sin cambios posteriores al cierre de jul-26
A49: BLOQUE 2 – ¿Los saldos del detalle 62 coinciden con lo que dice el banco?
A50: Qué se hizo: se tomó cada extracto o certificado bancario y se comparó capital, tasa y vencimiento con el detalle 62 del cliente.
A51: Capital banco 31-jul (amarillo) = saldo del certificado − abonos a capital pagados después de la fecha del certificado. Sección C: cada pago del banco vs el comprobante contable.
A52: ="Resultado: diferencia detalle 62 − banco "&TEXT(L74,"#,##0")&"; saldo cubierto con certificados: "&TEXT($K$87,"0%") -> Resultado: diferencia detalle 62 − banco -171,599,701; saldo cubierto con certificados: 85%
A53: Cruce detalle 62 vs certificados / extractos bancarios (PDF adjunto)
A54: Fuente: ilovepdf_merged_1.pdf (25 págs.). Las págs. 3, 5, 7, 9, 11, 15, 23 y 25 son anexos/instructivos sin cifras. Capital banco 31-jul = capital certificado − abonos a capital entre corte y 31-jul.
A56: # | B56: Pág. PDF | C56: Banco | D56: Obligación (certificado) | E56: ID auditoría | F56: Tipo documento | G56: Fecha corte | H56: Capital s/certificado | I56: Abonos capital posteriores al corte (≤31-jul) | J56: Capital banco 31-jul-26 | K56: Saldo detalle 62 | L56: Diferencia detalle − banco | M56: Tasa EA certificado | N56: Tasa EA detalle | O56: Dif. (pb) | P56: Venc. certificado | Q56: Venc. detalle | R56: ¿Venc. coincide? | S56: Observaciones
A57: 1 | B57: 1 | C57: Davivienda | D57: 7000457300830624 | E57: DAV-830624 | F57: Extracto crédito corporativo | G57: 46102 | H57: =7499998630.82-127.57 -> 7.4999985e+09 | I57: 0 | J57: =IF(H57="","N/D",H57-I57) -> 7.4999985e+09 | K57: =SUMIFS(Detalle_62!$F$14:$F$35,Detalle_62!$C$14:$C$35,E57) -> 7500000000 | L57: =IF(H57="","N/D",K57-J57) -> 1496.75 | M57: 0.1551 | N57: =INDEX(Detalle_62!$J$14:$J$35,MATCH(E57,Detalle_62!$C$14:$C$35,0)) -> 0.15589377 | O57: =(N57-M57)*10000 -> 7.9376562 | P57: 52677 | Q57: =INDEX(Detalle_62!$P$14:$P$35,MATCH(E57,Detalle_62!$C$14:$C$35,0)) -> 52677 | R57: =IF(P57="","N/D",IF(P57=Q57,"Sí","NO")) -> Sí | S57: Saldo anterior 21-sep-25 $7.499.998.630,82 − abono capital 21-mar-26 $127,57. Próximo pago 21-sep-26 sólo intereses $565.738.188,80 (IBR semestral + 3,00).
A58: 2 | B58: 2 | C58: Banco de Bogotá | D58: 00856670629 | E58: BOG-856670629 | F58: Extracto Sustitución Finagro | G58: 46169 | H58: 1.6395e+09 | I58: 182166667 | J58: =IF(H58="","N/D",H58-I58) -> 1.4573333e+09 | K58: =SUMIFS(Detalle_62!$F$14:$F$35,Detalle_62!$C$14:$C$35,E58) -> 1457333332 | L58: =IF(H58="","N/D",K58-J58) -> 6.4100001 | M58: 0.1494 | N58: =INDEX(Detalle_62!$J$14:$J$35,MATCH(E58,Detalle_62!$C$14:$C$35,0)) -> 0.15829309 | O58: =(N58-M58)*10000 -> 88.930895 | Q58: =INDEX(Detalle_62!$P$14:$P$35,MATCH(E58,Detalle_62!$C$14:$C$35,0)) -> 46925 | R58: =IF(P58="","N/D",IF(P58=Q58,"Sí","NO")) -> N/D | S58: Cuota 12 (21-jun-26): capital $182.166.667 + intereses $59.390.887,23. Valor aprobado $2.186 MM, plazo 60 meses.
A59: 3 | B59: 4 | C59: Bancolombia | D59: 01260105867 | E59: BCL-1260105867 | F59: Detalle del crédito (Sucursal Virtual) | G59: 46245 | H59: 3333333334 | I59: 0 | J59: =IF(H59="","N/D",H59-I59) -> 3333333334 | K59: =SUMIFS(Detalle_62!$F$14:$F$35,Detalle_62!$C$14:$C$35,E59) -> 3.3333333e+09 | L59: =IF(H59="","N/D",K59-J59) -> -0.66666698 | M59: 0.1417 | N59: =INDEX(Detalle_62!$J$14:$J$35,MATCH(E59,Detalle_62!$C$14:$C$35,0)) -> 0.14105339 | O59: =(N59-M59)*10000 -> -6.4660895 | P59: 46865 | Q59: =INDEX(Detalle_62!$P$14:$P$35,MATCH(E59,Detalle_62!$C$14:$C$35,0)) -> 46864 | R59: =IF(P59="","N/D",IF(P59=Q59,"Sí","NO")) -> NO | S59: Capital vigente al 11-ago-26; sin abonos entre 31-jul y 11-ago. Intereses corrientes causados $24.607.407; próximo pago 22-oct-26. IBR + 1,5.
A60: 4 | B60: 6 | C60: Banco de Bogotá | D60: 00453436746 | E60: BOG-453436746 | F60: Extracto Ordinaria Comercial | G60: 46195 | H60: 3e+09 | I60: 62500000 | J60: =IF(H60="","N/D",H60-I60) -> 2.9375e+09 | K60: =SUMIFS(Detalle_62!$F$14:$F$35,Detalle_62!$C$14:$C$35,E60) -> 2937500000 | L60: =IF(H60="","N/D",K60-J60) -> 22.61 | M60: 0.1696 | N60: =INDEX(Detalle_62!$J$14:$J$35,MATCH(E60,Detalle_62!$C$14:$C$35,0)) -> 0.17522416 | O60: =(N60-M60)*10000 -> 56.241608 | Q60: =INDEX(Detalle_62!$P$14:$P$35,MATCH(E60,Detalle_62!$C$14:$C$35,0)) -> 47651 | R60: =IF(P60="","N/D",IF(P60=Q60,"Sí","NO")) -> N/D | S60: Cuota 100 (17-jul-26): capital $62.500.000 + intereses $38.894.999,71. Aprobado $7.500 MM, plazo 146 meses.
A61: 5 | B61: 8 | C61: Banco de Bogotá | D61: 00858177259 | E61: BOG-858177259 | F61: Extracto Sustitución Finagro | G61: 46234 | H61: 1.125e+09 | I61: 0 | J61: =IF(H61="","N/D",H61-I61) -> 1.125e+09 | K61: =SUMIFS(Detalle_62!$F$14:$F$35,Detalle_62!$C$14:$C$35,E61) -> 1125000000 | L61: =IF(H61="","N/D",K61-J61) -> 3.5899999 | M61: 0.1665 | N61: =INDEX(Detalle_62!$J$14:$J$35,MATCH(E61,Detalle_62!$C$14:$C$35,0)) -> 0.17400356 | O61: =(N61-M61)*10000 -> 75.035556 | Q61: =INDEX(Detalle_62!$P$14:$P$35,MATCH(E61,Detalle_62!$C$14:$C$35,0)) -> 46990 | R61: =IF(P61="","N/D",IF(P61=Q61,"Sí","NO")) -> N/D | S61: Corte 31-jul-26 (fecha de auditoría). Próxima cuota 25-ago-26: capital $125.000.000 + intereses $45.166.249,86.
A62: 6 | B62: 10 | C62: Banco de Bogotá | D62: 01155297469 → prorrogado 1159383796 | E62: BOG-1159383796 | F62: Extracto Sustitución Finagro | G62: 46190 | H62: 10000000000 | I62: 0 | J62: =IF(H62="","N/D",H62-I62) -> 10000000000 | K62: =SUMIFS(Detalle_62!$F$14:$F$35,Detalle_62!$C$14:$C$35,E62) -> 10000000000 | L62: =IF(H62="","N/D",K62-J62) -> 0 | M62: 0.1239 | N62: =INDEX(Detalle_62!$J$14:$J$35,MATCH(E62,Detalle_62!$C$14:$C$35,0)) -> 0.12962887 | O62: =(N62-M62)*10000 -> 57.288656 | Q62: =INDEX(Detalle_62!$P$14:$P$35,MATCH(E62,Detalle_62!$C$14:$C$35,0)) -> 46409 | R62: =IF(P62="","N/D",IF(P62=Q62,"Sí","NO")) -> N/D | S62: Cuota 2 (14-jul-26) por $10.299.617.737,55 incluye capital $10.000 MM. Contabilidad registra prórroga (NB-1016, 29-jul) al crédito 1159383796 – sin certificado del nuevo crédito.
A63: 7 | B63: 12 | C63: Davivienda | D63: 7000457300607691 | E63: DAV-607691 | F63: Extracto crédito corporativo | G63: 46050 | H63: 3.9599984e+09 | I63: =272300000-272299382.05 -> 617.95 | J63: =IF(H63="","N/D",H63-I63) -> 3.9599978e+09 | K63: =SUMIFS(Detalle_62!$F$14:$F$35,Detalle_62!$C$14:$C$35,E63) -> 3960000000 | L63: =IF(H63="","N/D",K63-J63) -> 2182.05 | M63: 0.1258 | N63: =INDEX(Detalle_62!$J$14:$J$35,MATCH(E63,Detalle_62!$C$14:$C$35,0)) -> 0.16019827 | O63: =(N63-M63)*10000 -> 343.98266 | P63: 51710 | Q63: =INDEX(Detalle_62!$P$14:$P$35,MATCH(E63,Detalle_62!$C$14:$C$35,0)) -> 51710 | R63: =IF(P63="","N/D",IF(P63=Q63,"Sí","NO")) -> Sí | S63: Pago 28-jul-26 de $272.300.000 vs intereses facturados $272.299.382,05: excedente $617,95 se aplica a capital.
A64: 8 | B64: 13 | C64: Davivienda | D64: 7000457300569032 | E64: DAV-569032 | F64: Extracto crédito corporativo | G64: 46050 | H64: 2.9999959e+09 | I64: =206288000-206287213.2 -> 786.8 | J64: =IF(H64="","N/D",H64-I64) -> 2999995157 | K64: =SUMIFS(Detalle_62!$F$14:$F$35,Detalle_62!$C$14:$C$35,E64) -> 3000000000 | L64: =IF(H64="","N/D",K64-J64) -> 4843 | M64: 0.1258 | N64: =INDEX(Detalle_62!$J$14:$J$35,MATCH(E64,Detalle_62!$C$14:$C$35,0)) -> 0.16019827 | O64: =(N64-M64)*10000 -> 343.98266 | P64: 51710 | Q64: =INDEX(Detalle_62!$P$14:$P$35,MATCH(E64,Detalle_62!$C$14:$C$35,0)) -> 51710 | R64: =IF(P64="","N/D",IF(P64=Q64,"Sí","NO")) -> Sí | S64: Pago 28-jul-26 de $206.288.000 vs intereses facturados $206.287.213,20: excedente $786,80 se aplica a capital.
A65: 9 | B65: p.14 + LEASING_1275-3_DAVIVIENDA.pdf | C65: Davivienda Leasing | D65: 000030001021275-3 | E65: DAV-L1021275 | F65: Factura leasing | G65: 46209 | I65: 0 | J65: =IF(H65="","N/D",H65-I65) -> N/D | K65: =SUMIFS(Detalle_62!$F$14:$F$35,Detalle_62!$C$14:$C$35,E65) -> 1.8837122e+09 | L65: =IF(H65="","N/D",K65-J65) -> N/D | M65: 0.1441 | N65: =INDEX(Detalle_62!$J$14:$J$35,MATCH(E65,Detalle_62!$C$14:$C$35,0)) -> 0.14827711 | O65: =(N65-M65)*10000 -> 41.771146 | Q65: =INDEX(Detalle_62!$P$14:$P$35,MATCH(E65,Detalle_62!$C$14:$C$35,0)) -> 48235 | R65: =IF(P65="","N/D",IF(P65=Q65,"Sí","NO")) -> N/D | S65: Canon 006 (23-jul-26) sólo intereses $64.041.851; 16 cuotas pactadas. El extracto NO informa saldo de capital → ver saldo implícito en Pruebas_Auditoria (bloque 4).
A66: 10 | B66: 16 | C66: Banco de Bogotá Leasing | D66: 00557285005 | E66: BOG-L557285005 | F66: Estado de cuenta leasing | G66: 46215 | H66: 1.047113e+09 | I66: 62866117 | J66: =IF(H66="","N/D",H66-I66) -> 9.8424689e+08 | K66: =SUMIFS(Detalle_62!$F$14:$F$35,Detalle_62!$C$14:$C$35,E66) -> 9.6862047e+08 | L66: =IF(H66="","N/D",K66-J66) -> -15626414 | M66: 0.1604 | N66: =INDEX(Detalle_62!$J$14:$J$35,MATCH(E66,Detalle_62!$C$14:$C$35,0)) -> 0.16478246 | O66: =(N66-M66)*10000 -> 43.824553 | P66: 47321 | Q66: =INDEX(Detalle_62!$P$14:$P$35,MATCH(E66,Detalle_62!$C$14:$C$35,0)) -> 47321 | R66: =IF(P66="","N/D",IF(P66=Q66,"Sí","NO")) -> Sí | S66: Saldo capital tras pago 22-abr-26; canon 22-jul-26 capital $62.866.117,12 / costo financiero $39.578.631,88. Opción de compra $16.220.758.
A67: 11 | B67: 17 | C67: Banco de Bogotá Leasing | D67: 00556449064 | E67: BOG-L556449064 | F67: Estado de cuenta leasing | G67: 46220 | H67: 2.8027464e+08 | I67: 26602534 | J67: =IF(H67="","N/D",H67-I67) -> 2.536721e+08 | K67: =SUMIFS(Detalle_62!$F$14:$F$35,Detalle_62!$C$14:$C$35,E67) -> 1.9672018e+08 | L67: =IF(H67="","N/D",K67-J67) -> -56951926 | M67: 0.1425 | N67: =INDEX(Detalle_62!$J$14:$J$35,MATCH(E67,Detalle_62!$C$14:$C$35,0)) -> 0.14541789 | O67: =(N67-M67)*10000 -> 29.178864 | P67: 46961 | Q67: =INDEX(Detalle_62!$P$14:$P$35,MATCH(E67,Detalle_62!$C$14:$C$35,0)) -> 46870 | R67: =IF(P67="","N/D",IF(P67=Q67,"Sí","NO")) -> NO | S67: Saldo tras pago 27-abr-26; canon 27-jul-26 capital $26.602.533,70 / costo financiero $9.497.274,30. DTF.
A68: 12 | B68: 18 | C68: Banco de Bogotá Leasing | D68: 00556449117 | E68: BOG-L556449117 | F68: Estado de cuenta leasing | G68: 46220 | H68: 2.8027464e+08 | I68: 26602534 | J68: =IF(H68="","N/D",H68-I68) -> 2.5367211e+08 | K68: =SUMIFS(Detalle_62!$F$14:$F$35,Detalle_62!$C$14:$C$35,E68) -> 1.9672018e+08 | L68: =IF(H68="","N/D",K68-J68) -> -56951927 | M68: 0.1425 | N68: =INDEX(Detalle_62!$J$14:$J$35,MATCH(E68,Detalle_62!$C$14:$C$35,0)) -> 0.14541789 | O68: =(N68-M68)*10000 -> 29.178864 | P68: 46961 | Q68: =INDEX(Detalle_62!$P$14:$P$35,MATCH(E68,Detalle_62!$C$14:$C$35,0)) -> 46870 | R68: =IF(P68="","N/D",IF(P68=Q68,"Sí","NO")) -> NO | S68: Saldo tras pago 27-abr-26; canon 27-jul-26 capital $26.602.533,71 / costo financiero $9.497.274,29. DTF.
A69: 13 | B69: 19 | C69: Banco de Bogotá Leasing | D69: 00556449180 | E69: BOG-L556449180 | F69: Estado de cuenta leasing | G69: 46216 | H69: 4.1765035e+08 | I69: 21538319 | J69: =IF(H69="","N/D",H69-I69) -> 3.9611203e+08 | K69: =SUMIFS(Detalle_62!$F$14:$F$35,Detalle_62!$C$14:$C$35,E69) -> 3.8184539e+08 | L69: =IF(H69="","N/D",K69-J69) -> -14266642 | M69: 0.1422 | N69: =INDEX(Detalle_62!$J$14:$J$35,MATCH(E69,Detalle_62!$C$14:$C$35,0)) -> 0.14541789 | O69: =(N69-M69)*10000 -> 32.178864 | P69: 47506 | Q69: =INDEX(Detalle_62!$P$14:$P$35,MATCH(E69,Detalle_62!$C$14:$C$35,0)) -> 47503 | R69: =IF(P69="","N/D",IF(P69=Q69,"Sí","NO")) -> NO | S69: Saldo tras pago 23-abr-26; canon 23-jul-26 capital $21.538.319,01 / costo financiero $14.118.857,99. DTF.
A70: 14 | B70: 20 | C70: Banco de Bogotá Leasing | D70: 00556449224 | E70: BOG-L556449224 | F70: Estado de cuenta leasing | G70: 46216 | H70: 4.1765035e+08 | I70: 21538319 | J70: =IF(H70="","N/D",H70-I70) -> 3.9611203e+08 | K70: =SUMIFS(Detalle_62!$F$14:$F$35,Detalle_62!$C$14:$C$35,E70) -> 3.8184539e+08 | L70: =IF(H70="","N/D",K70-J70) -> -14266642 | M70: 0.1422 | N70: =INDEX(Detalle_62!$J$14:$J$35,MATCH(E70,Detalle_62!$C$14:$C$35,0)) -> 0.14541789 | O70: =(N70-M70)*10000 -> 32.178864 | P70: 47506 | Q70: =INDEX(Detalle_62!$P$14:$P$35,MATCH(E70,Detalle_62!$C$14:$C$35,0)) -> 47503 | R70: =IF(P70="","N/D",IF(P70=Q70,"Sí","NO")) -> NO | S70: Saldo tras pago 23-abr-26; canon 23-jul-26 capital $21.538.319,02 / costo financiero $14.118.857,98. DTF.
A71: 15 | B71: 21 | C71: Banco de Bogotá Leasing | D71: 00556449288 | E71: BOG-L556449288 | F71: Estado de cuenta leasing | G71: 46213 | H71: 4.1773678e+08 | I71: 21542838 | J71: =IF(H71="","N/D",H71-I71) -> 3.9619394e+08 | K71: =SUMIFS(Detalle_62!$F$14:$F$35,Detalle_62!$C$14:$C$35,E71) -> 3.8264924e+08 | L71: =IF(H71="","N/D",K71-J71) -> -13544703 | M71: 0.1422 | N71: =INDEX(Detalle_62!$J$14:$J$35,MATCH(E71,Detalle_62!$C$14:$C$35,0)) -> 0.14541789 | O71: =(N71-M71)*10000 -> 32.178864 | P71: 47503 | Q71: =INDEX(Detalle_62!$P$14:$P$35,MATCH(E71,Detalle_62!$C$14:$C$35,0)) -> 47503 | R71: =IF(P71="","N/D",IF(P71=Q71,"Sí","NO")) -> Sí | S71: Saldo tras pago 20-abr-26; canon 20-jul-26 capital $21.542.838,16 / costo financiero $14.121.779,84. DTF.
A72: 16 | B72: p.22 + LEASING_9441-2_DAVIVIENDA.pdf | C72: Davivienda Leasing | D72: 000030001019441-2 | E72: DAV-L1019441 | F72: Factura leasing | G72: 46198 | I72: 0 | J72: =IF(H72="","N/D",H72-I72) -> N/D | K72: =SUMIFS(Detalle_62!$F$14:$F$35,Detalle_62!$C$14:$C$35,E72) -> 3.9858217e+08 | L72: =IF(H72="","N/D",K72-J72) -> N/D | M72: 0.1603 | N72: =INDEX(Detalle_62!$J$14:$J$35,MATCH(E72,Detalle_62!$C$14:$C$35,0)) -> 0.16713318 | O72: =(N72-M72)*10000 -> 68.331817 | Q72: =INDEX(Detalle_62!$P$14:$P$35,MATCH(E72,Detalle_62!$C$14:$C$35,0)) -> 47037 | R72: =IF(P72="","N/D",IF(P72=Q72,"Sí","NO")) -> N/D | S72: Canon 033 (13-jul-26): capital $12.327.298, intereses $5.062.372, seguro $1.263.646. Último pago 11-jun-26 canon 032 $1.029.562 (sólo intereses). Sin saldo de capital.
A73: 17 | B73: p.24 + LEASING_9448-3_DAVIVIENDA.pdf | C73: Davivienda Leasing | D73: 000030001019448-3 | E73: DAV-L1019448 | F73: Factura leasing | G73: 46191 | I73: 0 | J73: =IF(H73="","N/D",H73-I73) -> N/D | K73: =SUMIFS(Detalle_62!$F$14:$F$35,Detalle_62!$C$14:$C$35,E73) -> 3.2352969e+08 | L73: =IF(H73="","N/D",K73-J73) -> N/D | M73: 0.1593 | N73: =INDEX(Detalle_62!$J$14:$J$35,MATCH(E73,Detalle_62!$C$14:$C$35,0)) -> 0.16713318 | O73: =(N73-M73)*10000 -> 78.331817 | Q73: =INDEX(Detalle_62!$P$14:$P$35,MATCH(E73,Detalle_62!$C$14:$C$35,0)) -> 47098 | R73: =IF(P73="","N/D",IF(P73=Q73,"Sí","NO")) -> N/D | S73: Canon 031 (6-jul-26): capital $8.867.342, intereses $4.177.893. Último pago 5-jun-26 canon 030: capital $8.901.235, intereses $4.402.982. Sin saldo de capital.
F74: TOTAL obligaciones con saldo certificado | J74: =SUMIFS(J57:J73,$H$57:$H$73,"<>") -> 3.5993167e+10 | K74: =SUMIFS(K57:K73,$H$57:$H$73,"<>") -> 3.5821568e+10 | L74: =SUM(L57:L73) -> -1.715997e+08
F75: Diferencia detalle − banco: leasings Banco de Bogotá | L75: =SUMIFS(L57:L73,E57:E73,"BOG-L*") -> -1.7160825e+08
F76: Diferencia detalle − banco: créditos (redondeos) | L76: =L74-L75 -> 8553.7433
A78: B. Cobertura de confirmación – obligaciones del detalle 62 SIN certificado/extracto en el PDF
C79: Banco | D79: Obligación | E79: ID auditoría | F79: Tipo | K79: Saldo detalle 62
C80: BANCO POPULAR | D80: 631309940-2 | E80: POP-631309940 | F80: Crédito | K80: =SUMIFS(Detalle_62!$F$14:$F$35,Detalle_62!$C$14:$C$35,E80) -> 287500000
C81: BBVA | D81: 252059 | E81: BBVA-0141 | F81: Crédito | K81: =SUMIFS(Detalle_62!$F$14:$F$35,Detalle_62!$C$14:$C$35,E81) -> 4700000000
C82: BANCOLOMBIA S.A. | D82: LEASING 362095 | E82: BCL-L362095 | F82: Leasing | K82: =SUMIFS(Detalle_62!$F$14:$F$35,Detalle_62!$C$14:$C$35,E82) -> 497241599
C83: BANCOLOMBIA S.A. | D83: LEASING 336817 | E83: BCL-L336817 | F83: Leasing | K83: =SUMIFS(Detalle_62!$F$14:$F$35,Detalle_62!$C$14:$C$35,E83) -> 7.7008543e+08
C84: BANCOLOMBIA S.A. | D84: LEASING 331330 | E84: BCL-L331330 | F84: Leasing | K84: =SUMIFS(Detalle_62!$F$14:$F$35,Detalle_62!$C$14:$C$35,E84) -> 503693510
C85: Bancolombia | D85: Leasing 386735 (no está en detalle 62) | E85: BCL-L386735 | F85: Leasing | K85: =SUMIFS(Mayor_Mov!$F$5:$F$445,Mayor_Mov!$N$5:$N$445,E85)-SUMIFS(Mayor_Mov!$E$5:$E$445,Mayor_Mov!$N$5:$N$445,E85) -> 675837500
F86: Total sin certificado (detalle 62) | K86: =SUM(K80:K84) -> 6.7585205e+09
F87: % del saldo del detalle 62 cubierto con certificado/extracto | K87: =1-K86/Detalle_62!$F$36 -> 0.85042859
A89: C. Cruce de pagos/intereses según certificado vs registro contable (comprobantes del mayor)
C90: ID auditoría | D90: Concepto | E90: Documento contable | F90: Fecha | H90: Valor s/certificado | I90: Valor s/contabilidad | J90: Diferencia | S90: Comentario
C91: DAV-830624 | D91: Pago 21-mar-26 total aplicado (int. 445.207.872,43 + cap. 127,57) | E91: NI-00004268 | F91: =INDEX(Mayor_Mov!$H$5:$H$445,MATCH(E91,Mayor_Mov!$J$5:$J$445,0)) -> 46105 | H91: 445208000 | I91: =SUMIFS(Mayor_Mov!$E$5:$E$445,Mayor_Mov!$J$5:$J$445,E91,Mayor_Mov!$N$5:$N$445,C91) -> 445208000 | J91: =I91-H91 -> 0 | S91: El cliente reversa el total como interés; los $127,57 abonados a capital no se registran.
C92: DAV-607691 | D92: Pago 28-ene-26 total aplicado (int. 243.932.730,53 + cap. 269,47) | E92: NI-00004061 | F92: =INDEX(Mayor_Mov!$H$5:$H$445,MATCH(E92,Mayor_Mov!$J$5:$J$445,0)) -> 46051 | H92: 243933000 | I92: =SUMIFS(Mayor_Mov!$E$5:$E$445,Mayor_Mov!$J$5:$J$445,E92,Mayor_Mov!$N$5:$N$445,C92) -> 243933000 | J92: =I92-H92 -> 0 | S92: Capital $269,47 no registrado.
C93: DAV-569032 | D93: Pago 28-ene-26 total aplicado (int. 184.797.372,21 + cap. 627,79) | E93: NI-00004063 | F93: =INDEX(Mayor_Mov!$H$5:$H$445,MATCH(E93,Mayor_Mov!$J$5:$J$445,0)) -> 46051 | H93: 184798000 | I93: =SUMIFS(Mayor_Mov!$E$5:$E$445,Mayor_Mov!$J$5:$J$445,E93,Mayor_Mov!$N$5:$N$445,C93) -> 184798000 | J93: =I93-H93 -> 0 | S93: Capital $627,79 no registrado.
C94: DAV-607691 | D94: Intereses 28-ene a 28-jul-26 facturados | E94: NI-00004743 | F94: =INDEX(Mayor_Mov!$H$5:$H$445,MATCH(E94,Mayor_Mov!$J$5:$J$445,0)) -> 46231 | H94: 2.7229938e+08 | I94: =SUMIFS(Mayor_Mov!$E$5:$E$445,Mayor_Mov!$J$5:$J$445,E94,Mayor_Mov!$N$5:$N$445,C94) -> 272300000 | J94: =I94-H94 -> 617.95 | S94: Contabilidad reversa $272.300.000 (pago redondeado); $617,95 corresponden a capital.
C95: DAV-569032 | D95: Intereses 28-ene a 28-jul-26 facturados | E95: NI-00004745 | F95: =INDEX(Mayor_Mov!$H$5:$H$445,MATCH(E95,Mayor_Mov!$J$5:$J$445,0)) -> 46231 | H95: 2.0628721e+08 | I95: =SUMIFS(Mayor_Mov!$E$5:$E$445,Mayor_Mov!$J$5:$J$445,E95,Mayor_Mov!$N$5:$N$445,C95) -> 206288000 | J95: =I95-H95 -> 786.8 | S95: Contabilidad reversa $206.288.000; $786,80 corresponden a capital.
C96: BOG-856670629 | D96: Cuota 11 – capital | E96: CL-00000383 | F96: =INDEX(Mayor_Mov!$H$5:$H$445,MATCH(E96,Mayor_Mov!$J$5:$J$445,0)) -> 46100 | H96: 1.8216667e+08 | I96: =SUMIFS(Mayor_Mov!$E$5:$E$445,Mayor_Mov!$J$5:$J$445,E96,Mayor_Mov!$N$5:$N$445,C96) -> 182166667 | J96: =I96-H96 -> -0.53 | S96: Diferencia de redondeo del banco.
C97: BOG-856670629 | D97: Cuota 11 – intereses | E97: NI-00004260 | F97: =INDEX(Mayor_Mov!$H$5:$H$445,MATCH(E97,Mayor_Mov!$J$5:$J$445,0)) -> 46100 | H97: 56089116 | I97: =SUMIFS(Mayor_Mov!$E$5:$E$445,Mayor_Mov!$J$5:$J$445,E97,Mayor_Mov!$N$5:$N$445,C97) -> 56089116 | J97: =I97-H97 -> -0.47
C98: BOG-856670629 | D98: Cuota 12 – capital | E98: CL-00000410 | F98: =INDEX(Mayor_Mov!$H$5:$H$445,MATCH(E98,Mayor_Mov!$J$5:$J$445,0)) -> 46197 | H98: 182166667 | I98: =SUMIFS(Mayor_Mov!$E$5:$E$445,Mayor_Mov!$J$5:$J$445,E98,Mayor_Mov!$N$5:$N$445,C98) -> 182166667 | J98: =I98-H98 -> 0
C99: BOG-856670629 | D99: Cuota 12 – intereses | E99: NI-00004662 | F99: =INDEX(Mayor_Mov!$H$5:$H$445,MATCH(E99,Mayor_Mov!$J$5:$J$445,0)) -> 46203 | H99: 59390887 | I99: =SUMIFS(Mayor_Mov!$E$5:$E$445,Mayor_Mov!$J$5:$J$445,E99,Mayor_Mov!$N$5:$N$445,C99) -> 59390887 | J99: =I99-H99 -> -0.23
C100: BOG-453436746 | D100: Cuota 99 – capital | E100: CL-00000409 | F100: =INDEX(Mayor_Mov!$H$5:$H$445,MATCH(E100,Mayor_Mov!$J$5:$J$445,0)) -> 46197 | H100: 62500000 | I100: =SUMIFS(Mayor_Mov!$E$5:$E$445,Mayor_Mov!$J$5:$J$445,E100,Mayor_Mov!$N$5:$N$445,C100) -> 62500000 | J100: =I100-H100 -> -0.090000004
C101: BOG-453436746 | D101: Cuota 100 – capital | E101: CL-00000422 | F101: =INDEX(Mayor_Mov!$H$5:$H$445,MATCH(E101,Mayor_Mov!$J$5:$J$445,0)) -> 46230 | H101: 62500000 | I101: =SUMIFS(Mayor_Mov!$E$5:$E$445,Mayor_Mov!$J$5:$J$445,E101,Mayor_Mov!$N$5:$N$445,C101) -> 62500000 | J101: =I101-H101 -> 0 | S101: Intereses cuota 100 $38.894.999,71 coinciden con la descripción del CL-422 (gasto directo 53052020).
C102: BOG-858177259 | D102: Cuota mayo – capital | E102: CL-00000407 | F102: =INDEX(Mayor_Mov!$H$5:$H$445,MATCH(E102,Mayor_Mov!$J$5:$J$445,0)) -> 46164 | H102: 1.25e+08 | I102: =SUMIFS(Mayor_Mov!$E$5:$E$445,Mayor_Mov!$J$5:$J$445,E102,Mayor_Mov!$N$5:$N$445,C102) -> 125000000 | J102: =I102-H102 -> -0.56
C103: BOG-858177259 | D103: Cuota mayo – intereses | E103: NI-00004526 | F103: =INDEX(Mayor_Mov!$H$5:$H$445,MATCH(E103,Mayor_Mov!$J$5:$J$445,0)) -> 46164 | H103: 46619930 | I103: =SUMIFS(Mayor_Mov!$E$5:$E$445,Mayor_Mov!$J$5:$J$445,E103,Mayor_Mov!$N$5:$N$445,C103) -> 46619930 | J103: =I103-H103 -> -0.44
C104: BOG-1159383796 | D104: Crédito 1155297469 – intereses cuota 1 | E104: NI-00004402 | F104: =INDEX(Mayor_Mov!$H$5:$H$445,MATCH(E104,Mayor_Mov!$J$5:$J$445,0)) -> 46136 | H104: 2.5461056e+08 | I104: =SUMIFS(Mayor_Mov!$E$5:$E$445,Mayor_Mov!$J$5:$J$445,E104,Mayor_Mov!$N$5:$N$445,C104) -> 254610556 | J104: =I104-H104 -> 0.44999999
C105: BOG-1159383796 | D105: Crédito 1155297469 – intereses cuota 2 (14-jul) | E105: NI-00004736 | F105: =INDEX(Mayor_Mov!$H$5:$H$445,MATCH(E105,Mayor_Mov!$J$5:$J$445,0)) -> 46230 | H105: 299617500 | I105: =SUMIFS(Mayor_Mov!$E$5:$E$445,Mayor_Mov!$J$5:$J$445,E105,Mayor_Mov!$N$5:$N$445,C105) -> 299617499 | J105: =I105-H105 -> -1
C106: BOG-L557285005 | D106: Canon abr – capital | E106: CL-00000391 | F106: =INDEX(Mayor_Mov!$H$5:$H$445,MATCH(E106,Mayor_Mov!$J$5:$J$445,0)) -> 46136 | H106: 62648860 | I106: =SUMIFS(Mayor_Mov!$E$5:$E$445,Mayor_Mov!$J$5:$J$445,E106,Mayor_Mov!$N$5:$N$445,C106) -> 62648860 | J106: =I106-H106 -> 0
C107: BOG-L557285005 | D107: Canon abr – costo financiero | E107: NI-00004396 | F107: =INDEX(Mayor_Mov!$H$5:$H$445,MATCH(E107,Mayor_Mov!$J$5:$J$445,0)) -> 46136 | H107: 36783057 | I107: =SUMIFS(Mayor_Mov!$E$5:$E$445,Mayor_Mov!$J$5:$J$445,E107,Mayor_Mov!$N$5:$N$445,C107) -> 36783056 | J107: =I107-H107 -> -0.97
C108: BOG-L557285005 | D108: Canon jul – capital | E108: CL-00000429 | F108: =INDEX(Mayor_Mov!$H$5:$H$445,MATCH(E108,Mayor_Mov!$J$5:$J$445,0)) -> 46231 | H108: 62866117 | I108: =SUMIFS(Mayor_Mov!$E$5:$E$445,Mayor_Mov!$J$5:$J$445,E108,Mayor_Mov!$N$5:$N$445,C108) -> 62866117 | J108: =I108-H108 -> 0
C109: BOG-L557285005 | D109: Canon jul – costo financiero | E109: NI-00004740 | F109: =INDEX(Mayor_Mov!$H$5:$H$445,MATCH(E109,Mayor_Mov!$J$5:$J$445,0)) -> 46231 | H109: 39578632 | I109: =SUMIFS(Mayor_Mov!$E$5:$E$445,Mayor_Mov!$J$5:$J$445,E109,Mayor_Mov!$N$5:$N$445,C109) -> 39578631 | J109: =I109-H109 -> -0.88
C110: BOG-L556449064 | D110: Canon abr – capital | E110: CL-00000394 | F110: =INDEX(Mayor_Mov!$H$5:$H$445,MATCH(E110,Mayor_Mov!$J$5:$J$445,0)) -> 46136 | H110: 26079255 | I110: =SUMIFS(Mayor_Mov!$E$5:$E$445,Mayor_Mov!$J$5:$J$445,E110,Mayor_Mov!$N$5:$N$445,C110) -> 26079255 | J110: =I110-H110 -> 0
...

Sheet Tablas_Amortizacion
A1: REVISIÓN DE LAS TABLAS DE AMORTIZACIÓN DEL CLIENTE (papel 64) – 25 tablas
A2: Cómo leer esta hoja: primero el RESUMEN de las 25 tablas; debajo, cada tabla completa (usa los enlaces de la columna 'Anexo' del resumen).
A3: En cada tabla: columnas A–G BLANCAS = tabla tal como la entregó el cliente; columnas H–P AMARILLAS = recálculo de auditoría.
A4: Si 'Dif. saldo' = 0 la tabla está bien calculada. 'Tabla − banco' muestra cuánto se aleja la tabla de lo que realmente cobra el banco.
A6: RESUMEN DE LA REVISIÓN DE TABLAS
A7: Cada fila es una tabla. La última columna ('Observación de auditoría') explica en palabras lo encontrado.
A8: Revisión y recálculo de las tablas de amortización del cliente (papel 64) – corte 31-jul-2026
A9: Cada fila resume un anexo Tablas_Amortizacion. Saldo banco desde Pruebas_Auditoria (bloque 3); interés registrado desde Intereses_x_Obligacion.
A11: ID auditoría | B11: Hoja cliente | C11: Anexo | D11: Banco | E11: Contrato | F11: Tipo | G11: Valor inicial | H11: Fecha inicio | I11: Tasa pactada | J11: TIR tabla (periodo) | K11: TIR recalc. | L11: Dif. TIR (pb) | M11: Última cuota ≤ corte | N11: Saldo tabla 31-jul | O11: Saldo detalle 62 | P11: Tabla − detalle 62 | Q11: Saldo banco 31-jul | R11: Tabla − banco | S11: Interés tabla ene–jul 26 | T11: Interés registrado 2026 | U11: Registrado − tabla | V11: CP 12m según tabla | W11: CP detalle 62 | X11: CP tabla − detalle | Y11: Máx. dif. recálculo saldo | Z11: Costo amortizado cliente (col. W) 31-jul | AA11: C. amortizado − saldo tabla | AB11: Observación de auditoría
A12: DAV-L1019441 | B12: 9441 | C12: A01-9441 | D12: BANCO DAVIVIENDA | E12: _0001019441 | F12: Leasing | G12: =C52 -> 726630000 | H12: =C53 -> 45210 | I12: =C54 -> 60 MESES – IBR+4% | J12: =IF(ISNUMBER(C55),C55,"Por fila") -> 0.013357044 | K12: =IFERROR(C56,"N/A") -> 0.013357044 | L12: =IF(AND(ISNUMBER(J12),ISNUMBER(K12)),(K12-J12)*10000,"N/A") -> -2.6194324e-12 | M12: =I52 -> 46214 | N12: =I53 -> 3.9858217e+08 | O12: =IF(COUNTIF(Detalle_62!$C$14:$C$35,A12)>0,SUMIFS(Detalle_62!$F$14:$F$35,Detalle_62!$C$14:$C$35,A12),"No está") -> 3.9858217e+08 | P12: =IF(ISNUMBER(O12),N12-O12,"N/A") -> 0 | Q12: =IFERROR(INDEX(Pruebas_Auditoria!$L$144:$L$183,MATCH("DAV-L1019441",Pruebas_Auditoria!$A$144:$A$183,0)),"N/D") -> 399387154 | R12: =IF(ISNUMBER(Q12),N12-Q12,"N/D") -> -804986.79 | S12: =I55 -> 41709582 | T12: =IFERROR(INDEX(Intereses_x_Obligacion!$I:$I,MATCH("DAV-L1019441",Intereses_x_Obligacion!$A:$A,0)),"N/D") -> 31222019 | U12: =IF(ISNUMBER(T12),T12-S12,"N/D") -> -10487563 | V12: =MAX(I56,0) -> 1.5968177e+08 | W12: =IF(COUNTIF(Detalle_62!$C$14:$C$35,A12)>0,SUMIFS(Detalle_62!$M$14:$M$35,Detalle_62!$C$14:$C$35,A12),"No está") -> 194846536 | X12: =IF(ISNUMBER(W12),V12-W12,"N/A") -> -35164770 | Y12: =I57 -> 7.4505806e-09 | Z12: N/A | AA12: N/A | AB12: Tabla teórica a tasa fija (TIR mensual constante) y cuota fija $17.681.217; el banco liquida a tasa variable (canon 033: capital $12.327.298 / interés $5.062.372). El saldo del detalle 62 es el de esta tabla, no el del banco.
A13: DAV-L1019448 | B13: 9448 | C13: A02-9448 | D13: BANCO DAVIVIENDA | E13: _0001019448-3 | F13: Leasing | G13: =C128 -> 560790000 | H13: =C129 -> 45265 | I13: =C130 -> 60 MESES – IBR+4% | J13: =IF(ISNUMBER(C131),C131,"Por fila") -> 0.012666707 | K13: =IFERROR(C132,"N/A") -> 0.012666707 | L13: =IF(AND(ISNUMBER(J13),ISNUMBER(K13)),(K13-J13)*10000,"N/A") -> -1.244959e-09 | M13: =I128 -> 46208 | N13: =I129 -> 3.2352969e+08 | O13: =IF(COUNTIF(Detalle_62!$C$14:$C$35,A13)>0,SUMIFS(Detalle_62!$F$14:$F$35,Detalle_62!$C$14:$C$35,A13),"No está") -> 3.2352969e+08 | P13: =IF(ISNUMBER(O13),N13-O13,"N/A") -> 0 | Q13: =IFERROR(INDEX(Pruebas_Auditoria!$L$144:$L$183,MATCH("DAV-L1019448",Pruebas_Auditoria!$A$144:$A$183,0)),"N/D") -> 332999135 | R13: =IF(ISNUMBER(Q13),N13-Q13,"N/D") -> -9469446.5 | S13: =I131 -> 31864026 | T13: =IFERROR(INDEX(Intereses_x_Obligacion!$I:$I,MATCH("DAV-L1019448",Intereses_x_Obligacion!$A:$A,0)),"N/D") -> 25643813 | U13: =IF(ISNUMBER(T13),T13-S13,"N/D") -> -6220212.6 | V13: =MAX(I132,0) -> 1.1973915e+08 | W13: =IF(COUNTIF(Detalle_62!$C$14:$C$35,A13)>0,SUMIFS(Detalle_62!$M$14:$M$35,Detalle_62!$C$14:$C$35,A13),"No está") -> 1.4201465e+08 | X13: =IF(ISNUMBER(W13),V13-W13,"N/A") -> -22275501 | Y13: =I133 -> 9.4994903e-08 | Z13: N/A | AA13: N/A | AB13: Tabla teórica a tasa fija y cuota constante; el banco liquida a tasa variable (canon 031: capital $8.867.342 / interés $4.177.893). Detalle 62 = saldo de la tabla.
A14: DAV-L1021275 | B14: 2753 | C14: A03-2753 | D14: BANCO DAVIVIENDA | E14: 30001021275-3 | F14: Leasing | G14: =C204 -> 1876684264 | H14: =C205 -> 45679 | I14: =C206 -> 84 MESES – IBR TV + 2,3 | J14: =IF(ISNUMBER(C207),C207,"Por fila") -> 0.027362714 | K14: =IFERROR(C208,"N/A") -> 0.027362714 | L14: =IF(AND(ISNUMBER(J14),ISNUMBER(K14)),(K14-J14)*10000,"N/A") -> -5.4123372e-12 | M14: =I204 -> 46225 | N14: =I205 -> 1.8837122e+09 | O14: =IF(COUNTIF(Detalle_62!$C$14:$C$35,A14)>0,SUMIFS(Detalle_62!$F$14:$F$35,Detalle_62!$C$14:$C$35,A14),"No está") -> 1.8837122e+09 | P14: =IF(ISNUMBER(O14),N14-O14,"N/A") -> 0 | Q14: =IFERROR(INDEX(Pruebas_Auditoria!$L$144:$L$183,MATCH("DAV-L1021275",Pruebas_Auditoria!$A$144:$A$183,0)),"N/D") -> 1876684264 | R14: =IF(ISNUMBER(Q14),N14-Q14,"N/D") -> 7027954.1 | S14: =I207 -> 1.5442855e+08 | T14: =IFERROR(INDEX(Intereses_x_Obligacion!$I:$I,MATCH("DAV-L1021275",Intereses_x_Obligacion!$A:$A,0)),"N/D") -> 138538864 | U14: =IF(ISNUMBER(T14),T14-S14,"N/D") -> -15889687 | V14: =MAX(I208,0) -> 0 | W14: =IF(COUNTIF(Detalle_62!$C$14:$C$35,A14)>0,SUMIFS(Detalle_62!$M$14:$M$35,Detalle_62!$C$14:$C$35,A14),"No está") -> 0 | X14: =IF(ISNUMBER(W14),V14-W14,"N/A") -> 0 | Y14: =I209 -> 0 | Z14: N/A | AA14: N/A | AB14: La TIR de la tabla supera el canon de sólo intereses de los primeros 12 trimestres: la tabla capitaliza intereses y el saldo crece ($1.876,7 MM → $1.883,7 MM). El banco mantiene el capital en $1.876.684.264 y cobra 14,41% EA ($64,0 MM en jul-26 vs $51,5 MM en la tabla).
A15: DAV-830624 | B15: D-0624 | C15: A04-D-0624 | D15: BANCO DAVIVIENDA | E15: 457300830624 | F15: Crédito | G15: =C248 -> 7500000000 | H15: =C249 -> 45372 | I15: =C250 -> 240 meses – IBR 6MESES + 3 | J15: =IF(ISNUMBER(C251),C251,"Por fila") -> Por fila | K15: =IFERROR(C252,"N/A") -> N/A | L15: =IF(AND(ISNUMBER(J15),ISNUMBER(K15)),(K15-J15)*10000,"N/A") -> N/A | M15: =I248 -> 46224 | N15: =I249 -> 7500000000 | O15: =IF(COUNTIF(Detalle_62!$C$14:$C$35,A15)>0,SUMIFS(Detalle_62!$F$14:$F$35,Detalle_62!$C$14:$C$35,A15),"No está") -> 7500000000 | P15: =IF(ISNUMBER(O15),N15-O15,"N/A") -> 0 | Q15: =IFERROR(INDEX(Pruebas_Auditoria!$L$144:$L$183,MATCH("DAV-830624",Pruebas_Auditoria!$A$144:$A$183,0)),"N/D") -> 7.4999985e+09 | R15: =IF(ISNUMBER(Q15),N15-Q15,"N/D") -> 1496.75 | S15: =I251 -> 639243750 | T15: =IFERROR(INDEX(Intereses_x_Obligacion!$I:$I,MATCH("DAV-830624",Intereses_x_Obligacion!$A:$A,0)),"N/D") -> 586251750 | U15: =IF(ISNUMBER(T15),T15-S15,"N/D") -> -52992000 | V15: =MAX(I252,0) -> 0 | W15: =IF(COUNTIF(Detalle_62!$C$14:$C$35,A15)>0,SUMIFS(Detalle_62!$M$14:$M$35,Detalle_62!$C$14:$C$35,A15),"No está") -> 0 | X15: =IF(ISNUMBER(W15),V15-W15,"N/A") -> 0 | Y15: =I253 -> 3.5762787e-07 | Z15: 5259837500 | AA15: =IF(ISNUMBER(Z15),Z15-N15,"N/A") -> -2240162500 | AB15: Interés mensual simple con IBR 6M + 3 pts / 12; el banco liquida semestre vencido a 15,51% EA. La columna 'medición al costo' (costo amortizado) resta los intereses del saldo: error de fórmula (ver columna Z).
A16: DAV-607691 | B16: D-7691 | C16: A05-D-7691 | D16: BANCO DAVIVIENDA | E16: 457300607691 | F16: Crédito | G16: =C504 -> 3960000000 | H16: =C505 -> 44405 | I16: =C506 -> 240 meses – IBR 6MESES +3,4 | J16: =IF(ISNUMBER(C507),C507,"Por fila") -> Por fila | K16: =IFERROR(C508,"N/A") -> N/A | L16: =IF(AND(ISNUMBER(J16),ISNUMBER(K16)),(K16-J16)*10000,"N/A") -> N/A | M16: =I504 -> 46231 | N16: =I505 -> 3960000000 | O16: =IF(COUNTIF(Detalle_62!$C$14:$C$35,A16)>0,SUMIFS(Detalle_62!$F$14:$F$35,Detalle_62!$C$14:$C$35,A16),"No está") -> 3960000000 | P16: =IF(ISNUMBER(O16),N16-O16,"N/A") -> 0 | Q16: =IFERROR(INDEX(Pruebas_Auditoria!$L$144:$L$183,MATCH("DAV-607691",Pruebas_Auditoria!$A$144:$A$183,0)),"N/D") -> 3.9599978e+09 | R16: =IF(ISNUMBER(Q16),N16-Q16,"N/D") -> 2182.05 | S16: =I507 -> 346760700 | T16: =IFERROR(INDEX(Intereses_x_Obligacion!$I:$I,MATCH("DAV-607691",Intereses_x_Obligacion!$A:$A,0)),"N/D") -> 309646400 | U16: =IF(ISNUMBER(T16),T16-S16,"N/D") -> -37114300 | V16: =MAX(I508,0) -> 0 | W16: =IF(COUNTIF(Detalle_62!$C$14:$C$35,A16)>0,SUMIFS(Detalle_62!$M$14:$M$35,Detalle_62!$C$14:$C$35,A16),"No está") -> 0 | X16: =IF(ISNUMBER(W16),V16-W16,"N/A") -> 0 | Y16: =I509 -> 2.1457672e-06 | Z16: 4.234723e+09 | AA16: =IF(ISNUMBER(Z16),Z16-N16,"N/A") -> 2.7472299e+08 | AB16: Interés mensual simple con IBR 6M + 3 pts; el contrato es IBR + 3,40 y el banco factura semestral. Columna de costo amortizado con el mismo error de fórmula (ver columna Z).
A17: DAV-569032 | B17: D-9032 | C17: A06-D-9032 | D17: BANCO DAVIVIENDA | E17: 457300569032 | F17: Crédito | G17: =C760 -> 3000000000 | H17: =C761 -> 44405 | I17: =C762 -> 240 meses – IBR 6MESES +3,4 | J17: =IF(ISNUMBER(C763),C763,"Por fila") -> Por fila | K17: =IFERROR(C764,"N/A") -> N/A | L17: =IF(AND(ISNUMBER(J17),ISNUMBER(K17)),(K17-J17)*10000,"N/A") -> N/A | M17: =I760 -> 46231 | N17: =I761 -> 3000000000 | O17: =IF(COUNTIF(Detalle_62!$C$14:$C$35,A17)>0,SUMIFS(Detalle_62!$F$14:$F$35,Detalle_62!$C$14:$C$35,A17),"No está") -> 3000000000 | P17: =IF(ISNUMBER(O17),N17-O17,"N/A") -> 0 | Q17: =IFERROR(INDEX(Pruebas_Auditoria!$L$144:$L$183,MATCH("DAV-569032",Pruebas_Auditoria!$A$144:$A$183,0)),"N/D") -> 2999995157 | R17: =IF(ISNUMBER(Q17),N17-Q17,"N/D") -> 4843 | S17: =I763 -> 262697500 | T17: =IFERROR(INDEX(Intereses_x_Obligacion!$I:$I,MATCH("DAV-569032",Intereses_x_Obligacion!$A:$A,0)),"N/D") -> 234581000 | U17: =IF(ISNUMBER(T17),T17-S17,"N/D") -> -28116500 | V17: =MAX(I764,0) -> 0 | W17: =IF(COUNTIF(Detalle_62!$C$14:$C$35,A17)>0,SUMIFS(Detalle_62!$M$14:$M$35,Detalle_62!$C$14:$C$35,A17),"No está") -> 0 | X17: =IF(ISNUMBER(W17),V17-W17,"N/A") -> 0 | Y17: =I765 -> 9.2387199e-07 | Z17: 3.2081235e+09 | AA17: =IF(ISNUMBER(Z17),Z17-N17,"N/A") -> 2.0812348e+08 | AB17: Igual que 607691: puntos adicionales de la tabla (3%) distintos al contrato (3,40%); costo amortizado mal formulado.
A18: BOG-453436746 | B18: B-6746 | C18: A07-B-6746 | D18: BANCO BOGOTA | E18: 453436746 | F18: Crédito | G18: =C1016 -> 7500000000 | H18: =C1017 -> 43207 | I18: =C1018 -> 144 meses – IBR +4,70 | J18: =IF(ISNUMBER(C1019),C1019,"Por fila") -> Por fila | K18: =IFERROR(C1020,"N/A") -> N/A | L18: =IF(AND(ISNUMBER(J18),ISNUMBER(K18)),(K18-J18)*10000,"N/A") -> N/A | M18: =I1016 -> 46220 | N18: =I1017 -> 2937500000 | O18: =IF(COUNTIF(Detalle_62!$C$14:$C$35,A18)>0,SUMIFS(Detalle_62!$F$14:$F$35,Detalle_62!$C$14:$C$35,A18),"No está") -> 2937500000 | P18: =IF(ISNUMBER(O18),N18-O18,"N/A") -> 0 | Q18: =IFERROR(INDEX(Pruebas_Auditoria!$L$144:$L$183,MATCH("BOG-453436746",Pruebas_Auditoria!$A$144:$A$183,0)),"N/D") -> 2.9375e+09 | R18: =IF(ISNUMBER(Q18),N18-Q18,"N/D") -> 22.61 | S18: =I1019 -> 2.8421922e+08 | T18: =IFERROR(INDEX(Intereses_x_Obligacion!$I:$I,MATCH("BOG-453436746",Intereses_x_Obligacion!$A:$A,0)),"N/D") -> 2.3229766e+08 | U18: =IF(ISNUMBER(T18),T18-S18,"N/D") -> -51921555 | V18: =MAX(I1020,0) -> 750000000 | W18: =IF(COUNTIF(Detalle_62!$C$14:$C$35,A18)>0,SUMIFS(Detalle_62!$M$14:$M$35,Detalle_62!$C$14:$C$35,A18),"No está") -> 750000000 | X18: =IF(ISNUMBER(W18),V18-W18,"N/A") -> 0 | Y18: =I1021 -> 0 | Z18: 3.2226743e+09 | AA18: =IF(ISNUMBER(Z18),Z18-N18,"N/A") -> 2.8517427e+08 | AB18: Capital fijo $62,5 MM mensual coincide con el banco; el interés de la tabla usa el IBR proyectado.
A19: BOG-856670629 | B19: B-0629 | C19: A08-B-0629 | D19: BANCO DE BOGOTA | E19: 856670629 | F19: Crédito | G19: =C1178 -> 2186000000 | H19: =C1179 -> 45098 | I19: =C1180 -> 60 meses – IBR(3M) + 3,2% | J19: =IF(ISNUMBER(C1181),C1181,"Por fila") -> Por fila | K19: =IFERROR(C1182,"N/A") -> N/A | L19: =IF(AND(ISNUMBER(J19),ISNUMBER(K19)),(K19-J19)*10000,"N/A") -> N/A | M19: =I1178 -> 46224 | N19: =I1179 -> 1457333336 | O19: =IF(COUNTIF(Detalle_62!$C$14:$C$35,A19)>0,SUMIFS(Detalle_62!$F$14:$F$35,Detalle_62!$C$14:$C$35,A19),"No está") -> 1457333332 | P19: =IF(ISNUMBER(O19),N19-O19,"N/A") -> 4 | Q19: =IFERROR(INDEX(Pruebas_Auditoria!$L$144:$L$183,MATCH("BOG-856670629",Pruebas_Auditoria!$A$144:$A$183,0)),"N/D") -> 1.4573333e+09 | R19: =IF(ISNUMBER(Q19),N19-Q19,"N/D") -> 10.41 | S19: =I1181 -> 1.4013201e+08 | T19: =IFERROR(INDEX(Intereses_x_Obligacion!$I:$I,MATCH("BOG-856670629",Intereses_x_Obligacion!$A:$A,0)),"N/D") -> 133305619 | U19: =IF(ISNUMBER(T19),T19-S19,"N/D") -> -6826393.2 | V19: =MAX(I1182,0) -> 728666668 | W19: =IF(COUNTIF(Detalle_62!$C$14:$C$35,A19)>0,SUMIFS(Detalle_62!$M$14:$M$35,Detalle_62!$C$14:$C$35,A19),"No está") -> 750000000 | X19: =IF(ISNUMBER(W19),V19-W19,"N/A") -> -21333332 | Y19: =I1183 -> 0 | Z19: 1.4730309e+09 | AA19: =IF(ISNUMBER(Z19),Z19-N19,"N/A") -> 15697543 | AB19: Capital trimestral $182,2 MM coincide con el banco (diferencia de redondeo en el saldo).
A20: BOG-858177259 | B20: B-7259 | C20: A09-B-7259 | D20: BANCO DE BOGOTA | E20: 858177259 | F20: Crédito | G20: =C1254 -> 2500000000 | H20: =C1255 -> 45163 | I20: =C1256 -> 60 meses – IBR(3M) + 4,6% | J20: =IF(ISNUMBER(C1257),C1257,"Por fila") -> Por fila | K20: =IFERROR(C1258,"N/A") -> 0.012817645 | L20: =IF(AND(ISNUMBER(J20),ISNUMBER(K20)),(K20-J20)*10000,"N/A") -> N/A | M20: =I1254 -> 46224 | N20: =I1255 -> 1125000000 | O20: =IF(COUNTIF(Detalle_62!$C$14:$C$35,A20)>0,SUMIFS(Detalle_62!$F$14:$F$35,Detalle_62!$C$14:$C$35,A20),"No está") -> 1125000000 | P20: =IF(ISNUMBER(O20),N20-O20,"N/A") -> 0 | Q20: =IFERROR(INDEX(Pruebas_Auditoria!$L$144:$L$183,MATCH("BOG-858177259",Pruebas_Auditoria!$A$144:$A$183,0)),"N/D") -> 1.125e+09 | R20: =IF(ISNUMBER(Q20),N20-Q20,"N/D") -> 3.5899999 | S20: =I1257 -> 108575000 | T20: =IFERROR(INDEX(Intereses_x_Obligacion!$I:$I,MATCH("BOG-858177259",Intereses_x_Obligacion!$A:$A,0)),"N/D") -> 108941341 | U20: =IF(ISNUMBER(T20),T20-S20,"N/D") -> 366341 | V20: =MAX(I1258,0) -> 500000000 | W20: =IF(COUNTIF(Detalle_62!$C$14:$C$35,A20)>0,SUMIFS(Detalle_62!$M$14:$M$35,Detalle_62!$C$14:$C$35,A20),"No está") -> 500000000 | X20: =IF(ISNUMBER(W20),V20-W20,"N/A") -> 0 | Y20: =I1259 -> 0 | Z20: 1.1354471e+09 | AA20: =IF(ISNUMBER(Z20),Z20-N20,"N/A") -> 10447091 | AB20: Capital trimestral $125 MM coincide con el banco.
A21: BOG-1155297469 | B21: B-7469 | C21: A10-B-7469 | D21: BANCO DE BOGOTA | E21: 1155297469 | F21: Crédito | G21: =C1330 -> 10000000000 | H21: =C1331 -> 46036 | I21: =C1332 -> 6 meses – IBR(3M) + 0,8% | J21: =IF(ISNUMBER(C1333),C1333,"Por fila") -> Por fila | K21: =IFERROR(C1334,"N/A") -> 0.01006648 | L21: =IF(AND(ISNUMBER(J21),ISNUMBER(K21)),(K21-J21)*10000,"N/A") -> N/A | M21: =I1330 -> 46217 | N21: =I1331 -> 0 | O21: =IF(COUNTIF(Detalle_62!$C$14:$C$35,A21)>0,SUMIFS(Detalle_62!$F$14:$F$35,Detalle_62!$C$14:$C$35,A21),"No está") -> No está | P21: =IF(ISNUMBER(O21),N21-O21,"N/A") -> N/A | Q21: =IFERROR(INDEX(Pruebas_Auditoria!$L$144:$L$183,MATCH("BOG-1155297469",Pruebas_Auditoria!$A$144:$A$183,0)),"N/D") -> N/D | R21: =IF(ISNUMBER(Q21),N21-Q21,"N/D") -> N/D | S21: =I1333 -> 604300000 | T21: =IFERROR(INDEX(Intereses_x_Obligacion!$I:$I,MATCH("BOG-1155297469",Intereses_x_Obligacion!$A:$A,0)),"N/D") -> N/D | U21: =IF(ISNUMBER(T21),T21-S21,"N/D") -> N/D | V21: =MAX(I1334,0) -> 0 | W21: =IF(COUNTIF(Detalle_62!$C$14:$C$35,A21)>0,SUMIFS(Detalle_62!$M$14:$M$35,Detalle_62!$C$14:$C$35,A21),"No está") -> No está | X21: =IF(ISNUMBER(W21),V21-W21,"N/A") -> N/A | Y21: =I1335 -> 0 | Z21: 0 | AA21: =IF(ISNUMBER(Z21),Z21-N21,"N/A") -> 0 | AB21: Tabla del crédito cancelado/prorrogado el 14/29-jul-26.
A22: BOG-1159383796 | B22: Hoja2 | C22: A11-Hoja2 | D22: BANCO DE BOGOTA | E22: 1159383796 | F22: Crédito | G22: =C1352 -> 10000000000 | H22: =C1353 -> 46225 | I22: =C1354 -> 6 meses – IBR(3M) + 0,8% | J22: =IF(ISNUMBER(C1355),C1355,"Por fila") -> Por fila | K22: =IFERROR(C1356,"N/A") -> 0.01006648 | L22: =IF(AND(ISNUMBER(J22),ISNUMBER(K22)),(K22-J22)*10000,"N/A") -> N/A | M22: =I1352 -> 46225 | N22: =I1353 -> 10000000000 | O22: =IF(COUNTIF(Detalle_62!$C$14:$C$35,A22)>0,SUMIFS(Detalle_62!$F$14:$F$35,Detalle_62!$C$14:$C$35,A22),"No está") -> 10000000000 | P22: =IF(ISNUMBER(O22),N22-O22,"N/A") -> 0 | Q22: =IFERROR(INDEX(Pruebas_Auditoria!$L$144:$L$183,MATCH("BOG-1159383796",Pruebas_Auditoria!$A$144:$A$183,0)),"N/D") -> 10000000000 | R22: =IF(ISNUMBER(Q22),N22-Q22,"N/D") -> 0 | S22: =I1355 -> 604300000 | T22: =IFERROR(INDEX(Intereses_x_Obligacion!$I:$I,MATCH("BOG-1159383796",Intereses_x_Obligacion!$A:$A,0)),"N/D") -> 554228055 | U22: =IF(ISNUMBER(T22),T22-S22,"N/D") -> -50071945 | V22: =MAX(I1356,0) -> 0 | W22: =IF(COUNTIF(Detalle_62!$C$14:$C$35,A22)>0,SUMIFS(Detalle_62!$M$14:$M$35,Detalle_62!$C$14:$C$35,A22),"No está") -> 10000000000 | X22: =IF(ISNUMBER(W22),V22-W22,"N/A") -> -10000000000 | Y22: =I1357 -> 0 | Z22: 0 | AA22: =IF(ISNUMBER(Z22),Z22-N22,"N/A") -> -10000000000 | AB22: La hoja 'Hoja2' es copia de la tabla del 1155297469: fechas feb–jul 2026 anteriores al inicio (22-jul-26) y saldo cero al 14-jul. No sirve como tabla del crédito nuevo.
A23: BOG-L556449224 | B23: 9224 | C23: A12-9224 | D23: BANCO DE BOGOTA | E23: 556449224 | F23: Leasing | G23: =C1374 -> 569902000 | H23: =C1375 -> 44946 | I23: =C1376 -> 28 TRIMESTRES – DTF+3,57% | J23: =IF(ISNUMBER(C1377),C1377,"Por fila") -> 0.036189196 | K23: =IFERROR(C1378,"N/A") -> 0.036189196 | L23: =IF(AND(ISNUMBER(J23),ISNUMBER(K23)),(K23-J23)*10000,"N/A") -> -1.179612e-11 | M23: =I1374 -> 46223 | N23: =I1375 -> 3.8184539e+08 | O23: =IF(COUNTIF(Detalle_62!$C$14:$C$35,A23)>0,SUMIFS(Detalle_62!$F$14:$F$35,Detalle_62!$C$14:$C$35,A23),"No está") -> 3.8184539e+08 | P23: =IF(ISNUMBER(O23),N23-O23,"N/A") -> 0 | Q23: =IFERROR(INDEX(Pruebas_Auditoria!$L$144:$L$183,MATCH("BOG-L556449224",Pruebas_Auditoria!$A$144:$A$183,0)),"N/D") -> 3.9611203e+08 | R23: =IF(ISNUMBER(Q23),N23-Q23,"N/D") -> -14266642 | S23: =I1377 -> 45776937 | T23: =IFERROR(INDEX(Intereses_x_Obligacion!$I:$I,MATCH("BOG-L556449224",Intereses_x_Obligacion!$A:$A,0)),"N/D") -> 31068671 | U23: =IF(ISNUMBER(T23),T23-S23,"N/D") -> -14708266 | V23: =MAX(I1378,0) -> 89122277 | W23: =IF(COUNTIF(Detalle_62!$C$14:$C$35,A23)>0,SUMIFS(Detalle_62!$M$14:$M$35,Detalle_62!$C$14:$C$35,A23),"No está") -> 1.7563157e+08 | X23: =IF(ISNUMBER(W23),V23-W23,"N/A") -> -86509292 | Y23: =I1379 -> 4.4703484e-08 | Z23: N/A | AA23: N/A | AB23: Tabla a tasa fija; el banco liquida DTF variable: saldo certificado mayor que el de la tabla.
A24: BOG-L556449180 | B24: 9180 | C24: A13-9180 | D24: BANCO DE BOGOTA | E24: 556449180 | F24: Leasing | G24: =C1418 -> 569902000 | H24: =C1419 -> 44949 | I24: =C1420 -> 28 TRIMESTRES – DTF+3,57% | J24: =IF(ISNUMBER(C1421),C1421,"Por fila") -> 0.036189196 | K24: =IFERROR(C1422,"N/A") -> 0.036189196 | L24: =IF(AND(ISNUMBER(J24),ISNUMBER(K24)),(K24-J24)*10000,"N/A") -> -1.179612e-11 | M24: =I1418 -> 46226 | N24: =I1419 -> 3.8184539e+08 | O24: =IF(COUNTIF(Detalle_62!$C$14:$C$35,A24)>0,SUMIFS(Detalle_62!$F$14:$F$35,Detalle_62!$C$14:$C$35,A24),"No está") -> 3.8184539e+08 | P24: =IF(ISNUMBER(O24),N24-O24,"N/A") -> 0 | Q24: =IFERROR(INDEX(Pruebas_Auditoria!$L$144:$L$183,MATCH("BOG-L556449180",Pruebas_Auditoria!$A$144:$A$183,0)),"N/D") -> 3.9611203e+08 | R24: =IF(ISNUMBER(Q24),N24-Q24,"N/D") -> -14266642 | S24: =I1421 -> 45776937 | T24: =IFERROR(INDEX(Intereses_x_Obligacion!$I:$I,MATCH("BOG-L556449180",Intereses_x_Obligacion!$A:$A,0)),"N/D") -> 31068672 | U24: =IF(ISNUMBER(T24),T24-S24,"N/D") -> -14708265 | V24: =MAX(I1422,0) -> 89122277 | W24: =IF(COUNTIF(Detalle_62!$C$14:$C$35,A24)>0,SUMIFS(Detalle_62!$M$14:$M$35,Detalle_62!$C$14:$C$35,A24),"No está") -> 1.7563157e+08 | X24: =IF(ISNUMBER(W24),V24-W24,"N/A") -> -86509292 | Y24: =I1423 -> 4.4703484e-08 | Z24: N/A | AA24: N/A | AB24: Tabla a tasa fija; el banco liquida DTF variable: saldo certificado mayor que el de la tabla.
A25: BOG-L556449117 | B25: 9117 | C25: A14-9117 | D25: BANCO DE BOGOTA | E25: 556449117 | F25: Leasing | G25: =C1462 -> 569902000 | H25: =C1463 -> 44404 | I25: =C1464 -> 28 TRIMESTRES – DTF+3,57% | J25: =IF(ISNUMBER(C1465),C1465,"Por fila") -> 0.0059356385 | K25: =IFERROR(C1466,"N/A") -> 0.0059356385 | L25: =IF(AND(ISNUMBER(J25),ISNUMBER(K25)),(K25-J25)*10000,"N/A") -> 2.6801478e-12 | M25: =I1462 -> 46230 | N25: =I1463 -> 1.9672018e+08 | O25: =IF(COUNTIF(Detalle_62!$C$14:$C$35,A25)>0,SUMIFS(Detalle_62!$F$14:$F$35,Detalle_62!$C$14:$C$35,A25),"No está") -> 1.9672018e+08 | P25: =IF(ISNUMBER(O25),N25-O25,"N/A") -> 0 | Q25: =IFERROR(INDEX(Pruebas_Auditoria!$L$144:$L$183,MATCH("BOG-L556449117",Pruebas_Auditoria!$A$144:$A$183,0)),"N/D") -> 2.5367211e+08 | R25: =IF(ISNUMBER(Q25),N25-Q25,"N/D") -> -56951927 | S25: =I1465 -> 4327677.9 | T25: =IFERROR(INDEX(Intereses_x_Obligacion!$I:$I,MATCH("BOG-L556449117",Intereses_x_Obligacion!$A:$A,0)),"N/D") -> 28058555 | U25: =IF(ISNUMBER(T25),T25-S25,"N/D") -> 23730877 | V25: =MAX(I1466,0) -> 94380151 | W25: =IF(COUNTIF(Detalle_62!$C$14:$C$35,A25)>0,SUMIFS(Detalle_62!$M$14:$M$35,Detalle_62!$C$14:$C$35,A25),"No está") -> 1.7563157e+08 | X25: =IF(ISNUMBER(W25),V25-W25,"N/A") -> -81251418 | Y25: =I1467 -> 4.4703484e-08 | Z25: N/A | AA25: N/A | AB25: Tabla a tasa fija con TIR muy baja (0,59% trimestral) y capital acelerado: saldo $57 MM por debajo del banco.
A26: BOG-L556449064 | B26: 9064 | C26: A15-9064 | D26: BANCO DE BOGOTA | E26: 556449064 | F26: Leasing | G26: =C1506 -> 569902000 | H26: =C1507 -> 44404 | I26: =C1508 -> 28 TRIMESTRES – DTF+3,57% | J26: =IF(ISNUMBER(C1509),C1509,"Por fila") -> 0.0059356385 | K26: =IFERROR(C1510,"N/A") -> 0.0059356385 | L26: =IF(AND(ISNUMBER(J26),ISNUMBER(K26)),(K26-J26)*10000,"N/A") -> 2.6801478e-12 | M26: =I1506 -> 46230 | N26: =I1507 -> 1.9672018e+08 | O26: =IF(COUNTIF(Detalle_62!$C$14:$C$35,A26)>0,SUMIFS(Detalle_62!$F$14:$F$35,Detalle_62!$C$14:$C$35,A26),"No está") -> 1.9672018e+08 | P26: =IF(ISNUMBER(O26),N26-O26,"N/A") -> 0 | Q26: =IFERROR(INDEX(Pruebas_Auditoria!$L$144:$L$183,MATCH("BOG-L556449064",Pruebas_Auditoria!$A$144:$A$183,0)),"N/D") -> 2.536721e+08 | R26: =IF(ISNUMBER(Q26),N26-Q26,"N/D") -> -56951926 | S26: =I1509 -> 4327677.9 | T26: =IFERROR(INDEX(Intereses_x_Obligacion!$I:$I,MATCH("BOG-L556449064",Intereses_x_Obligacion!$A:$A,0)),"N/D") -> 28058555 | U26: =IF(ISNUMBER(T26),T26-S26,"N/D") -> 23730877 | V26: =MAX(I1510,0) -> 94380151 | W26: =IF(COUNTIF(Detalle_62!$C$14:$C$35,A26)>0,SUMIFS(Detalle_62!$M$14:$M$35,Detalle_62!$C$14:$C$35,A26),"No está") -> 1.7563157e+08 | X26: =IF(ISNUMBER(W26),V26-W26,"N/A") -> -81251418 | Y26: =I1511 -> 4.4703484e-08 | Z26: N/A | AA26: N/A | AB26: Tabla a tasa fija con TIR muy baja (0,59% trimestral) y capital acelerado: saldo $57 MM por debajo del banco.
A27: BOG-L556449288 | B27: 9299 | C27: A16-9299 | D27: BANCO DE BOGOTA | E27: 556449288 | F27: Leasing | G27: =C1550 -> 569902000 | H27: =C1551 -> 44949 | I27: =C1552 -> 28 TRIMESTRES – DTF+3,57% | J27: =IF(ISNUMBER(C1553),C1553,"Por fila") -> 0.036728133 | K27: =IFERROR(C1554,"N/A") -> 0.036728133 | L27: =IF(AND(ISNUMBER(J27),ISNUMBER(K27)),(K27-J27)*10000,"N/A") -> -4.9960036e-12 | M27: =I1550 -> 46226 | N27: =I1551 -> 3.8264924e+08 | O27: =IF(COUNTIF(Detalle_62!$C$14:$C$35,A27)>0,SUMIFS(Detalle_62!$F$14:$F$35,Detalle_62!$C$14:$C$35,A27),"No está") -> 3.8264924e+08 | P27: =IF(ISNUMBER(O27),N27-O27,"N/A") -> 0 | Q27: =IFERROR(INDEX(Pruebas_Auditoria!$L$144:$L$183,MATCH("BOG-L556449288",Pruebas_Auditoria!$A$144:$A$183,0)),"N/D") -> 3.9619394e+08 | R27: =IF(ISNUMBER(Q27),N27-Q27,"N/D") -> -13544703 | S27: =I1553 -> 46536705 | T27: =IFERROR(INDEX(Intereses_x_Obligacion!$I:$I,MATCH("BOG-L556449288",Intereses_x_Obligacion!$A:$A,0)),"N/D") -> 30902950 | U27: =IF(ISNUMBER(T27),T27-S27,"N/D") -> -15633755 | V27: =MAX(I1554,0) -> 89056070 | W27: =IF(COUNTIF(Detalle_62!$C$14:$C$35,A27)>0,SUMIFS(Detalle_62!$M$14:$M$35,Detalle_62!$C$14:$C$35,A27),"No está") -> 1.7563157e+08 | X27: =IF(ISNUMBER(W27),V27-W27,"N/A") -> -86575499 | Y27: =I1555 -> 1.4901161e-08 | Z27: N/A | AA27: N/A | AB27: Tabla a tasa fija; el banco liquida DTF variable: saldo certificado mayor que el de la tabla.
A28: BOG-L557285005 | B28: 5005 | C28: A17-5005 | D28: BANCO DE BOGOTA | E28: 557285005 | F28: Leasing | G28: =C1594 -> 1622075804 | H28: =C1595 -> 44764 | I28: =C1596 -> 24 TRIMESTRES – IBR(3M)+3,78% | J28: =IF(ISNUMBER(C1597),C1597,"Por fila") -> 0.031890496 | K28: =IFERROR(C1598,"N/A") -> 0.031890496 | L28: =IF(AND(ISNUMBER(J28),ISNUMBER(K28)),(K28-J28)*10000,"N/A") -> 0 | M28: =I1594 -> 46225 | N28: =I1595 -> 9.6862047e+08 | O28: =IF(COUNTIF(Detalle_62!$C$14:$C$35,A28)>0,SUMIFS(Detalle_62!$F$14:$F$35,Detalle_62!$C$14:$C$35,A28),"No está") -> 9.6862047e+08 | P28: =IF(ISNUMBER(O28),N28-O28,"N/A") -> 0 | Q28: =IFERROR(INDEX(Pruebas_Auditoria!$L$144:$L$183,MATCH("BOG-L557285005",Pruebas_Auditoria!$A$144:$A$183,0)),"N/D") -> 9.8424689e+08 | R28: =IF(ISNUMBER(Q28),N28-Q28,"N/D") -> -15626414 | S28: =I1597 -> 1.0472844e+08 | T28: =IFERROR(INDEX(Intereses_x_Obligacion!$I:$I,MATCH("BOG-L557285005",Intereses_x_Obligacion!$A:$A,0)),"N/D") -> 89512386 | U28: =IF(ISNUMBER(T28),T28-S28,"N/D") -> -15216056 | V28: =MAX(I1598,0) -> 2.7853765e+08 | W28: =IF(COUNTIF(Detalle_62!$C$14:$C$35,A28)>0,SUMIFS(Detalle_62!$M$14:$M$35,Detalle_62!$C$14:$C$35,A28),"No está") -> 722980190 | X28: =IF(ISNUMBER(W28),V28-W28,"N/A") -> -4.4444254e+08 | Y28: =I1599 -> 1.937151e-07 | Z28: N/A | AA28: N/A | AB28: Tabla a tasa fija; el banco liquida IBR 3M variable: saldo certificado mayor que el de la tabla.
A29: POP-631309940 | B29: P-9940 | C29: A18-P-9940 | D29: BANCO POPULAR | E29: 631309940-2 | F29: Crédito | G29: =C1634 -> 2300000000 | H29: =C1635 -> 44547 | I29: =C1636 -> 60 meses – IBR 3MESES +2,4 | J29: =IF(ISNUMBER(C1637),C1637,"Por fila") -> Por fila | K29: =IFERROR(C1638,"N/A") -> N/A | L29: =IF(AND(ISNUMBER(J29),ISNUMBER(K29)),(K29-J29)*10000,"N/A") -> N/A | M29: =I1634 -> 46220 | N29: =I1635 -> 287500000 | O29: =IF(COUNTIF(Detalle_62!$C$14:$C$35,A29)>0,SUMIFS(Detalle_62!$F$14:$F$35,Detalle_62!$C$14:$C$35,A29),"No está") -> 287500000 | P29: =IF(ISNUMBER(O29),N29-O29,"N/A") -> 0 | Q29: =IFERROR(INDEX(Pruebas_Auditoria!$L$144:$L$183,MATCH("POP-631309940",Pruebas_Auditoria!$A$144:$A$183,0)),"N/D") -> 287500000 | R29: =IF(ISNUMBER(Q29),N29-Q29,"N/D") -> 0 | S29: =I1637 -> 36715667 | T29: =IFERROR(INDEX(Intereses_x_Obligacion!$I:$I,MATCH("POP-631309940",Intereses_x_Obligacion!$A:$A,0)),"N/D") -> 34304862 | U29: =IF(ISNUMBER(T29),T29-S29,"N/D") -> -2410804.7 | V29: =MAX(I1638,0) -> 287500000 | W29: =IF(COUNTIF(Detalle_62!$C$14:$C$35,A29)>0,SUMIFS(Detalle_62!$M$14:$M$35,Detalle_62!$C$14:$C$35,A29),"No está") -> 575000000 | X29: =IF(ISNUMBER(W29),V29-W29,"N/A") -> -287500000 | Y29: =I1639 -> 0 | Z29: 2.8714872e+08 | AA29: =IF(ISNUMBER(Z29),Z29-N29,"N/A") -> -351282.59 | AB29: Capital trimestral $143,75 MM coincide con lo pagado; vence 17-dic-26 (todo corriente).
A30: BBVA-9600277262 | B30: V-7262 | C30: A19-V-7262 | D30: BBVA | E30: 9600277262 | F30: Crédito | G30: =C1710 -> 4700000000 | H30: =C1711 -> 46002 | I30: =C1712 -> 6 meses – IBR 3 MESES + 0,95% | J30: =IF(ISNUMBER(C1713),C1713,"Por fila") -> Por fila | K30: =IFERROR(C1714,"N/A") -> 0.0099264868 | L30: =IF(AND(ISNUMBER(J30),ISNUMBER(K30)),(K30-J30)*10000,"N/A") -> N/A | M30: =I1710 -> 46184 | N30: =I1711 -> 0 | O30: =IF(COUNTIF(Detalle_62!$C$14:$C$35,A30)>0,SUMIFS(Detalle_62!$F$14:$F$35,Detalle_62!$C$14:$C$35,A30),"No está") -> No está | P30: =IF(ISNUMBER(O30),N30-O30,"N/A") -> N/A | Q30: =IFERROR(INDEX(Pruebas_Auditoria!$L$144:$L$183,MATCH("BBVA-9600277262",Pruebas_Auditoria!$A$144:$A$183,0)),"N/D") -> N/D | R30: =IF(ISNUMBER(Q30),N30-Q30,"N/D") -> N/D | S30: =I1713 -> 2.8017092e+08 | T30: =IFERROR(INDEX(Intereses_x_Obligacion!$I:$I,MATCH("BBVA-9600277262",Intereses_x_Obligacion!$A:$A,0)),"N/D") -> N/D | U30: =IF(ISNUMBER(T30),T30-S30,"N/D") -> N/D | V30: =MAX(I1714,0) -> 0 | W30: =IF(COUNTIF(Detalle_62!$C$14:$C$35,A30)>0,SUMIFS(Detalle_62!$M$14:$M$35,Detalle_62!$C$14:$C$35,A30),"No está") -> No está | X30: =IF(ISNUMBER(W30),V30-W30,"N/A") -> N/A | Y30: =I1715 -> 0 | Z30: 0 | AA30: =IF(ISNUMBER(Z30),Z30-N30,"N/A") -> 0 | AB30: Tabla del crédito anterior (11-dic-25 a 11-jun-26). No hay tabla del crédito renovado el 30-jun-26 (glosa 'crédito 0141').
A31: BCL-1260105867 | B31: BC-5867 | C31: A20-BC-5867 | D31: BANCOLOMBIA | E31: 1260105867 | F31: Crédito | G31: =C1732 -> 5000000000 | H31: =C1733 -> 45768 | I31: =C1734 -> 36 meses – IBR 3 MESES + 1,5% | J31: =IF(ISNUMBER(C1735),C1735,"Por fila") -> Por fila | K31: =IFERROR(C1736,"N/A") -> 0.0099893752 | L31: =IF(AND(ISNUMBER(J31),ISNUMBER(K31)),(K31-J31)*10000,"N/A") -> N/A | M31: =I1732 -> 46224 | N31: =I1733 -> 3.3333333e+09 | O31: =IF(COUNTIF(Detalle_62!$C$14:$C$35,A31)>0,SUMIFS(Detalle_62!$F$14:$F$35,Detalle_62!$C$14:$C$35,A31),"No está") -> 3.3333333e+09 | P31: =IF(ISNUMBER(O31),N31-O31,"N/A") -> 0 | Q31: =IFERROR(INDEX(Pruebas_Auditoria!$L$144:$L$183,MATCH("BCL-1260105867",Pruebas_Auditoria!$A$144:$A$183,0)),"N/D") -> 3333333334 | R31: =IF(ISNUMBER(Q31),N31-Q31,"N/D") -> -0.66666698 | S31: =I1735 -> 3.1140278e+08 | T31: =IFERROR(INDEX(Intereses_x_Obligacion!$I:$I,MATCH("BCL-1260105867",Intereses_x_Obligacion!$A:$A,0)),"N/D") -> 287833704 | U31: =IF(ISNUMBER(T31),T31-S31,"N/D") -> -23569074 | V31: =MAX(I1736,0) -> 1.6666667e+09 | W31: =IF(COUNTIF(Detalle_62!$C$14:$C$35,A31)>0,SUMIFS(Detalle_62!$M$14:$M$35,Detalle_62!$C$14:$C$35,A31),"No está") -> 1.6666667e+09 | X31: =IF(ISNUMBER(W31),V31-W31,"N/A") -> -0.0033330917 | Y31: =I1737 -> 0 | Z31: 3.3821184e+09 | AA31: =IF(ISNUMBER(Z31),Z31-N31,"N/A") -> 48785100 | AB31: Capital anual $1.666,7 MM; coincide con el certificado (capital vigente $3.333.333.334).
A32: BCL-L362095 | B32: 362095 | C32: A21-362095 | D32: LEASING BANCOLOMBIA S.A. | E32: 362095 | F32: Leasing | G32: =C1784 -> 561680000 | H32: =C1785 -> 45730 | I32: =C1786 -> 60 MESES – IBR TV + 2,85% | J32: =IF(ISNUMBER(C1787),C1787,"Por fila") -> 0.02145014 | K32: =IFERROR(C1788,"N/A") -> 0.025689224 | L32: =IF(AND(ISNUMBER(J32),ISNUMBER(K32)),(K32-J32)*10000,"N/A") -> 42.390836 | M32: =I1784 -> 46187 | N32: =I1785 -> 5.2451929e+08 | O32: =IF(COUNTIF(Detalle_62!$C$14:$C$35,A32)>0,SUMIFS(Detalle_62!$F$14:$F$35,Detalle_62!$C$14:$C$35,A32),"No está") -> 497241599 | P32: =IF(ISNUMBER(O32),N32-O32,"N/A") -> 27277692 | Q32: =IFERROR(INDEX(Pruebas_Auditoria!$L$144:$L$183,MATCH("BCL-L362095",Pruebas_Auditoria!$A$144:$A$183,0)),"N/D") -> 448477372 | R32: =IF(ISNUMBER(Q32),N32-Q32,"N/D") -> 76041919 | S32: =I1787 -> 20871066 | T32: =IFERROR(INDEX(Intereses_x_Obligacion!$I:$I,MATCH("BCL-L362095",Intereses_x_Obligacion!$A:$A,0)),"N/D") -> 32199918 | U32: =IF(ISNUMBER(T32),T32-S32,"N/D") -> 11328852 | V32: =MAX(I1788,0) -> 1.4864284e+08 | W32: =IF(COUNTIF(Detalle_62!$C$14:$C$35,A32)>0,SUMIFS(Detalle_62!$M$14:$M$35,Detalle_62!$C$14:$C$35,A32),"No está") -> 154259653 | X32: =IF(ISNUMBER(W32),V32-W32,"N/A") -> -5616817.5 | Y32: =I1789 -> 5.2154064e-08 | Z32: N/A | AA32: N/A | AB32: ERROR: el periodo 5 (14-jun-26) aumenta el saldo en $48,8 MM (capital negativo) y la última cuota deja saldo negativo. El detalle 62 usa el saldo de dic-25 ($497,2 MM) sin actualizar.
A33: BCL-L336817 | B33: 336817 | C33: A22-336817 | D33: LEASING BANCOLOMBIA S.A. | E33: 336817 | F33: Leasing | G33: =C1820 -> 858438452 | H33: =C1821 -> 45804 | I33: =C1822 -> 72 MESES – IBR MV + 3,2% | J33: =IF(ISNUMBER(C1823),C1823,"Por fila") -> 0.0079203502 | K33: =IFERROR(C1824,"N/A") -> N/A | L33: =IF(AND(ISNUMBER(J33),ISNUMBER(K33)),(K33-J33)*10000,"N/A") -> N/A | M33: =I1820 -> 46230 | N33: =I1821 -> 7.7008543e+08 | O33: =IF(COUNTIF(Detalle_62!$C$14:$C$35,A33)>0,SUMIFS(Detalle_62!$F$14:$F$35,Detalle_62!$C$14:$C$35,A33),"No está") -> 7.7008543e+08 | P33: =IF(ISNUMBER(O33),N33-O33,"N/A") -> 0 | Q33: =IFERROR(INDEX(Pruebas_Auditoria!$L$144:$L$183,MATCH("BCL-L336817",Pruebas_Auditoria!$A$144:$A$183,0)),"N/D") -> 787729700 | R33: =IF(ISNUMBER(Q33),N33-Q33,"N/D") -> -17644275 | S33: =I1823 -> 44946958 | T33: =IFERROR(INDEX(Intereses_x_Obligacion!$I:$I,MATCH("BCL-L336817",Intereses_x_Obligacion!$A:$A,0)),"N/D") -> 28583500 | U33: =IF(ISNUMBER(T33),T33-S33,"N/D") -> -16363458 | V33: =MAX(I1824,0) -> 1.3031695e+08 | W33: =IF(COUNTIF(Detalle_62!$C$14:$C$35,A33)>0,SUMIFS(Detalle_62!$M$14:$M$35,Detalle_62!$C$14:$C$35,A33),"No está") -> 206513651 | X33: =IF(ISNUMBER(W33),V33-W33,"N/A") -> -76196703 | Y33: =I1825 -> 6.7055225e-08 | Z33: N/A | AA33: N/A | AB33: Tabla a tasa fija; detalle 62 = saldo de la tabla. Sin extracto 2026.
A34: BCL-L331330 | B34: 331330 | C34: A23-331330 | D34: LEASING BANCOLOMBIA S.A. | E34: 331330 | F34: Leasing | G34: =C1908 -> 915429932 | H34: =C1909 -> 45133 | I34: =C1910 -> 60 Meses – IBR+3,75% | J34: =IF(ISNUMBER(C1911),C1911,"Por fila") -> 0.02539371 | K34: =IFERROR(C1912,"N/A") -> 0.022892936 | L34: =IF(AND(ISNUMBER(J34),ISNUMBER(K34)),(K34-J34)*10000,"N/A") -> -25.00774 | M34: =I1908 -> 46229 | N34: =I1909 -> 503693510 | O34: =IF(COUNTIF(Detalle_62!$C$14:$C$35,A34)>0,SUMIFS(Detalle_62!$F$14:$F$35,Detalle_62!$C$14:$C$35,A34),"No está") -> 503693510 | P34: =IF(ISNUMBER(O34),N34-O34,"N/A") -> 0 | Q34: =IFERROR(INDEX(Pruebas_Auditoria!$L$144:$L$183,MATCH("BCL-L331330",Pruebas_Auditoria!$A$144:$A$183,0)),"N/D") -> 488525504 | R34: =IF(ISNUMBER(Q34),N34-Q34,"N/D") -> 15168006 | S34: =I1911 -> 99905793 | T34: =IFERROR(INDEX(Intereses_x_Obligacion!$I:$I,MATCH("BCL-L331330",Intereses_x_Obligacion!$A:$A,0)),"N/D") -> 26060708 | U34: =IF(ISNUMBER(T34),T34-S34,"N/D") -> -73845085 | V34: =MAX(I1912,0) -> 175036572 | W34: =IF(COUNTIF(Detalle_62!$C$14:$C$35,A34)>0,SUMIFS(Detalle_62!$M$14:$M$35,Detalle_62!$C$14:$C$35,A34),"No está") -> 388559429 | X34: =IF(ISNUMBER(W34),V34-W34,"N/A") -> -213522857 | Y34: =I1913 -> 0 | Z34: N/A | AA34: N/A | AB34: Tabla con amortización de capital constante $14.586.381, pero desde feb-26 se paga $17.114.382 (mayor): la tabla no refleja los pagos reales.
A35: DYP-482800190700 | B35: DD-0709 | C35: A24-DD-0709 | D35: DAVIVIENDA DYPSIS | E35: 7000482800190700 | F35: Crédito | G35: =C1984 -> 72300000000 | H35: =C1985 -> 45807 | I35: =C1986 -> 24 meses – IBR 3 MESES + 2,2% | J35: =IF(ISNUMBER(C1987),C1987,"Por fila") -> Por fila | K35: =IFERROR(C1988,"N/A") -> 0.010688955 | L35: =IF(AND(ISNUMBER(J35),ISNUMBER(K35)),(K35-J35)*10000,"N/A") -> N/A | M35: =I1984 -> 46233 | N35: =I1985 -> 72300000000 | O35: =IF(COUNTIF(Detalle_62!$C$14:$C$35,A35)>0,SUMIFS(Detalle_62!$F$14:$F$35,Detalle_62!$C$14:$C$35,A35),"No está") -> No está | P35: =IF(ISNUMBER(O35),N35-O35,"N/A") -> N/A | Q35: =IFERROR(INDEX(Pruebas_Auditoria!$L$144:$L$183,MATCH("DYP-482800190700",Pruebas_Auditoria!$A$144:$A$183,0)),"N/D") -> N/D | R35: =IF(ISNUMBER(Q35),N35-Q35,"N/D") -> N/D | S35: =I1987 -> 5585235250 | T35: =IFERROR(INDEX(Intereses_x_Obligacion!$I:$I,MATCH("DYP-482800190700",Intereses_x_Obligacion!$A:$A,0)),"N/D") -> N/D | U35: =IF(ISNUMBER(T35),T35-S35,"N/D") -> N/D | V35: =MAX(I1988,0) -> 72300000000 | W35: =IF(COUNTIF(Detalle_62!$C$14:$C$35,A35)>0,SUMIFS(Detalle_62!$M$14:$M$35,Detalle_62!$C$14:$C$35,A35),"No está") -> No está | X35: =IF(ISNUMBER(W35),V35-W35,"N/A") -> N/A | Y35: =I1989 -> 0 | Z35: 7.2948852e+10 | AA35: =IF(ISNUMBER(Z35),Z35-N35,"N/A") -> 6.4885162e+08 | AB35: Crédito Davivienda DYPSIS $72.300 MM (30-may-25 a 28-may-27) incluido en el archivo de tablas pero NO registrado en el mayor de Guaicaramo. Confirmar titular, vinculación y garantías otorgadas.
A36: DAV-L1013934 | B36: 3934 | C36: A25-3934 | D36: BANCO DAVIVIENDA INPARME | E36: 30001013934-6 | F36: Leasing | G36: =C2024 -> 142000000 | H36: =C2025 -> 44281 | I36: =C2026 -> 60 MESES – DTF MV + 6 | J36: =IF(ISNUMBER(C2027),C2027,"Por fila") -> -0.045876459 | K36: =IFERROR(C2028,"N/A") -> N/A | L36: =IF(AND(ISNUMBER(J36),ISNUMBER(K36)),(K36-J36)*10000,"N/A") -> N/A | M36: =I2024 -> 45133 | N36: =I2025 -> 6.0535967e-08 | O36: =IF(COUNTIF(Detalle_62!$C$14:$C$35,A36)>0,SUMIFS(Detalle_62!$F$14:$F$35,Detalle_62!$C$14:$C$35,A36),"No está") -> No está | P36: =IF(ISNUMBER(O36),N36-O36,"N/A") -> N/A | Q36: =IFERROR(INDEX(Pruebas_Auditoria!$L$144:$L$183,MATCH("DAV-L1013934",Pruebas_Auditoria!$A$144:$A$183,0)),"N/D") -> N/D | R36: =IF(ISNUMBER(Q36),N36-Q36,"N/D") -> N/D | S36: =I2027 -> 0 | T36: =IFERROR(INDEX(Intereses_x_Obligacion!$I:$I,MATCH("DAV-L1013934",Intereses_x_Obligacion!$A:$A,0)),"N/D") -> N/D | U36: =IF(ISNUMBER(T36),T36-S36,"N/D") -> N/D | V36: =MAX(I2028,0) -> 0 | W36: =IF(COUNTIF(Detalle_62!$C$14:$C$35,A36)>0,SUMIFS(Detalle_62!$M$14:$M$35,Detalle_62!$C$14:$C$35,A36),"No está") -> No está | X36: =IF(ISNUMBER(W36),V36-W36,"N/A") -> N/A | Y36: =I2029 -> 3.7252903e-09 | Z36: N/A | AA36: N/A | AB36: Contrato INPARME terminado; sin saldo en el mayor 2026.
A37: TOTAL (obligaciones en el mayor) | N37: =SUMIFS(N12:N36,$A$12:$A$36,"<>DYP*",$A$12:$A$36,"<>DAV-L1013934",$A$12:$A$36,"<>BOG-1155297469",$A$12:$A$36,"<>BBVA-9600277262") -> 4.051319e+10 | O37: =SUMIFS(O12:O36,$A$12:$A$36,"<>DYP*",$A$12:$A$36,"<>DAV-L1013934",$A$12:$A$36,"<>BOG-1155297469",$A$12:$A$36,"<>BBVA-9600277262") -> 4.0485912e+10 | Q37: =SUMIFS(Q12:Q36,$A$12:$A$36,"<>DYP*",$A$12:$A$36,"<>DAV-L1013934",$A$12:$A$36,"<>BOG-1155297469",$A$12:$A$36,"<>BBVA-9600277262") -> 4.061447e+10 | S37: =SUMIFS(S12:S36,$A$12:$A$36,"<>DYP*",$A$12:$A$36,"<>DAV-L1013934",$A$12:$A$36,"<>BOG-1155297469",$A$12:$A$36,"<>BBVA-9600277262") -> 3.379247e+09 | T37: =SUMIFS(T12:T36,$A$12:$A$36,"<>DYP*",$A$12:$A$36,"<>DAV-L1013934",$A$12:$A$36,"<>BOG-1155297469",$A$12:$A$36,"<>BBVA-9600277262") -> 3.002309e+09 | V37: =SUMIFS(V12:V36,$A$12:$A$36,"<>DYP*",$A$12:$A$36,"<>DAV-L1013934",$A$12:$A$36,"<>BOG-1155297469",$A$12:$A$36,"<>BBVA-9600277262") -> 5.4008492e+09 | W37: =SUMIFS(W12:W36,$A$12:$A$36,"<>DYP*",$A$12:$A$36,"<>DAV-L1013934",$A$12:$A$36,"<>BOG-1155297469",$A$12:$A$36,"<>BBVA-9600277262") -> 1.6928999e+10
A39: Conclusiones de la revisión de tablas
A40: 1. Los saldos del detalle 62 se toman de estas tablas teóricas (tasa fija / IBR-DTF proyectado), no de los extractos: en leasings la diferencia con el banco proviene de la tasa variable efectivamente cobrada.
A41: 2. El recálculo aritmético (columna Y) valida la consistencia interna de cada tabla (saldo inicial + interés − pago = saldo final). Las diferencias materiales indican fórmulas alteradas o filas pegadas como valor.
A42: 3. Las tablas de créditos Davivienda tienen la columna de costo amortizado mal formulada (resta intereses del saldo): no deben usarse para medir el pasivo bajo NIIF 9 (B5.4.1).
A43: 4. Faltan tablas para: leasing Bancolombia 386735, leasing GECOLSA (Davivienda), BBVA renovado (0141) y el crédito Bogotá 1159383796 ('Hoja2' es una copia del crédito anterior).
A44: 5. El archivo incluye el crédito Davivienda DYPSIS ($72.300 MM) que no está en el mayor de Guaicaramo: confirmar titular y garantías (NIC 24, NIIF 9 §2.1(e) garantías financieras, NIC 37).
A47: TABLA 01 – DAV-L1019441 – BANCO DAVIVIENDA _0001019441
A48: Observación: Tabla teórica a tasa fija (TIR mensual constante) y cuota fija $17.681.217; el banco liquida a tasa variable (canon 033: capital $12.327.298 / interés $5.062.372). El saldo del detalle 62 es el de esta tabla, no el del banco.
A49: Anexo A01-9441 – Tabla de amortización del cliente vs recálculo de auditoría – DAV-L1019441
A50: Fuente: 64._Tabla_amortización_obligaciones_financieras.xlsm, hoja '9441'. Columnas A–G: cliente [A]; H–P: recálculo auditoría [B].
A51: Banco / contrato | C51: BANCO DAVIVIENDA – _0001019441 | F51: Resultados al 31-jul-2026
A52: Valor inicial | C52: 726630000 | F52: Fecha última cuota ≤ corte | I52: =_xlfn.MAXIFS($B$60:$B$120,$B$60:$B$120,"<="&Resumen!$C$5) -> 46214
A53: Fecha inicio | C53: 45210 | F53: Saldo tabla cliente | I53: =SUMIFS($G$60:$G$120,$B$60:$B$120,I52) -> 3.9858217e+08
A54: Plazo / tasa pactada | C54: 60 MESES – IBR+4% | F54: Saldo recalculado | I54: =SUMIFS($J$60:$J$120,$B$60:$B$120,I52) -> 3.9858217e+08
A55: Tasa periódica tabla (TIR cliente) | C55: 0.013357044 | F55: Interés tabla ene–jul 26 | I55: =SUMIFS($D$60:$D$120,$O$60:$O$120,1) -> 41709582
A56: TIR recalculada (flujos col. M) | C56: =IFERROR(IRR($M$60:$M$120),"N/A") -> 0.013357044 | F56: Capital siguiente 12 meses (CP) | I56: =SUMIFS($E$60:$E$120,$P$60:$P$120,1) -> 1.5968177e+08
A57: Tasa EA equivalente | C57: =IF(ISNUMBER(C56),(1+C56)^12-1,"N/A") -> 0.1726 | F57: Máx. dif. saldo |cliente − recalc.| | I57: =SUMPRODUCT(MAX(ABS($L$60:$L$120))) -> 7.4505806e-09
A59: Per. | B59: Fecha | C59: Saldo inicial | D59: Interés | E59: Capital | F59: Pago / cuota | G59: Saldo final | H59: Saldo inicial recalc. | I59: Interés recalc. | J59: Saldo final recalc. | K59: Dif. interés | L59: Dif. saldo | M59: Flujo (TIR) | N59: Tasa periodo | O59: Ene–jul 26 | P59: CP 12m
A60: 0 | B60: 45210 | D60: 0 | E60: 0 | F60: 0 | G60: 726630000 | H60: =G60 -> 726630000 | I60: 0 | J60: =H60 -> 726630000 | K60: =D60-I60 -> 0 | L60: =G60-J60 -> 0 | M60: =-$C$52 -> -726630000 | N60: =$C$55 -> 0.013357044 | O60: =IF(AND(B60>=DATE(2026,1,1),B60<=Resumen!$C$5),1,0) -> 0 | P60: =IF(AND(B60>Resumen!$C$5,B60<=DATE(2027,7,31)),1,0) -> 0
A61: 1 | B61: 45241 | C61: 726630000 | D61: 9705629.1 | E61: 7975587.9 | F61: 17681217 | G61: 7.1865441e+08 | H61: =J60 -> 726630000 | I61: =H61*N61 -> 9705629.1 | J61: =H61+I61-F61 -> 7.1865441e+08 | K61: =D61-I61 -> 0 | L61: =G61-J61 -> 0 | M61: =F61 -> 17681217 | N61: =$C$55 -> 0.013357044 | O61: =IF(AND(B61>=DATE(2026,1,1),B61<=Resumen!$C$5),1,0) -> 0 | P61: =IF(AND(B61>Resumen!$C$5,B61<=DATE(2027,7,31)),1,0) -> 0
A62: 2 | B62: 45271 | C62: 7.1865441e+08 | D62: 9599098.8 | E62: 8082118.2 | F62: 17681217 | G62: 7.1057229e+08 | H62: =J61 -> 7.1865441e+08 | I62: =H62*N62 -> 9599098.8 | J62: =H62+I62-F62 -> 7.1057229e+08 | K62: =D62-I62 -> 0 | L62: =G62-J62 -> 0 | M62: =F62 -> 17681217 | N62: =$C$55 -> 0.013357044 | O62: =IF(AND(B62>=DATE(2026,1,1),B62<=Resumen!$C$5),1,0) -> 0 | P62: =IF(AND(B62>Resumen!$C$5,B62<=DATE(2027,7,31)),1,0) -> 0
A63: 3 | B63: 45302 | C63: 7.1057229e+08 | D63: 9491145.6 | E63: 8190071.4 | F63: 17681217 | G63: 7.0238222e+08 | H63: =J62 -> 7.1057229e+08 | I63: =H63*N63 -> 9491145.6 | J63: =H63+I63-F63 -> 7.0238222e+08 | K63: =D63-I63 -> 0 | L63: =G63-J63 -> 0 | M63: =F63 -> 17681217 | N63: =$C$55 -> 0.013357044 | O63: =IF(AND(B63>=DATE(2026,1,1),B63<=Resumen!$C$5),1,0) -> 0 | P63: =IF(AND(B63>Resumen!$C$5,B63<=DATE(2027,7,31)),1,0) -> 0
A64: 4 | B64: 45333 | C64: 7.0238222e+08 | D64: 9381750.5 | E64: 8299466.5 | F64: 17681217 | G64: 6.9408276e+08 | H64: =J63 -> 7.0238222e+08 | I64: =H64*N64 -> 9381750.5 | J64: =H64+I64-F64 -> 6.9408276e+08 | K64: =D64-I64 -> 0 | L64: =G64-J64 -> 0 | M64: =F64 -> 17681217 | N64: =$C$55 -> 0.013357044 | O64: =IF(AND(B64>=DATE(2026,1,1),B64<=Resumen!$C$5),1,0) -> 0 | P64: =IF(AND(B64>Resumen!$C$5,B64<=DATE(2027,7,31)),1,0) -> 0
A65: 5 | B65: 45362 | C65: 6.9408276e+08 | D65: 9270894.1 | E65: 8410322.9 | F65: 17681217 | G65: 6.8567243e+08 | H65: =J64 -> 6.9408276e+08 | I65: =H65*N65 -> 9270894.1 | J65: =H65+I65-F65 -> 6.8567243e+08 | K65: =D65-I65 -> 0 | L65: =G65-J65 -> 0 | M65: =F65 -> 17681217 | N65: =$C$55 -> 0.013357044 | O65: =IF(AND(B65>=DATE(2026,1,1),B65<=Resumen!$C$5),1,0) -> 0 | P65: =IF(AND(B65>Resumen!$C$5,B65<=DATE(2027,7,31)),1,0) -> 0
A66: 6 | B66: 45393 | C66: 6.8567243e+08 | D66: 9158557.1 | E66: 8522659.9 | F66: 17681217 | G66: 6.7714977e+08 | H66: =J65 -> 6.8567243e+08 | I66: =H66*N66 -> 9158557.1 | J66: =H66+I66-F66 -> 6.7714977e+08 | K66: =D66-I66 -> 0 | L66: =G66-J66 -> 0 | M66: =F66 -> 17681217 | N66: =$C$55 -> 0.013357044 | O66: =IF(AND(B66>=DATE(2026,1,1),B66<=Resumen!$C$5),1,0) -> 0 | P66: =IF(AND(B66>Resumen!$C$5,B66<=DATE(2027,7,31)),1,0) -> 0
A67: 7 | B67: 45423 | C67: 6.7714977e+08 | D67: 9044719.5 | E67: 8636497.5 | F67: 17681217 | G67: 6.6851328e+08 | H67: =J66 -> 6.7714977e+08 | I67: =H67*N67 -> 9044719.5 | J67: =H67+I67-F67 -> 6.6851328e+08 | K67: =D67-I67 -> 0 | L67: =G67-J67 -> 0 | M67: =F67 -> 17681217 | N67: =$C$55 -> 0.013357044 | O67: =IF(AND(B67>=DATE(2026,1,1),B67<=Resumen!$C$5),1,0) -> 0 | P67: =IF(AND(B67>Resumen!$C$5,B67<=DATE(2027,7,31)),1,0) -> 0
A68: 8 | B68: 45454 | C68: 6.6851328e+08 | D68: 8929361.4 | E68: 8751855.5 | F68: 17681217 | G68: 6.5976142e+08 | H68: =J67 -> 6.6851328e+08 | I68: =H68*N68 -> 8929361.4 | J68: =H68+I68-F68 -> 6.5976142e+08 | K68: =D68-I68 -> 0 | L68: =G68-J68 -> 0 | M68: =F68 -> 17681217 | N68: =$C$55 -> 0.013357044 | O68: =IF(AND(B68>=DATE(2026,1,1),B68<=Resumen!$C$5),1,0) -> 0 | P68: =IF(AND(B68>Resumen!$C$5,B68<=DATE(2027,7,31)),1,0) -> 0
A69: 9 | B69: 45484 | C69: 6.5976142e+08 | D69: 8812462.5 | E69: 8868754.5 | F69: 17681217 | G69: 6.5089267e+08 | H69: =J68 -> 6.5976142e+08 | I69: =H69*N69 -> 8812462.5 | J69: =H69+I69-F69 -> 6.5089267e+08 | K69: =D69-I69 -> 0 | L69: =G69-J69 -> 0 | M69: =F69 -> 17681217 | N69: =$C$55 -> 0.013357044 | O69: =IF(AND(B69>=DATE(2026,1,1),B69<=Resumen!$C$5),1,0) -> 0 | P69: =IF(AND(B69>Resumen!$C$5,B69<=DATE(2027,7,31)),1,0) -> 0
A70: 10 | B70: 45515 | C70: 6.5089267e+08 | D70: 8694002.2 | E70: 8987214.8 | F70: 17681217 | G70: 6.4190545e+08 | H70: =J69 -> 6.5089267e+08 | I70: =H70*N70 -> 8694002.2 | J70: =H70+I70-F70 -> 6.4190545e+08 | K70: =D70-I70 -> 0 | L70: =G70-J70 -> 0 | M70: =F70 -> 17681217 | N70: =$C$55 -> 0.013357044 | O70: =IF(AND(B70>=DATE(2026,1,1),B70<=Resumen!$C$5),1,0) -> 0 | P70: =IF(AND(B70>Resumen!$C$5,B70<=DATE(2027,7,31)),1,0) -> 0
A71: 11 | B71: 45546 | C71: 6.4190545e+08 | D71: 8573959.6 | E71: 9107257.4 | F71: 17681217 | G71: 6.3279819e+08 | H71: =J70 -> 6.4190545e+08 | I71: =H71*N71 -> 8573959.6 | J71: =H71+I71-F71 -> 6.3279819e+08 | K71: =D71-I71 -> 0 | L71: =G71-J71 -> 0 | M71: =F71 -> 17681217 | N71: =$C$55 -> 0.013357044 | O71: =IF(AND(B71>=DATE(2026,1,1),B71<=Resumen!$C$5),1,0) -> 0 | P71: =IF(AND(B71>Resumen!$C$5,B71<=DATE(2027,7,31)),1,0) -> 0
A72: 12 | B72: 45576 | C72: 6.3279819e+08 | D72: 8452313.5 | E72: 9228903.5 | F72: 17681217 | G72: 6.2356929e+08 | H72: =J71 -> 6.3279819e+08 | I72: =H72*N72 -> 8452313.5 | J72: =H72+I72-F72 -> 6.2356929e+08 | K72: =D72-I72 -> 0 | L72: =G72-J72 -> 0 | M72: =F72 -> 17681217 | N72: =$C$55 -> 0.013357044 | O72: =IF(AND(B72>=DATE(2026,1,1),B72<=Resumen!$C$5),1,0) -> 0 | P72: =IF(AND(B72>Resumen!$C$5,B72<=DATE(2027,7,31)),1,0) -> 0
... A120: 60 | B120: 47037 | C120: 17448161 | D120: 233055.86 | E120: 17448161 | F120: 17681217 | G120: 7.5437129e-06 | H120: =J119 -> 17448161 | I120: =H120*N120 -> 233055.86 | J120: =H120+I120-F120 -> 7.5511634e-06 | K120: =D120-I120 -> 0 | L120: =G120-J120 -> -7.4505806e-09 | M120: =F120 -> 17681217 | N120: =$C$55 -> 0.013357044 | O120: =IF(AND(B120>=DATE(2026,1,1),B120<=Resumen!$C$5),1,0) -> 0 | P120: =IF(AND(B120>Resumen!$C$5,B120<=DATE(2027,7,31)),1,0) -> 0
A123: TABLA 02 – DAV-L1019448 – BANCO DAVIVIENDA _0001019448-3
A124: Observación: Tabla teórica a tasa fija y cuota constante; el banco liquida a tasa variable (canon 031: capital $8.867.342 / interés $4.177.893). Detalle 62 = saldo de la tabla.
A125: Anexo A02-9448 – Tabla de amortización del cliente vs recálculo de auditoría – DAV-L1019448
A126: Fuente: 64._Tabla_amortización_obligaciones_financieras.xlsm, hoja '9448'. Columnas A–G: cliente [A]; H–P: recálculo auditoría [B].
A127: Banco / contrato | C127: BANCO DAVIVIENDA – _0001019448-3 | F127: Resultados al 31-jul-2026
A128: Valor inicial | C128: 560790000 | F128: Fecha última cuota ≤ corte | I128: =_xlfn.MAXIFS($B$136:$B$196,$B$136:$B$196,"<="&Resumen!$C$5) -> 46208
A129: Fecha inicio | C129: 45265 | F129: Saldo tabla cliente | I129: =SUMIFS($G$136:$G$196,$B$136:$B$196,I128) -> 3.2352969e+08
A130: Plazo / tasa pactada | C130: 60 MESES – IBR+4% | F130: Saldo recalculado | I130: =SUMIFS($J$136:$J$196,$B$136:$B$196,I128) -> 3.2352969e+08
A131: Tasa periódica tabla (TIR cliente) | C131: 0.012666707 | F131: Interés tabla ene–jul 26 | I131: =SUMIFS($D$136:$D$196,$O$136:$O$196,1) -> 31864026
A132: TIR recalculada (flujos col. M) | C132: =IFERROR(IRR($M$136:$M$196),"N/A") -> 0.012666707 | F132: Capital siguiente 12 meses (CP) | I132: =SUMIFS($E$136:$E$196,$P$136:$P$196,1) -> 1.1973915e+08
A133: Tasa EA equivalente | C133: =IF(ISNUMBER(C132),(1+C132)^12-1,"N/A") -> 0.16305 | F133: Máx. dif. saldo |cliente − recalc.| | I133: =SUMPRODUCT(MAX(ABS($L$136:$L$196))) -> 9.4994903e-08
A135: Per. | B135: Fecha | C135: Saldo inicial | D135: Interés | E135: Capital | F135: Pago / cuota | G135: Saldo final | H135: Saldo inicial recalc. | I135: Interés recalc. | J135: Saldo final recalc. | K135: Dif. interés | L135: Dif. saldo | M135: Flujo (TIR) | N135: Tasa periodo | O135: Ene–jul 26 | P135: CP 12m
A136: 0 | B136: 45265 | D136: 0 | E136: 0 | F136: 0 | G136: 560790000 | H136: =G136 -> 560790000 | I136: 0 | J136: =H136 -> 560790000 | K136: =D136-I136 -> 0 | L136: =G136-J136 -> 0 | M136: =-$C$128 -> -560790000 | N136: =$C$131 -> 0.012666707 | O136: =IF(AND(B136>=DATE(2026,1,1),B136<=Resumen!$C$5),1,0) -> 0 | P136: =IF(AND(B136>Resumen!$C$5,B136<=DATE(2027,7,31)),1,0) -> 0
A137: 1 | B137: 45296 | C137: 560790000 | D137: 7103362.7 | E137: 6296751.9 | F137: 13400115 | G137: 5.5449325e+08 | H137: =J136 -> 560790000 | I137: =H137*N137 -> 7103362.7 | J137: =H137+I137-F137 -> 5.5449325e+08 | K137: =D137-I137 -> 0 | L137: =G137-J137 -> 0 | M137: =F137 -> 13400115 | N137: =$C$131 -> 0.012666707 | O137: =IF(AND(B137>=DATE(2026,1,1),B137<=Resumen!$C$5),1,0) -> 0 | P137: =IF(AND(B137>Resumen!$C$5,B137<=DATE(2027,7,31)),1,0) -> 0
A138: 2 | B138: 45327 | C138: 5.5449325e+08 | D138: 7023603.5 | E138: 6376511 | F138: 13400115 | G138: 5.4811674e+08 | H138: =J137 -> 5.5449325e+08 | I138: =H138*N138 -> 7023603.5 | J138: =H138+I138-F138 -> 5.4811674e+08 | K138: =D138-I138 -> 0 | L138: =G138-J138 -> 0 | M138: =F138 -> 13400115 | N138: =$C$131 -> 0.012666707 | O138: =IF(AND(B138>=DATE(2026,1,1),B138<=Resumen!$C$5),1,0) -> 0 | P138: =IF(AND(B138>Resumen!$C$5,B138<=DATE(2027,7,31)),1,0) -> 0
A139: 3 | B139: 45356 | C139: 5.4811674e+08 | D139: 6942834.1 | E139: 6457280.4 | F139: 13400115 | G139: 5.4165946e+08 | H139: =J138 -> 5.4811674e+08 | I139: =H139*N139 -> 6942834.1 | J139: =H139+I139-F139 -> 5.4165946e+08 | K139: =D139-I139 -> 0 | L139: =G139-J139 -> 0 | M139: =F139 -> 13400115 | N139: =$C$131 -> 0.012666707 | O139: =IF(AND(B139>=DATE(2026,1,1),B139<=Resumen!$C$5),1,0) -> 0 | P139: =IF(AND(B139>Resumen!$C$5,B139<=DATE(2027,7,31)),1,0) -> 0
A140: 4 | B140: 45387 | C140: 5.4165946e+08 | D140: 6861041.7 | E140: 6539072.9 | F140: 13400115 | G140: 5.3512038e+08 | H140: =J139 -> 5.4165946e+08 | I140: =H140*N140 -> 6861041.7 | J140: =H140+I140-F140 -> 5.3512038e+08 | K140: =D140-I140 -> 0 | L140: =G140-J140 -> 0 | M140: =F140 -> 13400115 | N140: =$C$131 -> 0.012666707 | O140: =IF(AND(B140>=DATE(2026,1,1),B140<=Resumen!$C$5),1,0) -> 0 | P140: =IF(AND(B140>Resumen!$C$5,B140<=DATE(2027,7,31)),1,0) -> 0
A141: 5 | B141: 45417 | C141: 5.3512038e+08 | D141: 6778213.1 | E141: 6621901.4 | F141: 13400115 | G141: 5.2849848e+08 | H141: =J140 -> 5.3512038e+08 | I141: =H141*N141 -> 6778213.1 | J141: =H141+I141-F141 -> 5.2849848e+08 | K141: =D141-I141 -> 0 | L141: =G141-J141 -> 0 | M141: =F141 -> 13400115 | N141: =$C$131 -> 0.012666707 | O141: =IF(AND(B141>=DATE(2026,1,1),B141<=Resumen!$C$5),1,0) -> 0 | P141: =IF(AND(B141>Resumen!$C$5,B141<=DATE(2027,7,31)),1,0) -> 0
A142: 6 | B142: 45448 | C142: 5.2849848e+08 | D142: 6694335.5 | E142: 6705779.1 | F142: 13400115 | G142: 5.217927e+08 | H142: =J141 -> 5.2849848e+08 | I142: =H142*N142 -> 6694335.5 | J142: =H142+I142-F142 -> 5.217927e+08 | K142: =D142-I142 -> 0 | L142: =G142-J142 -> 0 | M142: =F142 -> 13400115 | N142: =$C$131 -> 0.012666707 | O142: =IF(AND(B142>=DATE(2026,1,1),B142<=Resumen!$C$5),1,0) -> 0 | P142: =IF(AND(B142>Resumen!$C$5,B142<=DATE(2027,7,31)),1,0) -> 0
A143: 7 | B143: 45478 | C143: 5.217927e+08 | D143: 6609395.3 | E143: 6790719.3 | F143: 13400115 | G143: 5.1500198e+08 | H143: =J142 -> 5.217927e+08 | I143: =H143*N143 -> 6609395.3 | J143: =H143+I143-F143 -> 5.1500198e+08 | K143: =D143-I143 -> 0 | L143: =G143-J143 -> 0 | M143: =F143 -> 13400115 | N143: =$C$131 -> 0.012666707 | O143: =IF(AND(B143>=DATE(2026,1,1),B143<=Resumen!$C$5),1,0) -> 0 | P143: =IF(AND(B143>Resumen!$C$5,B143<=DATE(2027,7,31)),1,0) -> 0
A144: 8 | B144: 45509 | C144: 5.1500198e+08 | D144: 6523379.3 | E144: 6876735.3 | F144: 13400115 | G144: 5.0812525e+08 | H144: =J143 -> 5.1500198e+08 | I144: =H144*N144 -> 6523379.3 | J144: =H144+I144-F144 -> 5.0812525e+08 | K144: =D144-I144 -> 0 | L144: =G144-J144 -> 0 | M144: =F144 -> 13400115 | N144: =$C$131 -> 0.012666707 | O144: =IF(AND(B144>=DATE(2026,1,1),B144<=Resumen!$C$5),1,0) -> 0 | P144: =IF(AND(B144>Resumen!$C$5,B144<=DATE(2027,7,31)),1,0) -> 0
A145: 9 | B145: 45540 | C145: 5.0812525e+08 | D145: 6436273.7 | E145: 6963840.9 | F145: 13400115 | G145: 5.0116141e+08 | H145: =J144 -> 5.0812525e+08 | I145: =H145*N145 -> 6436273.7 | J145: =H145+I145-F145 -> 5.0116141e+08 | K145: =D145-I145 -> 0 | L145: =G145-J145 -> 0 | M145: =F145 -> 13400115 | N145: =$C$131 -> 0.012666707 | O145: =IF(AND(B145>=DATE(2026,1,1),B145<=Resumen!$C$5),1,0) -> 0 | P145: =IF(AND(B145>Resumen!$C$5,B145<=DATE(2027,7,31)),1,0) -> 0
A146: 10 | B146: 45570 | C146: 5.0116141e+08 | D146: 6348064.7 | E146: 7052049.8 | F146: 13400115 | G146: 4.9410936e+08 | H146: =J145 -> 5.0116141e+08 | I146: =H146*N146 -> 6348064.7 | J146: =H146+I146-F146 -> 4.9410936e+08 | K146: =D146-I146 -> 0 | L146: =G146-J146 -> 0 | M146: =F146 -> 13400115 | N146: =$C$131 -> 0.012666707 | O146: =IF(AND(B146>=DATE(2026,1,1),B146<=Resumen!$C$5),1,0) -> 0 | P146: =IF(AND(B146>Resumen!$C$5,B146<=DATE(2027,7,31)),1,0) -> 0
A147: 11 | B147: 45601 | C147: 4.9410936e+08 | D147: 6258738.5 | E147: 7141376.1 | F147: 13400115 | G147: 4.8696798e+08 | H147: =J146 -> 4.9410936e+08 | I147: =H147*N147 -> 6258738.5 | J147: =H147+I147-F147 -> 4.8696798e+08 | K147: =D147-I147 -> 0 | L147: =G147-J147 -> 0 | M147: =F147 -> 13400115 | N147: =$C$131 -> 0.012666707 | O147: =IF(AND(B147>=DATE(2026,1,1),B147<=Resumen!$C$5),1,0) -> 0 | P147: =IF(AND(B147>Resumen!$C$5,B147<=DATE(2027,7,31)),1,0) -> 0
A148: 12 | B148: 45631 | C148: 4.8696798e+08 | D148: 6168280.8 | E148: 7231833.8 | F148: 13400115 | G148: 4.7973615e+08 | H148: =J147 -> 4.8696798e+08 | I148: =H148*N148 -> 6168280.8 | J148: =H148+I148-F148 -> 4.7973615e+08 | K148: =D148-I148 -> 0 | L148: =G148-J148 -> 0 | M148: =F148 -> 13400115 | N148: =$C$131 -> 0.012666707 | O148: =IF(AND(B148>=DATE(2026,1,1),B148<=Resumen!$C$5),1,0) -> 0 | P148: =IF(AND(B148>Resumen!$C$5,B148<=DATE(2027,7,31)),1,0) -> 0
... A196: 60 | B196: 47092 | C196: 13232502 | D196: 167612.23 | E196: 13232502 | F196: 13400115 | G196: -7.0780516e-06 | H196: =J195 -> 13232502 | I196: =H196*N196 -> 167612.23 | J196: =H196+I196-F196 -> -7.1730465e-06 | K196: =D196-I196 -> 1.1059456e-09 | L196: =G196-J196 -> 9.4994903e-08 | M196: =F196 -> 13400115 | N196: =$C$131 -> 0.012666707 | O196: =IF(AND(B196>=DATE(2026,1,1),B196<=Resumen!$C$5),1,0) -> 0 | P196: =IF(AND(B196>Resumen!$C$5,B196<=DATE(2027,7,31)),1,0) -> 0
A199: TABLA 03 – DAV-L1021275 – BANCO DAVIVIENDA 30001021275-3
A200: Observación: La TIR de la tabla supera el canon de sólo intereses de los primeros 12 trimestres: la tabla capitaliza intereses y el saldo crece ($1.876,7 MM → $1.883,7 MM). El banco mantiene el capital en $1.876.684.264 y cobra 14,41% EA ($64,0 MM en jul-26 vs $51,5 MM en la tabla).
A201: Anexo A03-2753 – Tabla de amortización del cliente vs recálculo de auditoría – DAV-L1021275
A202: Fuente: 64._Tabla_amortización_obligaciones_financieras.xlsm, hoja '2753'. Columnas A–G: cliente [A]; H–P: recálculo auditoría [B].
A203: Banco / contrato | C203: BANCO DAVIVIENDA – 30001021275-3 | F203: Resultados al 31-jul-2026
A204: Valor inicial | C204: 1876684264 | F204: Fecha última cuota ≤ corte | I204: =_xlfn.MAXIFS($B$212:$B$240,$B$212:$B$240,"<="&Resumen!$C$5) -> 46225
A205: Fecha inicio | C205: 45679 | F205: Saldo tabla cliente | I205: =SUMIFS($G$212:$G$240,$B$212:$B$240,I204) -> 1.8837122e+09
...

Sheet Hallazgos
A1: Hallazgos, referencias NIIF y ajustes propuestos
A2: Montos vinculados a las hojas de trabajo. Ajustes sujetos a la materialidad del encargo (no informada).
A4: # | B4: Afirmación | C4: Hallazgo | D4: Monto (COP) | E4: Referencia normativa | F4: Recomendación / acción | G4: Estado
A5: 1 | B5: Integridad | C5: El leasing Bancolombia 386735 (camión VW Constellation, IBR TV + 1,35) se registró en el mayor el 28-jul-26 (NB-00001014) pero NO está en el detalle 62 del cliente. | D5: =Cruce_Detalle_Mayor!F14 -> 675837500 | E5: NIIF 16 p.26; NIC 1 p.15 | F5: Incluir el contrato en el detalle 62 con su tabla de amortización; solicitar contrato y certificado. | G5: Concluido
A6: 2 | B6: Exactitud / Integridad | C6: Diferencia de capital de leasing entre el mayor (2120) y el detalle 62, explicada obligación por obligación (Pruebas_Auditoria (bloque 3)): 386735 y GECOLSA omitidos; Bogotá, Davivienda y Bancolombia con saldos de tablas teóricas en el detalle. | D6: =Cruce_Detalle_Mayor!F7 -> 1.0182662e+09 | E6: NIIF 16 p.36; NIC 1 p.15 | F6: Actualizar el detalle 62 con los saldos del banco y conciliar mensualmente por contrato. | G6: Pendiente de soporte (PEND-1, PEND-2, PEND-12)
A7: 3 | B7: Exactitud | C7: Leasings Bancolombia: el detalle 62 difiere del saldo estimado del banco (362095 conserva el saldo de dic-25; la tabla 331330 no refleja la cuota real pagada). | D7: =SUMIFS(Pruebas_Auditoria!$P$148:$P$174,Pruebas_Auditoria!$A$148:$A$174,"BCL-L3*") -> 46287958 | E7: NIIF 16 p.36 | F7: Obtener certificados Bancolombia al 31-jul-26 y actualizar tablas. | G7: Pendiente de soporte (PEND-2)
A8: 4 | B8: Exactitud | C8: Leasings Banco de Bogotá (pozos 1–5 y planta Jenbacher): el detalle 62 está por debajo del saldo certificado tras el canon de julio (p.ej. pozos 3 y 4 −$57 MM c/u). | D8: =-Pruebas_Auditoria!$L$75 -> 1.7160825e+08 | E8: NIIF 16 p.36 | F8: Actualizar el detalle 62 con los saldos certificados. | G8: Concluido
A9: 5 | B9: Corte / Valuación | C9: Intereses causados al 31-jul-26 no registrados: el cliente causa cifras fijas hasta ~el día 24 y no causa en obligaciones de pago mensual (453436746, BBVA, leasings mensuales) ni en el periodo posterior al último pago. | D9: =Pruebas_Auditoria!K236 -> 1.8770539e+08 | E9: NIC 1 p.27-28 (base de acumulación); NIIF 9 p.5.4.1 y B5.4 (método del interés efectivo) | F9: Registrar AJE-1; implementar causación diaria con tabla de amortización por obligación. | G9: Pendiente de soporte (PEND-3, PEND-5, PEND-10)
A10: 6 | B10: Exactitud | C10: Davivienda 607691 y 569032: la tasa 'cobrada' informada (12,58% EA) no reconcilia con los intereses facturados (tasa implícita ~14,4% EA). El detalle 62 usa 16,02% EA. | D10: =Pruebas_Auditoria!K196+Pruebas_Auditoria!K197 -> -51336720 | E10: NIIF 9 p.B5.4.5 (tasas variables); NIIF 7 p.39 | F10: Solicitar a Davivienda la liquidación detallada (IBR aplicado y spread). | G10: Pendiente de soporte (PEND-6)
A11: 7 | B11: Exactitud (detalle) | C11: Tasas EA del detalle 62 calculadas con periodicidad distinta a la declarada (BBVA, Bancolombia 1260105867 y 362095) y tasas del detalle distintas a las certificadas (p.ej. 453436746: 17,52% vs 16,96%; 856670629: 15,83% vs 14,94%). | D11: Cualitativo | E11: NIIF 7 p.33-40 (riesgo de tasa) | F11: Usar la tasa certificada por el banco y la periodicidad contractual. | G11: Concluido
A12: 8 | B12: Presentación | C12: Clasificación CP/LP: el detalle 62 tiene errores (Banco Popular CP $575 MM > saldo $287,5 MM y LP negativo; Pozo #2 CP + LP ≠ saldo) y las cuentas CP/LP del mayor no reflejan vencimientos a 12 meses. | D12: =Clasif_CP_LP!B11+Clasif_CP_LP!B12 -> 1.5766357e+09 | E12: NIC 1 p.69-76 | F12: Reclasificar la porción corriente (AJE-2) calculada con tablas y vencimientos; corregir el detalle 62. | G12: Pendiente de soporte (PEND-8)
A13: 9 | B13: Presentación | C13: Las tarjetas de crédito por pagar (21050301) están agrupadas dentro de 'Obligaciones financieras a largo plazo' (210502). | D13: =Clasif_CP_LP!B13 -> 31135732 | E13: NIC 1 p.69 | F13: Presentar como pasivo corriente. | G13: Concluido
A14: 10 | B14: Exactitud | C14: Abonos a capital aplicados por Davivienda por excedentes de pago (127,57 + 269,47 + 627,79 + 617,95 + 786,80) no registrados: el cliente lleva todo el pago a intereses. | D14: =127.57+269.47+627.79+617.95+786.8 -> 2429.58 | E14: NIIF 9 p.3.3.1 | F14: Inmaterial; registrar en el siguiente pago. | G14: Concluido
A15: 11 | B15: Ocurrencia / Exactitud | C15: Leasing Davivienda 1019441: el banco reporta el canon 032 (11-jun) pagado por $1.029.562, sólo intereses; la contabilidad registró capital $11.973.677 (CL-416). | D15: 11973677 | E15: NIIF 16 p.36 | F15: Obtener el estado de cuenta del contrato y verificar la aplicación del pago. | G15: Pendiente de soporte (PEND-7)
A16: 12 | B16: Control interno | C16: Partidas ajenas registradas en cuentas de obligaciones financieras: comisiones Valley Trading en 21202040 y cruce de anticipo de calderas (NI-4731) en 21202140 (netas cero). | D16: =4068134+31360500+8261283 -> 43689917 | E16: NIC 1 p.32 (no compensar) | F16: Restringir el uso de las cuentas 2120 a contratos de leasing con tercero y número de contrato. | G16: Concluido
A17: 13 | B17: Integridad / Confirmación | C17: Obligaciones sin certificado ni extracto en el PDF: BBVA ($4.700 MM), Banco Popular, Bogotá 1159383796 (nuevo crédito) y leasings Bancolombia. | D17: =Pruebas_Auditoria!K86 -> 6.7585205e+09 | E17: NIA 505 | F17: Enviar confirmaciones bancarias. | G17: Pendiente de soporte (PEND-1 a PEND-5)
A18: 14 | B18: Exactitud (detalle) | C18: Vencimientos del detalle 62 distintos a los certificados: pozos 3 y 4 (abr-2028 vs 27-jul-2028), pozos 1 y 2 (20-ene vs 23-ene-2030), Bancolombia 1260105867 (21 vs 22-abr-2028). | D18: Cualitativo | E18: NIIF 7 p.39 (análisis de vencimientos) | F18: Corregir; afecta la clasificación CP/LP y la revelación de liquidez. | G18: Concluido
A19: 15 | B19: Valuación / Revelación | C19: Renovaciones y refinanciaciones (BBVA 30-jun; Bogotá 1155297469 → 1159383796 el 29-jul; Davivienda 8906 pagado con el crédito Bogotá 1155297469): se registraron a la par sin costos de transacción. | D19: Cualitativo | E19: NIIF 9 p.3.3.2 y B3.3.6 (prueba del 10%) | F19: Documentar la prueba del 10% (modificación sustancial) y los costos de transacción, si los hubo. | G19: Pendiente de soporte (PEND-11)
A20: 16 | B20: Control interno | C20: Causación no sistemática de intereses de leasing (p.ej. pozos 3 y 4: feb–mar $480.943 vs abr $8,6 MM) y glosas con valores errados (CL-393, NI-4397) o números de crédito errados (BBVA 252059 vs 0141; '12660105867'). | D20: Cualitativo | E20: NIC 8 p.41; NIC 1 p.27 | F20: Usar tablas de amortización por obligación; revisar las glosas. | G20: Concluido
A21: 17 | B21: Integridad | C21: Mayor vs balance: los débitos, créditos y saldos de las cuentas 21 del movimiento cuadran con los dos balances de prueba (24-ago y 29-sep), que son idénticos. | D21: =Pruebas_Auditoria!H21 -> -2.6077032e-08 | E21: — | F21: Sin excepción. | G21: Concluido
A22: 18 | B22: Integridad | C22: Leasing Davivienda GECOLSA (2 motogeneradores, registrado jul-25 en 21202140) incluido en el mayor pero omitido en el detalle 62 y en la validación del PT 2025; sin tabla ni extracto. | D22: =SUMIFS(Pruebas_Auditoria!$H$148:$H$174,Pruebas_Auditoria!$A$148:$A$174,"DAV-LGECOLSA") -> 213861900 | E22: NIIF 16 p.26 y 47; NIA 505 | F22: Obtener contrato, tabla y certificado; incluirlo en el detalle 62. | G22: Pendiente de soporte (PEND-12)
A23: 19 | B23: Valuación | C23: Las tablas de leasing del cliente son teóricas (tasa fija / índice proyectado) y no se remiden cuando cambian IBR/DTF: el saldo de la tabla difiere del saldo bancario. | D23: =SUMIFS(Tablas_Amortizacion!R12:R36,Tablas_Amortizacion!F12:F36,"Leasing") -> -1.0128908e+08 | E23: NIIF 16 p.36, 42(b) y 43 (nueva medición por cambio en índice o tasa) | F23: Remedir el pasivo con la tasa vigente o usar el saldo bancario; actualizar tablas cada periodo. | G23: Concluido
A24: 20 | B24: Exactitud (tabla) | C24: Tabla Bancolombia 362095 con error: el periodo 5 (14-jun-26) aumenta el saldo (capital negativo) y la última cuota deja saldo negativo. | D24: =ABS(Tablas_Amortizacion!E1797) -> 48757159 | E24: NIIF 16 p.36 | F24: Corregir la tabla con el plan de pagos del banco. | G24: Pendiente de soporte (PEND-14)
A25: 21 | B25: Exactitud (tabla) | C25: La tabla 'Hoja2' del crédito Bogotá 1159383796 es copia de la del 1155297469 (fechas feb–jul 2026 y saldo cero al 14-jul): no representa el crédito vigente. | D25: Cualitativo | E25: NIIF 9 B5.4 | F25: Elaborar la tabla del crédito nuevo (22-jul-26 a 22-ene-27). | G25: Pendiente de soporte (PEND-5, PEND-14)
A26: 22 | B26: Valuación (tabla) | C26: Columna 'medición al costo' (costo amortizado) de las tablas de créditos Davivienda mal formulada: resta los intereses del saldo (830624: costo amortizado < capital). | D26: =INDEX(Tablas_Amortizacion!AA$8:AA$44,MATCH("DAV-830624",Tablas_Amortizacion!A$8:A$44,0)) -> -2240162500 | E26: NIIF 9 p.4.2.1, 5.4.1 y B5.4.1 | F26: Corregir la fórmula; no usar esa columna para medir el pasivo. | G26: Pendiente de soporte (PEND-14)
A27: 23 | B27: Derechos y obligaciones | C27: El archivo de tablas incluye el crédito Davivienda DYPSIS 7000482800190700 por $72.300 MM (may-25 a may-27) que no está en el mayor de Guaicaramo. | D27: 72300000000 | E27: NIC 24; NIIF 9 §2.1(e) y B2.5 (garantías financieras); NIC 37 p.86 | F27: Confirmar titular, vinculación y si Guaicaramo es garante/codeudor; revelar si aplica. | G27: Pendiente de soporte (PEND-13)
A28: 24 | B28: Integridad (tablas) | C28: Faltan tablas de amortización para: leasing Bancolombia 386735, leasing GECOLSA, BBVA renovado (0141) y crédito Bogotá 1159383796. | D28: Cualitativo | E28: NIIF 7 p.39; NIC 1 p.69 | F28: Solicitar las tablas o planes de pago bancarios. | G28: Pendiente de soporte (PEND-8)
A30: Ajustes propuestos (AJE)
A31: AJE | B31: Cuenta | C31: Descripción | D31: Débito | E31: Crédito | F31: Soporte
A32: AJE-1 | B32: 53052030 | C32: Intereses sobre préstamos causados | D32: =Pruebas_Auditoria!K237 -> 1.5672993e+08 | F32: Causación de intereses de créditos al 31-jul-26
A33: AJE-1 | B33: 21300101 | C33: Intereses financieros por pagar O.F. | E33: =Pruebas_Auditoria!K237 -> 1.5672993e+08
A34: AJE-1 | B34: 53052040 | C34: Intereses leasing causados | D34: =Pruebas_Auditoria!K238 -> 30975464 | F34: Causación de intereses de leasing al 31-jul-26
A35: AJE-1 | B35: 21300102 | C35: Intereses leasing por pagar | E35: =Pruebas_Auditoria!K238 -> 30975464
A36: AJE-2 | B36: 21050201 | C36: Obligación financiera LP | D36: =Clasif_CP_LP!B11 -> 6.945e+08 | F36: Reclasificación de la porción corriente (presentación)
A37: AJE-2 | B37: 21050100 | C37: Obligación financiera CP | E37: =Clasif_CP_LP!B11 -> 6.945e+08
A38: AJE-2 | B38: 21202140 | C38: Leasing LP | D38: =Clasif_CP_LP!B12 -> 8.8213565e+08
A39: AJE-2 | B39: 21202040 | C39: Leasing CP | E39: =Clasif_CP_LP!B12 -> 8.8213565e+08
C40: Sumas iguales | D40: =SUM(D32:D39) -> 1.764341e+09 | E40: =SUM(E32:E39) -> 1.764341e+09
C41: AJE-2 se calcula con tablas de amortización y vencimientos (Clasif_CP_LP); para 386735 y GECOLSA (sin tabla) se mantiene la clasificación contable. El mayor de leasing cuadra con el banco en Bogotá; en Davivienda/Bancolombia se usa el extracto de dic-25 (estimado).

Sheet Pendientes
A1: Pendientes de soporte – el papel se emite sin esta información
A2: Las cifras afectadas se dejan calculadas con la información disponible y supuestos documentados; se actualizarán al recibir el soporte.
A4: Ref. | B4: Pendiente / información requerida | C4: Obligación (ID) | D4: Monto afectado (COP) | E4: Hallazgo relacionado | F4: Solicitar a | G4: Estado | H4: Tratamiento provisional en este papel
A5: PEND-1 | B5: Certificados de saldo de capital al 31-jul-26 de los leasings Davivienda 1019441-2, 1019448-3 y 1021275-3 (los extractos sólo traen la factura del canon). | C5: DAV-L1019441 / L1019448 / L1021275 | D5: =Pruebas_Auditoria!K247 -> 2.6058241e+09 | E5: 2, 3, 13 | F5: Davivienda Leasing | G5: Parcial – estimado con extracto dic-25 | H5: Saldo banco estimado = extracto 31-dic-25 (PT 2025) + movimientos 2026 [E] (Pruebas_Auditoria (bloque 3)). Facturas LEASING_1275-3/9441-2/9448-3_DAVIVIENDA.pdf recibidas sin saldo de capital.
A6: PEND-2 | B6: Certificados de saldo de los leasings Bancolombia 362095, 336817, 331330 y contrato + tabla de amortización del nuevo leasing 386735. | C6: BCL-L362095 / L336817 / L331330 / L386735 | D6: =Cruce_Detalle_Mayor!F16 -> 1.7160826e+08 | E6: 1, 2, 3, 13 | F6: Bancolombia | G6: Parcial – estimado con extracto dic-25 | H6: Saldo banco estimado con extracto dic-25 (PT 2025) [E]; 386735 se toma del mayor (NB-1014). La diferencia mayor vs detalle quedó explicada por obligación.
A7: PEND-3 | B7: Confirmación BBVA del crédito renovado 30-jun-26 ($4.700 MM): número de obligación, tasa y si el interés de julio se pagó (y a qué cuenta se llevó). | C7: BBVA-0141 | D7: =SUMIFS(Pruebas_Auditoria!K213:K235,Pruebas_Auditoria!A213:A235,"BBVA-0141") -> 50972240 | E7: 5, 13 | F7: BBVA / cliente | G7: Pendiente | H7: Se incluye en AJE-1 la causación estimada de julio; se retira si se demuestra el pago en 53052020.
A8: PEND-4 | B8: Confirmación Banco Popular del crédito 631309940-2 (saldo, tasa, fechas de cuota). | C8: POP-631309940 | D8: =SUMIFS(Detalle_62!$F$14:$F$35,Detalle_62!$C$14:$C$35,"POP-631309940") -> 287500000 | E8: 13 | F8: Banco Popular | G8: Pendiente | H8: Saldo del detalle 62; inicio de causación estimado 17-jun.
A9: PEND-5 | B9: Certificado del nuevo crédito Bogotá 1159383796 (prórroga del 1155297469): fecha de inicio, tasa y si hubo intereses entre el 14 y el 22-jul. | C9: BOG-1159383796 | D9: =SUMIFS(Pruebas_Auditoria!K213:K235,Pruebas_Auditoria!A213:A235,"BOG-1159383796") -> 30518761 | E9: 5, 13 | F9: Banco de Bogotá | G9: Pendiente | H9: Inicio estimado 22-jul con tasa del detalle 62 (IBR 3M + 0,8).
A10: PEND-6 | B10: Liquidación detallada Davivienda créditos 607691 y 569032 (IBR aplicado y spread): la tasa declarada 12,58% EA no reconcilia con lo facturado. | C10: DAV-607691 / DAV-569032 | D10: =Pruebas_Auditoria!K196+Pruebas_Auditoria!K197 -> -51336720 | E10: 6 | F10: Davivienda | G10: Pendiente | H10: Se acepta lo facturado (coincide con lo contabilizado); diferencia de tasa queda abierta.
A11: PEND-7 | B11: Estado de cuenta del leasing Davivienda 1019441: aplicación del pago del canon 032 (banco: sólo intereses $1.029.562; contabilidad: capital $11.973.677). | C11: DAV-L1019441 | D11: 11973677 | E11: 11 | F11: Cliente | G11: Parcial – banco reconfirma | H11: Sin ajuste hasta verificar. LEASING_9441-2_DAVIVIENDA.pdf reconfirma el lado del banco; falta la explicación del cliente del registro CL-416.
A12: PEND-8 | B12: Tablas de amortización por obligación para determinar la porción corriente a 12 meses (NIC 1.69). | C12: Todas | D12: =Clasif_CP_LP!B11+Clasif_CP_LP!B12 -> 1.5766357e+09 | E12: 8, 24 | F12: Cliente | G12: Parcial – tablas recibidas | H12: Tablas recibidas (papel 64): CP calculado por obligación en Clasif_CP_LP. Faltan tablas de 386735, GECOLSA, BBVA 0141 y 1159383796.
A13: PEND-9 | B13: Materialidad del encargo (global, de ejecución y umbral de errores triviales). | C13: — | D13: Cualitativo | E13: Todos | F13: Socio / gerente del encargo | G13: Pendiente | H13: Umbral de redondeo $1.000 y tolerancia de recálculo 2% (hoja Resumen, celdas amarillas).
A14: PEND-10 | B14: Fechas reales de último pago/canon de Banco Popular y leasings Bancolombia (362095, 336817, 331330) para la causación al corte. | C14: POP / BCL-L* | D14: =SUMIFS(Pruebas_Auditoria!K213:K235,Pruebas_Auditoria!A213:A235,"BCL-L*")+SUMIFS(Pruebas_Auditoria!K213:K235,Pruebas_Auditoria!A213:A235,"POP-*") -> 12382575 | E14: 5 | F14: Cliente / bancos | G14: Pendiente | H14: Fechas estimadas (anotadas en Pruebas_Auditoria (bloque 4) Parte 2).
A15: PEND-11 | B15: Documentación de la prueba del 10% (NIIF 9 B3.3.6) y costos de transacción de las renovaciones BBVA y Bogotá y de la refinanciación Davivienda 8906. | C15: BBVA-0141 / BOG-1159383796 / DAV-8906 | D15: Cualitativo | E15: 15 | F15: Cliente | G15: Pendiente | H15: Se asume modificación no sustancial a la par, sin costos.
A16: PEND-12 | B16: Contrato, tabla de amortización y certificado del leasing Davivienda GECOLSA (2 motogeneradores) registrado en 21202140 y no incluido en el detalle 62. | C16: DAV-LGECOLSA | D16: =SUMIFS(Pruebas_Auditoria!$H$148:$H$174,Pruebas_Auditoria!$A$148:$A$174,"DAV-LGECOLSA") -> 213861900 | E16: 18 | F16: Davivienda Leasing / cliente | G16: Pendiente | H16: Se toma el saldo del mayor; sin intereses identificados en 2026.
A17: PEND-13 | B17: Aclaración del crédito Davivienda DYPSIS 7000482800190700 ($72.300 MM) incluido en el archivo de tablas: titular, vinculación y garantías de Guaicaramo. | C17: DYP-482800190700 | D17: 72300000000 | E17: 23 | F17: Cliente / Davivienda | G17: Pendiente | H17: No se incluye en el pasivo de Guaicaramo; posible revelación (NIC 24 / garantías).
A18: PEND-14 | B18: Tablas de amortización corregidas: 362095 (error en periodo 5), crédito 1159383796 (Hoja2 copiada) y columna de costo amortizado de créditos Davivienda. | C18: BCL-L362095 / BOG-1159383796 / DAV-* | D18: Cualitativo | E18: 20, 21, 22 | F18: Cliente | G18: Pendiente | H18: Se usan los saldos del mayor y del banco; las tablas no se usan para medir.
B20: Pendientes abiertos | D20: =COUNTIF(G5:G18,"<>Recibido") -> 14
B21: Instrucción: al recibir un soporte suficiente, cambiar el Estado a 'Recibido' (se descuenta del contador), actualizar los datos de entrada (azul) en la hoja correspondiente y recalcular.

Sheet Cruce_Detalle_Mayor
A1: Cruce detalle 62 vs mayor (cuentas 2105 y 2120) – Integridad y exactitud
A2: Saldos del mayor tomados del balance con signo invertido (pasivo positivo). Movimientos de capital por obligación desde Mayor_Mov.
A4: A. Totales
A5: Concepto | B5: Cuentas mayor | D5: Saldo detalle 62 | E5: Saldo mayor 31-jul | F5: Diferencia (mayor − detalle) | G5: Estado
A6: Créditos (capital) | B6: 21050100 + 21050201 | D6: =SUMIFS(Detalle_62!$F$14:$F$35,Detalle_62!$D$14:$D$35,"Crédito") -> 3.8300667e+10 | E6: =-(Balance_21!$F$16+Balance_21!$F$18) -> 38300666666 | F6: =E6-D6 -> 0.66666412 | G6: =IF(ABS(F6)<=Resumen!$C$6,"OK","DIFERENCIA") -> OK
A7: Leasing financiero (capital) | B7: 21202040 + 21202140 | D7: =SUMIFS(Detalle_62!$F$14:$F$35,Detalle_62!$D$14:$D$35,"Leasing") -> 6.8852455e+09 | E7: =-(Balance_21!$F$22+Balance_21!$F$24) -> 7.9035116e+09 | F7: =E7-D7 -> 1.0182662e+09 | G7: =IF(ABS(F7)<=Resumen!$C$6,"OK","DIFERENCIA") -> DIFERENCIA
A8: TOTAL | D8: =D6+D7 -> 4.5185912e+10 | E8: =E6+E7 -> 4.6204178e+10 | F8: =E8-D8 -> 1.0182662e+09 | G8: =IF(ABS(F8)<=Resumen!$C$6,"OK","DIFERENCIA") -> DIFERENCIA
A9: Comprobación: total detalle = 'Total Obligaciones' del cliente | D9: =Detalle_62!F36-D8 -> 0
A10: Tarjetas de crédito (21050301) e intereses por pagar (2130) no forman parte del detalle 62.
A12: B. Explicación de la diferencia en leasing (mayor − detalle) por obligación – ver Pruebas_Auditoria (bloque 3)
A13: Partida | F13: Valor | I13: Soporte
A14: 1. Leasing Bancolombia 386735 (camión VW Constellation) registrado el 28-jul-26 y omitido en el detalle 62 | F14: =SUMIFS(Pruebas_Auditoria!$N$148:$N$174,Pruebas_Auditoria!$A$148:$A$174,"BCL-L386735") -> 675837500 | I14: NB-00001014: Cr 21202040 $572.363.196 + Cr 21202140 $103.474.304.
A15: 2. Leasing Davivienda GECOLSA (2 motogeneradores) en el mayor desde jul-25 y omitido en el detalle 62 (tampoco validado en el PT 2025) | F15: =SUMIFS(Pruebas_Auditoria!$N$148:$N$174,Pruebas_Auditoria!$A$148:$A$174,"DAV-LGECOLSA") -> 213861900 | I15: Mayor_Dic25: reintegro anticipo GECOLSA, doc. 2672, $213.861.900.
A16: 3. Leasings Banco de Bogotá: el mayor coincide con los certificados; el detalle 62 trae saldos de tablas teóricas | F16: =SUMIFS(Pruebas_Auditoria!$N$148:$N$174,Pruebas_Auditoria!$A$148:$A$174,"BOG-L*") -> 1.7160826e+08 | I16: Pruebas_Auditoria (bloque 3): Mayor − banco ≈ 0 en los 6 contratos.
A17: 4. Leasings Davivienda 1019441, 1019448 y 1021275: detalle 62 = tabla teórica; mayor = extracto dic-25 − pagos 2026 | F17: =SUMIFS(Pruebas_Auditoria!$N$148:$N$174,Pruebas_Auditoria!$A$148:$A$174,"DAV-L1*") -> 3246479.2 | I17: 1021275: la tabla capitaliza intereses; banco mantiene $1.876.684.264.
A18: 5. Leasings Bancolombia 362095, 336817 y 331330: detalle 62 desactualizado (362095 con saldo de dic-25) | F18: =SUMIFS(Pruebas_Auditoria!$N$148:$N$174,Pruebas_Auditoria!$A$148:$A$174,"BCL-L362095")+SUMIFS(Pruebas_Auditoria!$N$148:$N$174,Pruebas_Auditoria!$A$148:$A$174,"BCL-L336817")+SUMIFS(Pruebas_Auditoria!$N$148:$N$174,Pruebas_Auditoria!$A$148:$A$174,"BCL-L331330") -> -46287958 | I18: Ver Tablas_Amortizacion (resumen) (error en tabla 362095).
A19: 6. Diferencia residual no explicada | F19: =F7-SUM(F14:F18) -> 0
A20: Total diferencia leasing | F20: =SUM(F14:F19) -> 1.0182662e+09 | G20: =IF(ABS(F20-F7)<0.01,"Cuadra","Revisar") -> Cuadra
A22: C. Roll-forward de capital por obligación (detalle 62 + movimiento ene–jul) → saldo inicial implícito al 1-ene-26
A23: ID auditoría | B23: Banco | C23: Tipo | D23: Saldo detalle 62 (31-jul) | E23: Pagos de capital (débitos) | F23: Desembolsos / renovaciones (créditos) | G23: Saldo inicial implícito 1-ene | H23: En detalle 62? | I23: Comentario
A24: DAV-L1019441 | B24: BANCO DAVIVIENDA | C24: Leasing | D24: =SUMIFS(Detalle_62!$F$14:$F$35,Detalle_62!$C$14:$C$35,A24) -> 3.9858217e+08 | E24: =SUMIFS(Mayor_Mov!$E$5:$E$445,Mayor_Mov!$N$5:$N$445,$A24,Mayor_Mov!$B$5:$B$445,"21050100")+SUMIFS(Mayor_Mov!$E$5:$E$445,Mayor_Mov!$N$5:$N$445,$A24,Mayor_Mov!$B$5:$B$445,"21050201")+SUMIFS(Mayor_Mov!$E$5:$E$445,Mayor_Mov!$N$5:$N$445,$A24,Mayor_Mov!$B$5:$B$445,"21202040")+SUMIFS(Mayor_Mov!$E$5:$E$445,Mayor_Mov!$N$5:$N$445,$A24,Mayor_Mov!$B$5:$B$445,"21202140") -> 82483752 | F24: =SUMIFS(Mayor_Mov!$F$5:$F$445,Mayor_Mov!$N$5:$N$445,$A24,Mayor_Mov!$B$5:$B$445,"21050100")+SUMIFS(Mayor_Mov!$F$5:$F$445,Mayor_Mov!$N$5:$N$445,$A24,Mayor_Mov!$B$5:$B$445,"21050201")+SUMIFS(Mayor_Mov!$F$5:$F$445,Mayor_Mov!$N$5:$N$445,$A24,Mayor_Mov!$B$5:$B$445,"21202040")+SUMIFS(Mayor_Mov!$F$5:$F$445,Mayor_Mov!$N$5:$N$445,$A24,Mayor_Mov!$B$5:$B$445,"21202140") -> 0 | G24: =D24+E24-F24 -> 4.8106592e+08 | H24: =IF(COUNTIF(Detalle_62!$C$14:$C$35,A24)>0,"Sí","NO") -> Sí
A25: DAV-L1019448 | B25: BANCO DAVIVIENDA | C25: Leasing | D25: =SUMIFS(Detalle_62!$F$14:$F$35,Detalle_62!$C$14:$C$35,A25) -> 3.2352969e+08 | E25: =SUMIFS(Mayor_Mov!$E$5:$E$445,Mayor_Mov!$N$5:$N$445,$A25,Mayor_Mov!$B$5:$B$445,"21050100")+SUMIFS(Mayor_Mov!$E$5:$E$445,Mayor_Mov!$N$5:$N$445,$A25,Mayor_Mov!$B$5:$B$445,"21050201")+SUMIFS(Mayor_Mov!$E$5:$E$445,Mayor_Mov!$N$5:$N$445,$A25,Mayor_Mov!$B$5:$B$445,"21202040")+SUMIFS(Mayor_Mov!$E$5:$E$445,Mayor_Mov!$N$5:$N$445,$A25,Mayor_Mov!$B$5:$B$445,"21202140") -> 60352563 | F25: =SUMIFS(Mayor_Mov!$F$5:$F$445,Mayor_Mov!$N$5:$N$445,$A25,Mayor_Mov!$B$5:$B$445,"21050100")+SUMIFS(Mayor_Mov!$F$5:$F$445,Mayor_Mov!$N$5:$N$445,$A25,Mayor_Mov!$B$5:$B$445,"21050201")+SUMIFS(Mayor_Mov!$F$5:$F$445,Mayor_Mov!$N$5:$N$445,$A25,Mayor_Mov!$B$5:$B$445,"21202040")+SUMIFS(Mayor_Mov!$F$5:$F$445,Mayor_Mov!$N$5:$N$445,$A25,Mayor_Mov!$B$5:$B$445,"21202140") -> 0 | G25: =D25+E25-F25 -> 3.8388225e+08 | H25: =IF(COUNTIF(Detalle_62!$C$14:$C$35,A25)>0,"Sí","NO") -> Sí
A26: DAV-L1021275 | B26: BANCO DAVIVIENDA | C26: Leasing | D26: =SUMIFS(Detalle_62!$F$14:$F$35,Detalle_62!$C$14:$C$35,A26) -> 1.8837122e+09 | E26: =SUMIFS(Mayor_Mov!$E$5:$E$445,Mayor_Mov!$N$5:$N$445,$A26,Mayor_Mov!$B$5:$B$445,"21050100")+SUMIFS(Mayor_Mov!$E$5:$E$445,Mayor_Mov!$N$5:$N$445,$A26,Mayor_Mov!$B$5:$B$445,"21050201")+SUMIFS(Mayor_Mov!$E$5:$E$445,Mayor_Mov!$N$5:$N$445,$A26,Mayor_Mov!$B$5:$B$445,"21202040")+SUMIFS(Mayor_Mov!$E$5:$E$445,Mayor_Mov!$N$5:$N$445,$A26,Mayor_Mov!$B$5:$B$445,"21202140") -> 0 | F26: =SUMIFS(Mayor_Mov!$F$5:$F$445,Mayor_Mov!$N$5:$N$445,$A26,Mayor_Mov!$B$5:$B$445,"21050100")+SUMIFS(Mayor_Mov!$F$5:$F$445,Mayor_Mov!$N$5:$N$445,$A26,Mayor_Mov!$B$5:$B$445,"21050201")+SUMIFS(Mayor_Mov!$F$5:$F$445,Mayor_Mov!$N$5:$N$445,$A26,Mayor_Mov!$B$5:$B$445,"21202040")+SUMIFS(Mayor_Mov!$F$5:$F$445,Mayor_Mov!$N$5:$N$445,$A26,Mayor_Mov!$B$5:$B$445,"21202140") -> 0 | G26: =D26+E26-F26 -> 1.8837122e+09 | H26: =IF(COUNTIF(Detalle_62!$C$14:$C$35,A26)>0,"Sí","NO") -> Sí
A27: DAV-569032 | B27: BANCO DAVIVIENDA | C27: Crédito | D27: =SUMIFS(Detalle_62!$F$14:$F$35,Detalle_62!$C$14:$C$35,A27) -> 3000000000 | E27: =SUMIFS(Mayor_Mov!$E$5:$E$445,Mayor_Mov!$N$5:$N$445,$A27,Mayor_Mov!$B$5:$B$445,"21050100")+SUMIFS(Mayor_Mov!$E$5:$E$445,Mayor_Mov!$N$5:$N$445,$A27,Mayor_Mov!$B$5:$B$445,"21050201")+SUMIFS(Mayor_Mov!$E$5:$E$445,Mayor_Mov!$N$5:$N$445,$A27,Mayor_Mov!$B$5:$B$445,"21202040")+SUMIFS(Mayor_Mov!$E$5:$E$445,Mayor_Mov!$N$5:$N$445,$A27,Mayor_Mov!$B$5:$B$445,"21202140") -> 0 | F27: =SUMIFS(Mayor_Mov!$F$5:$F$445,Mayor_Mov!$N$5:$N$445,$A27,Mayor_Mov!$B$5:$B$445,"21050100")+SUMIFS(Mayor_Mov!$F$5:$F$445,Mayor_Mov!$N$5:$N$445,$A27,Mayor_Mov!$B$5:$B$445,"21050201")+SUMIFS(Mayor_Mov!$F$5:$F$445,Mayor_Mov!$N$5:$N$445,$A27,Mayor_Mov!$B$5:$B$445,"21202040")+SUMIFS(Mayor_Mov!$F$5:$F$445,Mayor_Mov!$N$5:$N$445,$A27,Mayor_Mov!$B$5:$B$445,"21202140") -> 0 | G27: =D27+E27-F27 -> 3000000000 | H27: =IF(COUNTIF(Detalle_62!$C$14:$C$35,A27)>0,"Sí","NO") -> Sí
A28: DAV-830624 | B28: BANCO DAVIVIENDA | C28: Crédito | D28: =SUMIFS(Detalle_62!$F$14:$F$35,Detalle_62!$C$14:$C$35,A28) -> 7500000000 | E28: =SUMIFS(Mayor_Mov!$E$5:$E$445,Mayor_Mov!$N$5:$N$445,$A28,Mayor_Mov!$B$5:$B$445,"21050100")+SUMIFS(Mayor_Mov!$E$5:$E$445,Mayor_Mov!$N$5:$N$445,$A28,Mayor_Mov!$B$5:$B$445,"21050201")+SUMIFS(Mayor_Mov!$E$5:$E$445,Mayor_Mov!$N$5:$N$445,$A28,Mayor_Mov!$B$5:$B$445,"21202040")+SUMIFS(Mayor_Mov!$E$5:$E$445,Mayor_Mov!$N$5:$N$445,$A28,Mayor_Mov!$B$5:$B$445,"21202140") -> 0 | F28: =SUMIFS(Mayor_Mov!$F$5:$F$445,Mayor_Mov!$N$5:$N$445,$A28,Mayor_Mov!$B$5:$B$445,"21050100")+SUMIFS(Mayor_Mov!$F$5:$F$445,Mayor_Mov!$N$5:$N$445,$A28,Mayor_Mov!$B$5:$B$445,"21050201")+SUMIFS(Mayor_Mov!$F$5:$F$445,Mayor_Mov!$N$5:$N$445,$A28,Mayor_Mov!$B$5:$B$445,"21202040")+SUMIFS(Mayor_Mov!$F$5:$F$445,Mayor_Mov!$N$5:$N$445,$A28,Mayor_Mov!$B$5:$B$445,"21202140") -> 0 | G28: =D28+E28-F28 -> 7500000000 | H28: =IF(COUNTIF(Detalle_62!$C$14:$C$35,A28)>0,"Sí","NO") -> Sí
A29: DAV-607691 | B29: BANCO DAVIVIENDA | C29: Crédito | D29: =SUMIFS(Detalle_62!$F$14:$F$35,Detalle_62!$C$14:$C$35,A29) -> 3960000000 | E29: =SUMIFS(Mayor_Mov!$E$5:$E$445,Mayor_Mov!$N$5:$N$445,$A29,Mayor_Mov!$B$5:$B$445,"21050100")+SUMIFS(Mayor_Mov!$E$5:$E$445,Mayor_Mov!$N$5:$N$445,$A29,Mayor_Mov!$B$5:$B$445,"21050201")+SUMIFS(Mayor_Mov!$E$5:$E$445,Mayor_Mov!$N$5:$N$445,$A29,Mayor_Mov!$B$5:$B$445,"21202040")+SUMIFS(Mayor_Mov!$E$5:$E$445,Mayor_Mov!$N$5:$N$445,$A29,Mayor_Mov!$B$5:$B$445,"21202140") -> 0 | F29: =SUMIFS(Mayor_Mov!$F$5:$F$445,Mayor_Mov!$N$5:$N$445,$A29,Mayor_Mov!$B$5:$B$445,"21050100")+SUMIFS(Mayor_Mov!$F$5:$F$445,Mayor_Mov!$N$5:$N$445,$A29,Mayor_Mov!$B$5:$B$445,"21050201")+SUMIFS(Mayor_Mov!$F$5:$F$445,Mayor_Mov!$N$5:$N$445,$A29,Mayor_Mov!$B$5:$B$445,"21202040")+SUMIFS(Mayor_Mov!$F$5:$F$445,Mayor_Mov!$N$5:$N$445,$A29,Mayor_Mov!$B$5:$B$445,"21202140") -> 0 | G29: =D29+E29-F29 -> 3960000000 | H29: =IF(COUNTIF(Detalle_62!$C$14:$C$35,A29)>0,"Sí","NO") -> Sí
A30: BOG-453436746 | B30: BANCO DE BOGOTA | C30: Crédito | D30: =SUMIFS(Detalle_62!$F$14:$F$35,Detalle_62!$C$14:$C$35,A30) -> 2937500000 | E30: =SUMIFS(Mayor_Mov!$E$5:$E$445,Mayor_Mov!$N$5:$N$445,$A30,Mayor_Mov!$B$5:$B$445,"21050100")+SUMIFS(Mayor_Mov!$E$5:$E$445,Mayor_Mov!$N$5:$N$445,$A30,Mayor_Mov!$B$5:$B$445,"21050201")+SUMIFS(Mayor_Mov!$E$5:$E$445,Mayor_Mov!$N$5:$N$445,$A30,Mayor_Mov!$B$5:$B$445,"21202040")+SUMIFS(Mayor_Mov!$E$5:$E$445,Mayor_Mov!$N$5:$N$445,$A30,Mayor_Mov!$B$5:$B$445,"21202140") -> 437500000 | F30: =SUMIFS(Mayor_Mov!$F$5:$F$445,Mayor_Mov!$N$5:$N$445,$A30,Mayor_Mov!$B$5:$B$445,"21050100")+SUMIFS(Mayor_Mov!$F$5:$F$445,Mayor_Mov!$N$5:$N$445,$A30,Mayor_Mov!$B$5:$B$445,"21050201")+SUMIFS(Mayor_Mov!$F$5:$F$445,Mayor_Mov!$N$5:$N$445,$A30,Mayor_Mov!$B$5:$B$445,"21202040")+SUMIFS(Mayor_Mov!$F$5:$F$445,Mayor_Mov!$N$5:$N$445,$A30,Mayor_Mov!$B$5:$B$445,"21202140") -> 0 | G30: =D30+E30-F30 -> 3375000000 | H30: =IF(COUNTIF(Detalle_62!$C$14:$C$35,A30)>0,"Sí","NO") -> Sí
A31: BOG-856670629 | B31: BANCO DE BOGOTA | C31: Crédito | D31: =SUMIFS(Detalle_62!$F$14:$F$35,Detalle_62!$C$14:$C$35,A31) -> 1457333332 | E31: =SUMIFS(Mayor_Mov!$E$5:$E$445,Mayor_Mov!$N$5:$N$445,$A31,Mayor_Mov!$B$5:$B$445,"21050100")+SUMIFS(Mayor_Mov!$E$5:$E$445,Mayor_Mov!$N$5:$N$445,$A31,Mayor_Mov!$B$5:$B$445,"21050201")+SUMIFS(Mayor_Mov!$E$5:$E$445,Mayor_Mov!$N$5:$N$445,$A31,Mayor_Mov!$B$5:$B$445,"21202040")+SUMIFS(Mayor_Mov!$E$5:$E$445,Mayor_Mov!$N$5:$N$445,$A31,Mayor_Mov!$B$5:$B$445,"21202140") -> 364333334 | F31: =SUMIFS(Mayor_Mov!$F$5:$F$445,Mayor_Mov!$N$5:$N$445,$A31,Mayor_Mov!$B$5:$B$445,"21050100")+SUMIFS(Mayor_Mov!$F$5:$F$445,Mayor_Mov!$N$5:$N$445,$A31,Mayor_Mov!$B$5:$B$445,"21050201")+SUMIFS(Mayor_Mov!$F$5:$F$445,Mayor_Mov!$N$5:$N$445,$A31,Mayor_Mov!$B$5:$B$445,"21202040")+SUMIFS(Mayor_Mov!$F$5:$F$445,Mayor_Mov!$N$5:$N$445,$A31,Mayor_Mov!$B$5:$B$445,"21202140") -> 0 | G31: =D31+E31-F31 -> 1821666666 | H31: =IF(COUNTIF(Detalle_62!$C$14:$C$35,A31)>0,"Sí","NO") -> Sí
A32: BOG-858177259 | B32: BANCO DE BOGOTA | C32: Crédito | D32: =SUMIFS(Detalle_62!$F$14:$F$35,Detalle_62!$C$14:$C$35,A32) -> 1125000000 | E32: =SUMIFS(Mayor_Mov!$E$5:$E$445,Mayor_Mov!$N$5:$N$445,$A32,Mayor_Mov!$B$5:$B$445,"21050100")+SUMIFS(Mayor_Mov!$E$5:$E$445,Mayor_Mov!$N$5:$N$445,$A32,Mayor_Mov!$B$5:$B$445,"21050201")+SUMIFS(Mayor_Mov!$E$5:$E$445,Mayor_Mov!$N$5:$N$445,$A32,Mayor_Mov!$B$5:$B$445,"21202040")+SUMIFS(Mayor_Mov!$E$5:$E$445,Mayor_Mov!$N$5:$N$445,$A32,Mayor_Mov!$B$5:$B$445,"21202140") -> 250000000 | F32: =SUMIFS(Mayor_Mov!$F$5:$F$445,Mayor_Mov!$N$5:$N$445,$A32,Mayor_Mov!$B$5:$B$445,"21050100")+SUMIFS(Mayor_Mov!$F$5:$F$445,Mayor_Mov!$N$5:$N$445,$A32,Mayor_Mov!$B$5:$B$445,"21050201")+SUMIFS(Mayor_Mov!$F$5:$F$445,Mayor_Mov!$N$5:$N$445,$A32,Mayor_Mov!$B$5:$B$445,"21202040")+SUMIFS(Mayor_Mov!$F$5:$F$445,Mayor_Mov!$N$5:$N$445,$A32,Mayor_Mov!$B$5:$B$445,"21202140") -> 0 | G32: =D32+E32-F32 -> 1375000000 | H32: =IF(COUNTIF(Detalle_62!$C$14:$C$35,A32)>0,"Sí","NO") -> Sí
A33: BOG-1159383796 | B33: BANCO DE BOGOTA | C33: Crédito | D33: =SUMIFS(Detalle_62!$F$14:$F$35,Detalle_62!$C$14:$C$35,A33) -> 10000000000 | E33: =SUMIFS(Mayor_Mov!$E$5:$E$445,Mayor_Mov!$N$5:$N$445,$A33,Mayor_Mov!$B$5:$B$445,"21050100")+SUMIFS(Mayor_Mov!$E$5:$E$445,Mayor_Mov!$N$5:$N$445,$A33,Mayor_Mov!$B$5:$B$445,"21050201")+SUMIFS(Mayor_Mov!$E$5:$E$445,Mayor_Mov!$N$5:$N$445,$A33,Mayor_Mov!$B$5:$B$445,"21202040")+SUMIFS(Mayor_Mov!$E$5:$E$445,Mayor_Mov!$N$5:$N$445,$A33,Mayor_Mov!$B$5:$B$445,"21202140") -> 10000000000 | F33: =SUMIFS(Mayor_Mov!$F$5:$F$445,Mayor_Mov!$N$5:$N$445,$A33,Mayor_Mov!$B$5:$B$445,"21050100")+SUMIFS(Mayor_Mov!$F$5:$F$445,Mayor_Mov!$N$5:$N$445,$A33,Mayor_Mov!$B$5:$B$445,"21050201")+SUMIFS(Mayor_Mov!$F$5:$F$445,Mayor_Mov!$N$5:$N$445,$A33,Mayor_Mov!$B$5:$B$445,"21202040")+SUMIFS(Mayor_Mov!$F$5:$F$445,Mayor_Mov!$N$5:$N$445,$A33,Mayor_Mov!$B$5:$B$445,"21202140") -> 20000000000 | G33: =D33+E33-F33 -> 0 | H33: =IF(COUNTIF(Detalle_62!$C$14:$C$35,A33)>0,"Sí","NO") -> Sí | I33: Incluye el crédito 1155297469 (desembolso 28-ene) y su prórroga al 1159383796 (29-jul).
A34: BOG-L556449224 | B34: BANCO DE BOGOTA | C34: Leasing | D34: =SUMIFS(Detalle_62!$F$14:$F$35,Detalle_62!$C$14:$C$35,A34) -> 3.8184539e+08 | E34: =SUMIFS(Mayor_Mov!$E$5:$E$445,Mayor_Mov!$N$5:$N$445,$A34,Mayor_Mov!$B$5:$B$445,"21050100")+SUMIFS(Mayor_Mov!$E$5:$E$445,Mayor_Mov!$N$5:$N$445,$A34,Mayor_Mov!$B$5:$B$445,"21050201")+SUMIFS(Mayor_Mov!$E$5:$E$445,Mayor_Mov!$N$5:$N$445,$A34,Mayor_Mov!$B$5:$B$445,"21202040")+SUMIFS(Mayor_Mov!$E$5:$E$445,Mayor_Mov!$N$5:$N$445,$A34,Mayor_Mov!$B$5:$B$445,"21202140") -> 63658994 | F34: =SUMIFS(Mayor_Mov!$F$5:$F$445,Mayor_Mov!$N$5:$N$445,$A34,Mayor_Mov!$B$5:$B$445,"21050100")+SUMIFS(Mayor_Mov!$F$5:$F$445,Mayor_Mov!$N$5:$N$445,$A34,Mayor_Mov!$B$5:$B$445,"21050201")+SUMIFS(Mayor_Mov!$F$5:$F$445,Mayor_Mov!$N$5:$N$445,$A34,Mayor_Mov!$B$5:$B$445,"21202040")+SUMIFS(Mayor_Mov!$F$5:$F$445,Mayor_Mov!$N$5:$N$445,$A34,Mayor_Mov!$B$5:$B$445,"21202140") -> 0 | G34: =D34+E34-F34 -> 4.4550438e+08 | H34: =IF(COUNTIF(Detalle_62!$C$14:$C$35,A34)>0,"Sí","NO") -> Sí
A35: BOG-L556449180 | B35: BANCO DE BOGOTA | C35: Leasing | D35: =SUMIFS(Detalle_62!$F$14:$F$35,Detalle_62!$C$14:$C$35,A35) -> 3.8184539e+08 | E35: =SUMIFS(Mayor_Mov!$E$5:$E$445,Mayor_Mov!$N$5:$N$445,$A35,Mayor_Mov!$B$5:$B$445,"21050100")+SUMIFS(Mayor_Mov!$E$5:$E$445,Mayor_Mov!$N$5:$N$445,$A35,Mayor_Mov!$B$5:$B$445,"21050201")+SUMIFS(Mayor_Mov!$E$5:$E$445,Mayor_Mov!$N$5:$N$445,$A35,Mayor_Mov!$B$5:$B$445,"21202040")+SUMIFS(Mayor_Mov!$E$5:$E$445,Mayor_Mov!$N$5:$N$445,$A35,Mayor_Mov!$B$5:$B$445,"21202140") -> 63658994 | F35: =SUMIFS(Mayor_Mov!$F$5:$F$445,Mayor_Mov!$N$5:$N$445,$A35,Mayor_Mov!$B$5:$B$445,"21050100")+SUMIFS(Mayor_Mov!$F$5:$F$445,Mayor_Mov!$N$5:$N$445,$A35,Mayor_Mov!$B$5:$B$445,"21050201")+SUMIFS(Mayor_Mov!$F$5:$F$445,Mayor_Mov!$N$5:$N$445,$A35,Mayor_Mov!$B$5:$B$445,"21202040")+SUMIFS(Mayor_Mov!$F$5:$F$445,Mayor_Mov!$N$5:$N$445,$A35,Mayor_Mov!$B$5:$B$445,"21202140") -> 0 | G35: =D35+E35-F35 -> 4.4550438e+08 | H35: =IF(COUNTIF(Detalle_62!$C$14:$C$35,A35)>0,"Sí","NO") -> Sí
A36: BOG-L556449117 | B36: BANCO DE BOGOTA | C36: Leasing | D36: =SUMIFS(Detalle_62!$F$14:$F$35,Detalle_62!$C$14:$C$35,A36) -> 1.9672018e+08 | E36: =SUMIFS(Mayor_Mov!$E$5:$E$445,Mayor_Mov!$N$5:$N$445,$A36,Mayor_Mov!$B$5:$B$445,"21050100")+SUMIFS(Mayor_Mov!$E$5:$E$445,Mayor_Mov!$N$5:$N$445,$A36,Mayor_Mov!$B$5:$B$445,"21050201")+SUMIFS(Mayor_Mov!$E$5:$E$445,Mayor_Mov!$N$5:$N$445,$A36,Mayor_Mov!$B$5:$B$445,"21202040")+SUMIFS(Mayor_Mov!$E$5:$E$445,Mayor_Mov!$N$5:$N$445,$A36,Mayor_Mov!$B$5:$B$445,"21202140") -> 78102954 | F36: =SUMIFS(Mayor_Mov!$F$5:$F$445,Mayor_Mov!$N$5:$N$445,$A36,Mayor_Mov!$B$5:$B$445,"21050100")+SUMIFS(Mayor_Mov!$F$5:$F$445,Mayor_Mov!$N$5:$N$445,$A36,Mayor_Mov!$B$5:$B$445,"21050201")+SUMIFS(Mayor_Mov!$F$5:$F$445,Mayor_Mov!$N$5:$N$445,$A36,Mayor_Mov!$B$5:$B$445,"21202040")+SUMIFS(Mayor_Mov!$F$5:$F$445,Mayor_Mov!$N$5:$N$445,$A36,Mayor_Mov!$B$5:$B$445,"21202140") -> 0 | G36: =D36+E36-F36 -> 2.7482313e+08 | H36: =IF(COUNTIF(Detalle_62!$C$14:$C$35,A36)>0,"Sí","NO") -> Sí
A37: BOG-L556449064 | B37: BANCO DE BOGOTA | C37: Leasing | D37: =SUMIFS(Detalle_62!$F$14:$F$35,Detalle_62!$C$14:$C$35,A37) -> 1.9672018e+08 | E37: =SUMIFS(Mayor_Mov!$E$5:$E$445,Mayor_Mov!$N$5:$N$445,$A37,Mayor_Mov!$B$5:$B$445,"21050100")+SUMIFS(Mayor_Mov!$E$5:$E$445,Mayor_Mov!$N$5:$N$445,$A37,Mayor_Mov!$B$5:$B$445,"21050201")+SUMIFS(Mayor_Mov!$E$5:$E$445,Mayor_Mov!$N$5:$N$445,$A37,Mayor_Mov!$B$5:$B$445,"21202040")+SUMIFS(Mayor_Mov!$E$5:$E$445,Mayor_Mov!$N$5:$N$445,$A37,Mayor_Mov!$B$5:$B$445,"21202140") -> 78102954 | F37: =SUMIFS(Mayor_Mov!$F$5:$F$445,Mayor_Mov!$N$5:$N$445,$A37,Mayor_Mov!$B$5:$B$445,"21050100")+SUMIFS(Mayor_Mov!$F$5:$F$445,Mayor_Mov!$N$5:$N$445,$A37,Mayor_Mov!$B$5:$B$445,"21050201")+SUMIFS(Mayor_Mov!$F$5:$F$445,Mayor_Mov!$N$5:$N$445,$A37,Mayor_Mov!$B$5:$B$445,"21202040")+SUMIFS(Mayor_Mov!$F$5:$F$445,Mayor_Mov!$N$5:$N$445,$A37,Mayor_Mov!$B$5:$B$445,"21202140") -> 0 | G37: =D37+E37-F37 -> 2.7482313e+08 | H37: =IF(COUNTIF(Detalle_62!$C$14:$C$35,A37)>0,"Sí","NO") -> Sí
A38: BOG-L556449288 | B38: BANCO DE BOGOTA | C38: Leasing | D38: =SUMIFS(Detalle_62!$F$14:$F$35,Detalle_62!$C$14:$C$35,A38) -> 3.8264924e+08 | E38: =SUMIFS(Mayor_Mov!$E$5:$E$445,Mayor_Mov!$N$5:$N$445,$A38,Mayor_Mov!$B$5:$B$445,"21050100")+SUMIFS(Mayor_Mov!$E$5:$E$445,Mayor_Mov!$N$5:$N$445,$A38,Mayor_Mov!$B$5:$B$445,"21050201")+SUMIFS(Mayor_Mov!$E$5:$E$445,Mayor_Mov!$N$5:$N$445,$A38,Mayor_Mov!$B$5:$B$445,"21202040")+SUMIFS(Mayor_Mov!$E$5:$E$445,Mayor_Mov!$N$5:$N$445,$A38,Mayor_Mov!$B$5:$B$445,"21202140") -> 63672350 | F38: =SUMIFS(Mayor_Mov!$F$5:$F$445,Mayor_Mov!$N$5:$N$445,$A38,Mayor_Mov!$B$5:$B$445,"21050100")+SUMIFS(Mayor_Mov!$F$5:$F$445,Mayor_Mov!$N$5:$N$445,$A38,Mayor_Mov!$B$5:$B$445,"21050201")+SUMIFS(Mayor_Mov!$F$5:$F$445,Mayor_Mov!$N$5:$N$445,$A38,Mayor_Mov!$B$5:$B$445,"21202040")+SUMIFS(Mayor_Mov!$F$5:$F$445,Mayor_Mov!$N$5:$N$445,$A38,Mayor_Mov!$B$5:$B$445,"21202140") -> 0 | G38: =D38+E38-F38 -> 4.4632159e+08 | H38: =IF(COUNTIF(Detalle_62!$C$14:$C$35,A38)>0,"Sí","NO") -> Sí
A39: BOG-L557285005 | B39: BANCO DE BOGOTA | C39: Leasing | D39: =SUMIFS(Detalle_62!$F$14:$F$35,Detalle_62!$C$14:$C$35,A39) -> 9.6862047e+08 | E39: =SUMIFS(Mayor_Mov!$E$5:$E$445,Mayor_Mov!$N$5:$N$445,$A39,Mayor_Mov!$B$5:$B$445,"21050100")+SUMIFS(Mayor_Mov!$E$5:$E$445,Mayor_Mov!$N$5:$N$445,$A39,Mayor_Mov!$B$5:$B$445,"21050201")+SUMIFS(Mayor_Mov!$E$5:$E$445,Mayor_Mov!$N$5:$N$445,$A39,Mayor_Mov!$B$5:$B$445,"21202040")+SUMIFS(Mayor_Mov!$E$5:$E$445,Mayor_Mov!$N$5:$N$445,$A39,Mayor_Mov!$B$5:$B$445,"21202140") -> 1.8659222e+08 | F39: =SUMIFS(Mayor_Mov!$F$5:$F$445,Mayor_Mov!$N$5:$N$445,$A39,Mayor_Mov!$B$5:$B$445,"21050100")+SUMIFS(Mayor_Mov!$F$5:$F$445,Mayor_Mov!$N$5:$N$445,$A39,Mayor_Mov!$B$5:$B$445,"21050201")+SUMIFS(Mayor_Mov!$F$5:$F$445,Mayor_Mov!$N$5:$N$445,$A39,Mayor_Mov!$B$5:$B$445,"21202040")+SUMIFS(Mayor_Mov!$F$5:$F$445,Mayor_Mov!$N$5:$N$445,$A39,Mayor_Mov!$B$5:$B$445,"21202140") -> 0 | G39: =D39+E39-F39 -> 1.1552127e+09 | H39: =IF(COUNTIF(Detalle_62!$C$14:$C$35,A39)>0,"Sí","NO") -> Sí
A40: POP-631309940 | B40: BANCO POPULAR | C40: Crédito | D40: =SUMIFS(Detalle_62!$F$14:$F$35,Detalle_62!$C$14:$C$35,A40) -> 287500000 | E40: =SUMIFS(Mayor_Mov!$E$5:$E$445,Mayor_Mov!$N$5:$N$445,$A40,Mayor_Mov!$B$5:$B$445,"21050100")+SUMIFS(Mayor_Mov!$E$5:$E$445,Mayor_Mov!$N$5:$N$445,$A40,Mayor_Mov!$B$5:$B$445,"21050201")+SUMIFS(Mayor_Mov!$E$5:$E$445,Mayor_Mov!$N$5:$N$445,$A40,Mayor_Mov!$B$5:$B$445,"21202040")+SUMIFS(Mayor_Mov!$E$5:$E$445,Mayor_Mov!$N$5:$N$445,$A40,Mayor_Mov!$B$5:$B$445,"21202140") -> 287500000 | F40: =SUMIFS(Mayor_Mov!$F$5:$F$445,Mayor_Mov!$N$5:$N$445,$A40,Mayor_Mov!$B$5:$B$445,"21050100")+SUMIFS(Mayor_Mov!$F$5:$F$445,Mayor_Mov!$N$5:$N$445,$A40,Mayor_Mov!$B$5:$B$445,"21050201")+SUMIFS(Mayor_Mov!$F$5:$F$445,Mayor_Mov!$N$5:$N$445,$A40,Mayor_Mov!$B$5:$B$445,"21202040")+SUMIFS(Mayor_Mov!$F$5:$F$445,Mayor_Mov!$N$5:$N$445,$A40,Mayor_Mov!$B$5:$B$445,"21202140") -> 0 | G40: =D40+E40-F40 -> 575000000 | H40: =IF(COUNTIF(Detalle_62!$C$14:$C$35,A40)>0,"Sí","NO") -> Sí
A41: BBVA-0141 | B41: BBVA | C41: Crédito | D41: =SUMIFS(Detalle_62!$F$14:$F$35,Detalle_62!$C$14:$C$35,A41) -> 4700000000 | E41: =SUMIFS(Mayor_Mov!$E$5:$E$445,Mayor_Mov!$N$5:$N$445,$A41,Mayor_Mov!$B$5:$B$445,"21050100")+SUMIFS(Mayor_Mov!$E$5:$E$445,Mayor_Mov!$N$5:$N$445,$A41,Mayor_Mov!$B$5:$B$445,"21050201")+SUMIFS(Mayor_Mov!$E$5:$E$445,Mayor_Mov!$N$5:$N$445,$A41,Mayor_Mov!$B$5:$B$445,"21202040")+SUMIFS(Mayor_Mov!$E$5:$E$445,Mayor_Mov!$N$5:$N$445,$A41,Mayor_Mov!$B$5:$B$445,"21202140") -> 4700000000 | F41: =SUMIFS(Mayor_Mov!$F$5:$F$445,Mayor_Mov!$N$5:$N$445,$A41,Mayor_Mov!$B$5:$B$445,"21050100")+SUMIFS(Mayor_Mov!$F$5:$F$445,Mayor_Mov!$N$5:$N$445,$A41,Mayor_Mov!$B$5:$B$445,"21050201")+SUMIFS(Mayor_Mov!$F$5:$F$445,Mayor_Mov!$N$5:$N$445,$A41,Mayor_Mov!$B$5:$B$445,"21202040")+SUMIFS(Mayor_Mov!$F$5:$F$445,Mayor_Mov!$N$5:$N$445,$A41,Mayor_Mov!$B$5:$B$445,"21202140") -> 4700000000 | G41: =D41+E41-F41 -> 4700000000 | H41: =IF(COUNTIF(Detalle_62!$C$14:$C$35,A41)>0,"Sí","NO") -> Sí | I41: Renovación 30-jun-26 (CE-35090) a la par. El detalle 62 lo identifica como 252059; el mayor como 9600290141/0141 (y 4476 en ene–mar).
A42: BCL-1260105867 | B42: BANCOLOMBIA S.A. | C42: Crédito | D42: =SUMIFS(Detalle_62!$F$14:$F$35,Detalle_62!$C$14:$C$35,A42) -> 3.3333333e+09 | E42: =SUMIFS(Mayor_Mov!$E$5:$E$445,Mayor_Mov!$N$5:$N$445,$A42,Mayor_Mov!$B$5:$B$445,"21050100")+SUMIFS(Mayor_Mov!$E$5:$E$445,Mayor_Mov!$N$5:$N$445,$A42,Mayor_Mov!$B$5:$B$445,"21050201")+SUMIFS(Mayor_Mov!$E$5:$E$445,Mayor_Mov!$N$5:$N$445,$A42,Mayor_Mov!$B$5:$B$445,"21202040")+SUMIFS(Mayor_Mov!$E$5:$E$445,Mayor_Mov!$N$5:$N$445,$A42,Mayor_Mov!$B$5:$B$445,"21202140") -> 1666666666 | F42: =SUMIFS(Mayor_Mov!$F$5:$F$445,Mayor_Mov!$N$5:$N$445,$A42,Mayor_Mov!$B$5:$B$445,"21050100")+SUMIFS(Mayor_Mov!$F$5:$F$445,Mayor_Mov!$N$5:$N$445,$A42,Mayor_Mov!$B$5:$B$445,"21050201")+SUMIFS(Mayor_Mov!$F$5:$F$445,Mayor_Mov!$N$5:$N$445,$A42,Mayor_Mov!$B$5:$B$445,"21202040")+SUMIFS(Mayor_Mov!$F$5:$F$445,Mayor_Mov!$N$5:$N$445,$A42,Mayor_Mov!$B$5:$B$445,"21202140") -> 0 | G42: =D42+E42-F42 -> 5e+09 | H42: =IF(COUNTIF(Detalle_62!$C$14:$C$35,A42)>0,"Sí","NO") -> Sí | I42: Mayor glosa '12660105867' (error de digitación).
A43: BCL-L362095 | B43: BANCOLOMBIA S.A. | C43: Leasing | D43: =SUMIFS(Detalle_62!$F$14:$F$35,Detalle_62!$C$14:$C$35,A43) -> 497241599 | E43: =SUMIFS(Mayor_Mov!$E$5:$E$445,Mayor_Mov!$N$5:$N$445,$A43,Mayor_Mov!$B$5:$B$445,"21050100")+SUMIFS(Mayor_Mov!$E$5:$E$445,Mayor_Mov!$N$5:$N$445,$A43,Mayor_Mov!$B$5:$B$445,"21050201")+SUMIFS(Mayor_Mov!$E$5:$E$445,Mayor_Mov!$N$5:$N$445,$A43,Mayor_Mov!$B$5:$B$445,"21202040")+SUMIFS(Mayor_Mov!$E$5:$E$445,Mayor_Mov!$N$5:$N$445,$A43,Mayor_Mov!$B$5:$B$445,"21202140") -> 47053001 | F43: =SUMIFS(Mayor_Mov!$F$5:$F$445,Mayor_Mov!$N$5:$N$445,$A43,Mayor_Mov!$B$5:$B$445,"21050100")+SUMIFS(Mayor_Mov!$F$5:$F$445,Mayor_Mov!$N$5:$N$445,$A43,Mayor_Mov!$B$5:$B$445,"21050201")+SUMIFS(Mayor_Mov!$F$5:$F$445,Mayor_Mov!$N$5:$N$445,$A43,Mayor_Mov!$B$5:$B$445,"21202040")+SUMIFS(Mayor_Mov!$F$5:$F$445,Mayor_Mov!$N$5:$N$445,$A43,Mayor_Mov!$B$5:$B$445,"21202140") -> 0 | G43: =D43+E43-F43 -> 544294600 | H43: =IF(COUNTIF(Detalle_62!$C$14:$C$35,A43)>0,"Sí","NO") -> Sí
A44: BCL-L336817 | B44: BANCOLOMBIA S.A. | C44: Leasing | D44: =SUMIFS(Detalle_62!$F$14:$F$35,Detalle_62!$C$14:$C$35,A44) -> 7.7008543e+08 | E44: =SUMIFS(Mayor_Mov!$E$5:$E$445,Mayor_Mov!$N$5:$N$445,$A44,Mayor_Mov!$B$5:$B$445,"21050100")+SUMIFS(Mayor_Mov!$E$5:$E$445,Mayor_Mov!$N$5:$N$445,$A44,Mayor_Mov!$B$5:$B$445,"21050201")+SUMIFS(Mayor_Mov!$E$5:$E$445,Mayor_Mov!$N$5:$N$445,$A44,Mayor_Mov!$B$5:$B$445,"21202040")+SUMIFS(Mayor_Mov!$E$5:$E$445,Mayor_Mov!$N$5:$N$445,$A44,Mayor_Mov!$B$5:$B$445,"21202140") -> 61870158 | F44: =SUMIFS(Mayor_Mov!$F$5:$F$445,Mayor_Mov!$N$5:$N$445,$A44,Mayor_Mov!$B$5:$B$445,"21050100")+SUMIFS(Mayor_Mov!$F$5:$F$445,Mayor_Mov!$N$5:$N$445,$A44,Mayor_Mov!$B$5:$B$445,"21050201")+SUMIFS(Mayor_Mov!$F$5:$F$445,Mayor_Mov!$N$5:$N$445,$A44,Mayor_Mov!$B$5:$B$445,"21202040")+SUMIFS(Mayor_Mov!$F$5:$F$445,Mayor_Mov!$N$5:$N$445,$A44,Mayor_Mov!$B$5:$B$445,"21202140") -> 0 | G44: =D44+E44-F44 -> 8.3195558e+08 | H44: =IF(COUNTIF(Detalle_62!$C$14:$C$35,A44)>0,"Sí","NO") -> Sí
A45: BCL-L331330 | B45: BANCOLOMBIA S.A. | C45: Leasing | D45: =SUMIFS(Detalle_62!$F$14:$F$35,Detalle_62!$C$14:$C$35,A45) -> 503693510 | E45: =SUMIFS(Mayor_Mov!$E$5:$E$445,Mayor_Mov!$N$5:$N$445,$A45,Mayor_Mov!$B$5:$B$445,"21050100")+SUMIFS(Mayor_Mov!$E$5:$E$445,Mayor_Mov!$N$5:$N$445,$A45,Mayor_Mov!$B$5:$B$445,"21050201")+SUMIFS(Mayor_Mov!$E$5:$E$445,Mayor_Mov!$N$5:$N$445,$A45,Mayor_Mov!$B$5:$B$445,"21202040")+SUMIFS(Mayor_Mov!$E$5:$E$445,Mayor_Mov!$N$5:$N$445,$A45,Mayor_Mov!$B$5:$B$445,"21202140") -> 117272673 | F45: =SUMIFS(Mayor_Mov!$F$5:$F$445,Mayor_Mov!$N$5:$N$445,$A45,Mayor_Mov!$B$5:$B$445,"21050100")+SUMIFS(Mayor_Mov!$F$5:$F$445,Mayor_Mov!$N$5:$N$445,$A45,Mayor_Mov!$B$5:$B$445,"21050201")+SUMIFS(Mayor_Mov!$F$5:$F$445,Mayor_Mov!$N$5:$N$445,$A45,Mayor_Mov!$B$5:$B$445,"21202040")+SUMIFS(Mayor_Mov!$F$5:$F$445,Mayor_Mov!$N$5:$N$445,$A45,Mayor_Mov!$B$5:$B$445,"21202140") -> 0 | G45: =D45+E45-F45 -> 620966183 | H45: =IF(COUNTIF(Detalle_62!$C$14:$C$35,A45)>0,"Sí","NO") -> Sí
A46: DAV-8906 | B46: BANCO DAVIVIENDA | C46: Crédito | D46: =SUMIFS(Detalle_62!$F$14:$F$35,Detalle_62!$C$14:$C$35,A46) -> 0 | E46: =SUMIFS(Mayor_Mov!$E$5:$E$445,Mayor_Mov!$N$5:$N$445,$A46,Mayor_Mov!$B$5:$B$445,"21050100")+SUMIFS(Mayor_Mov!$E$5:$E$445,Mayor_Mov!$N$5:$N$445,$A46,Mayor_Mov!$B$5:$B$445,"21050201")+SUMIFS(Mayor_Mov!$E$5:$E$445,Mayor_Mov!$N$5:$N$445,$A46,Mayor_Mov!$B$5:$B$445,"21202040")+SUMIFS(Mayor_Mov!$E$5:$E$445,Mayor_Mov!$N$5:$N$445,$A46,Mayor_Mov!$B$5:$B$445,"21202140") -> 10000000000 | F46: =SUMIFS(Mayor_Mov!$F$5:$F$445,Mayor_Mov!$N$5:$N$445,$A46,Mayor_Mov!$B$5:$B$445,"21050100")+SUMIFS(Mayor_Mov!$F$5:$F$445,Mayor_Mov!$N$5:$N$445,$A46,Mayor_Mov!$B$5:$B$445,"21050201")+SUMIFS(Mayor_Mov!$F$5:$F$445,Mayor_Mov!$N$5:$N$445,$A46,Mayor_Mov!$B$5:$B$445,"21202040")+SUMIFS(Mayor_Mov!$F$5:$F$445,Mayor_Mov!$N$5:$N$445,$A46,Mayor_Mov!$B$5:$B$445,"21202140") -> 0 | G46: =D46+E46-F46 -> 10000000000 | H46: =IF(COUNTIF(Detalle_62!$C$14:$C$35,A46)>0,"Sí","NO") -> NO | I46: Crédito Davivienda $10.000 MM cancelado el 28-ene-26 con el crédito Bogotá 1155297469 (refinanciación con otro banco: baja en cuentas NIIF 9.3.3.1).
A47: BCL-L386735 | B47: BANCOLOMBIA S.A. | C47: Leasing | D47: =SUMIFS(Detalle_62!$F$14:$F$35,Detalle_62!$C$14:$C$35,A47) -> 0 | E47: =SUMIFS(Mayor_Mov!$E$5:$E$445,Mayor_Mov!$N$5:$N$445,$A47,Mayor_Mov!$B$5:$B$445,"21050100")+SUMIFS(Mayor_Mov!$E$5:$E$445,Mayor_Mov!$N$5:$N$445,$A47,Mayor_Mov!$B$5:$B$445,"21050201")+SUMIFS(Mayor_Mov!$E$5:$E$445,Mayor_Mov!$N$5:$N$445,$A47,Mayor_Mov!$B$5:$B$445,"21202040")+SUMIFS(Mayor_Mov!$E$5:$E$445,Mayor_Mov!$N$5:$N$445,$A47,Mayor_Mov!$B$5:$B$445,"21202140") -> 0 | F47: =SUMIFS(Mayor_Mov!$F$5:$F$445,Mayor_Mov!$N$5:$N$445,$A47,Mayor_Mov!$B$5:$B$445,"21050100")+SUMIFS(Mayor_Mov!$F$5:$F$445,Mayor_Mov!$N$5:$N$445,$A47,Mayor_Mov!$B$5:$B$445,"21050201")+SUMIFS(Mayor_Mov!$F$5:$F$445,Mayor_Mov!$N$5:$N$445,$A47,Mayor_Mov!$B$5:$B$445,"21202040")+SUMIFS(Mayor_Mov!$F$5:$F$445,Mayor_Mov!$N$5:$N$445,$A47,Mayor_Mov!$B$5:$B$445,"21202140") -> 675837500 | G47: =D47+E47-F47 -> -675837500 | H47: =IF(COUNTIF(Detalle_62!$C$14:$C$35,A47)>0,"Sí","NO") -> NO | I47: Leasing nuevo 28-jul-26 no incluido en el detalle 62 → saldo inicial implícito negativo = omisión.
A48: DAV-LGECOLSA | B48: BANCO DAVIVIENDA | C48: Leasing | D48: =SUMIFS(Detalle_62!$F$14:$F$35,Detalle_62!$C$14:$C$35,A48) -> 0 | E48: =SUMIFS(Mayor_Mov!$E$5:$E$445,Mayor_Mov!$N$5:$N$445,$A48,Mayor_Mov!$B$5:$B$445,"21050100")+SUMIFS(Mayor_Mov!$E$5:$E$445,Mayor_Mov!$N$5:$N$445,$A48,Mayor_Mov!$B$5:$B$445,"21050201")+SUMIFS(Mayor_Mov!$E$5:$E$445,Mayor_Mov!$N$5:$N$445,$A48,Mayor_Mov!$B$5:$B$445,"21202040")+SUMIFS(Mayor_Mov!$E$5:$E$445,Mayor_Mov!$N$5:$N$445,$A48,Mayor_Mov!$B$5:$B$445,"21202140") -> 0 | F48: =SUMIFS(Mayor_Mov!$F$5:$F$445,Mayor_Mov!$N$5:$N$445,$A48,Mayor_Mov!$B$5:$B$445,"21050100")+SUMIFS(Mayor_Mov!$F$5:$F$445,Mayor_Mov!$N$5:$N$445,$A48,Mayor_Mov!$B$5:$B$445,"21050201")+SUMIFS(Mayor_Mov!$F$5:$F$445,Mayor_Mov!$N$5:$N$445,$A48,Mayor_Mov!$B$5:$B$445,"21202040")+SUMIFS(Mayor_Mov!$F$5:$F$445,Mayor_Mov!$N$5:$N$445,$A48,Mayor_Mov!$B$5:$B$445,"21202140") -> 0 | G48: =D48+E48-F48 -> 0 | H48: =IF(COUNTIF(Detalle_62!$C$14:$C$35,A48)>0,"Sí","NO") -> NO | I48: Leasing GECOLSA: sin movimiento 2026 y fuera del detalle 62; su saldo ($213,9 MM) está en el saldo inicial del mayor.
A49: N/A-COMISION | B49: N/A | C49: Leasing | D49: =SUMIFS(Detalle_62!$F$14:$F$35,Detalle_62!$C$14:$C$35,A49) -> 0 | E49: =SUMIFS(Mayor_Mov!$E$5:$E$445,Mayor_Mov!$N$5:$N$445,$A49,Mayor_Mov!$B$5:$B$445,"21050100")+SUMIFS(Mayor_Mov!$E$5:$E$445,Mayor_Mov!$N$5:$N$445,$A49,Mayor_Mov!$B$5:$B$445,"21050201")+SUMIFS(Mayor_Mov!$E$5:$E$445,Mayor_Mov!$N$5:$N$445,$A49,Mayor_Mov!$B$5:$B$445,"21202040")+SUMIFS(Mayor_Mov!$E$5:$E$445,Mayor_Mov!$N$5:$N$445,$A49,Mayor_Mov!$B$5:$B$445,"21202140") -> 35428634 | F49: =SUMIFS(Mayor_Mov!$F$5:$F$445,Mayor_Mov!$N$5:$N$445,$A49,Mayor_Mov!$B$5:$B$445,"21050100")+SUMIFS(Mayor_Mov!$F$5:$F$445,Mayor_Mov!$N$5:$N$445,$A49,Mayor_Mov!$B$5:$B$445,"21050201")+SUMIFS(Mayor_Mov!$F$5:$F$445,Mayor_Mov!$N$5:$N$445,$A49,Mayor_Mov!$B$5:$B$445,"21202040")+SUMIFS(Mayor_Mov!$F$5:$F$445,Mayor_Mov!$N$5:$N$445,$A49,Mayor_Mov!$B$5:$B$445,"21202140") -> 35428634 | G49: =D49+E49-F49 -> 0 | H49: =IF(COUNTIF(Detalle_62!$C$14:$C$35,A49)>0,"Sí","NO") -> NO | I49: Comisiones Valley Trading registradas y reclasificadas en 21202040 (neto 0). Partida ajena a obligaciones.
A50: N/A-CRUCE | B50: N/A | C50: Leasing | D50: =SUMIFS(Detalle_62!$F$14:$F$35,Detalle_62!$C$14:$C$35,A50) -> 0 | E50: =SUMIFS(Mayor_Mov!$E$5:$E$445,Mayor_Mov!$N$5:$N$445,$A50,Mayor_Mov!$B$5:$B$445,"21050100")+SUMIFS(Mayor_Mov!$E$5:$E$445,Mayor_Mov!$N$5:$N$445,$A50,Mayor_Mov!$B$5:$B$445,"21050201")+SUMIFS(Mayor_Mov!$E$5:$E$445,Mayor_Mov!$N$5:$N$445,$A50,Mayor_Mov!$B$5:$B$445,"21202040")+SUMIFS(Mayor_Mov!$E$5:$E$445,Mayor_Mov!$N$5:$N$445,$A50,Mayor_Mov!$B$5:$B$445,"21202140") -> 8261283 | F50: =SUMIFS(Mayor_Mov!$F$5:$F$445,Mayor_Mov!$N$5:$N$445,$A50,Mayor_Mov!$B$5:$B$445,"21050100")+SUMIFS(Mayor_Mov!$F$5:$F$445,Mayor_Mov!$N$5:$N$445,$A50,Mayor_Mov!$B$5:$B$445,"21050201")+SUMIFS(Mayor_Mov!$F$5:$F$445,Mayor_Mov!$N$5:$N$445,$A50,Mayor_Mov!$B$5:$B$445,"21202040")+SUMIFS(Mayor_Mov!$F$5:$F$445,Mayor_Mov!$N$5:$N$445,$A50,Mayor_Mov!$B$5:$B$445,"21202140") -> 8261283 | G50: =D50+E50-F50 -> 0 | H50: =IF(COUNTIF(Detalle_62!$C$14:$C$35,A50)>0,"Sí","NO") -> NO | I50: NI-4731 'cruce anticipo calderas' en 21202140 Davivienda (neto 0). Partida ajena a obligaciones.
A51: Total Crédito | D51: =SUMIFS(D24:D50,$C$24:$C$50,"Crédito") -> 3.8300667e+10 | E51: =SUMIFS(E24:E50,$C$24:$C$50,"Crédito") -> 27706000000 | F51: =SUMIFS(F24:F50,$C$24:$C$50,"Crédito") -> 24700000000 | G51: =SUMIFS(G24:G50,$C$24:$C$50,"Crédito") -> 4.1306667e+10
A52: Mayor Crédito (SI / Déb / Créd / —) | E52: =Balance_21!$D$16+Balance_21!$D$18 -> 27706000000 | F52: =Balance_21!$E$16+Balance_21!$E$18 -> 24700000000 | G52: =-(Balance_21!$C$16+Balance_21!$C$18) -> 41306666666
A53: Diferencia Crédito (detalle implícito − mayor) | E53: =E51-E52 -> 0 | F53: =F51-F52 -> 0 | G53: =G51-G52 -> -0.66666412
A55: Total Leasing | D55: =SUMIFS(D24:D50,$C$24:$C$50,"Leasing") -> 6.8852455e+09 | E55: =SUMIFS(E24:E50,$C$24:$C$50,"Leasing") -> 9.4651053e+08 | F55: =SUMIFS(F24:F50,$C$24:$C$50,"Leasing") -> 719527417 | G55: =SUMIFS(G24:G50,$C$24:$C$50,"Leasing") -> 7.1122286e+09
A56: Mayor Leasing (SI / Déb / Créd / —) | E56: =Balance_21!$D$22+Balance_21!$D$24 -> 9.4651053e+08 | F56: =Balance_21!$E$22+Balance_21!$E$24 -> 719527417 | G56: =-(Balance_21!$C$22+Balance_21!$C$24) -> 8.1304947e+09
A57: Diferencia Leasing (detalle implícito − mayor) | E57: =E55-E56 -> 0 | F57: =F55-F56 -> 0 | G57: =G55-G56 -> -1.0182662e+09

Sheet Intereses_x_Obligacion
A1: Intereses por obligación 2026 – causación (2130), pagos, gasto y recálculo al corte
A2: Saldo 2130 por obligación = detalle 31-dic-25 + causaciones 2026 − reversiones 2026. Gasto 2026 = causaciones 2130 + intereses pagados directo al gasto (Int_Glosas).
A4: ID auditoría | B4: Banco | C4: 2130 al 31-dic-25 | D4: Causaciones 2026 (Cr 2130) | E4: Reversiones 2026 (Db 2130) | F4: 2130 al 31-jul-26 por obligación | G4: Pagado directo a gasto (glosas) | H4: Cuotas sin dato | I4: Gasto intereses 2026 registrado | J4: Interés según tabla ene–jul 26 | K4: Registrado − tabla | L4: Causación recalculada 31-jul | M4: Causación no registrada | N4: Comentario
A5: DAV-8906 | B5: BANCO DAVIVIENDA | C5: =SUMIFS(Mayor_Dic25!$G$5:$G$200,Mayor_Dic25!$J$5:$J$200,A5,Mayor_Dic25!$C$5:$C$200,"2130*") -> 409183333 | D5: =SUMIFS(Mayor_Mov!$F$5:$F$445,Mayor_Mov!$N$5:$N$445,A5,Mayor_Mov!$B$5:$B$445,"2130*") -> 66026667 | E5: =SUMIFS(Mayor_Mov!$E$5:$E$445,Mayor_Mov!$N$5:$N$445,A5,Mayor_Mov!$B$5:$B$445,"2130*") -> 475210000 | F5: =C5+D5-E5 -> 0 | G5: =SUMIFS(Int_Glosas!$E$5:$E$39,Int_Glosas!$A$5:$A$39,A5) -> 0 | H5: =COUNTIFS(Int_Glosas!$A$5:$A$39,A5,Int_Glosas!$F$5:$F$39,"Sin dato") -> 0 | I5: =D5+G5 -> 66026667 | J5: =IFERROR(INDEX(Tablas_Amortizacion!$S$8:$S$44,MATCH(A5,Tablas_Amortizacion!$A$8:$A$44,0)),"Sin tabla") -> Sin tabla | K5: =IF(ISNUMBER(J5),I5-J5,"N/A") -> N/A | L5: =SUMIFS(Pruebas_Auditoria!$I$213:$I$235,Pruebas_Auditoria!$A$213:$A$235,A5) -> 0 | M5: =L5-F5 -> 0 | N5: Cancelado ene-26: causación de 2025 reversada con el pago.
A6: DAV-569032 | B6: BANCO DAVIVIENDA | C6: =SUMIFS(Mayor_Dic25!$G$5:$G$200,Mayor_Dic25!$J$5:$J$200,A6,Mayor_Dic25!$C$5:$C$200,"2130*") -> 156505000 | D6: =SUMIFS(Mayor_Mov!$F$5:$F$445,Mayor_Mov!$N$5:$N$445,A6,Mayor_Mov!$B$5:$B$445,"2130*") -> 234581000 | E6: =SUMIFS(Mayor_Mov!$E$5:$E$445,Mayor_Mov!$N$5:$N$445,A6,Mayor_Mov!$B$5:$B$445,"2130*") -> 391086000 | F6: =C6+D6-E6 -> 0 | G6: =SUMIFS(Int_Glosas!$E$5:$E$39,Int_Glosas!$A$5:$A$39,A6) -> 0 | H6: =COUNTIFS(Int_Glosas!$A$5:$A$39,A6,Int_Glosas!$F$5:$F$39,"Sin dato") -> 0 | I6: =D6+G6 -> 234581000 | J6: =IFERROR(INDEX(Tablas_Amortizacion!$S$8:$S$44,MATCH(A6,Tablas_Amortizacion!$A$8:$A$44,0)),"Sin tabla") -> 262697500 | K6: =IF(ISNUMBER(J6),I6-J6,"N/A") -> -28116500 | L6: =SUMIFS(Pruebas_Auditoria!$I$213:$I$235,Pruebas_Auditoria!$A$213:$A$235,A6) -> 3666117.8 | M6: =L6-F6 -> 3666117.8
A7: DAV-830624 | B7: BANCO DAVIVIENDA | C7: =SUMIFS(Mayor_Dic25!$G$5:$G$200,Mayor_Dic25!$J$5:$J$200,A7,Mayor_Dic25!$C$5:$C$200,"2130*") -> 231356250 | D7: =SUMIFS(Mayor_Mov!$F$5:$F$445,Mayor_Mov!$N$5:$N$445,A7,Mayor_Mov!$B$5:$B$445,"2130*") -> 586251750 | E7: =SUMIFS(Mayor_Mov!$E$5:$E$445,Mayor_Mov!$N$5:$N$445,A7,Mayor_Mov!$B$5:$B$445,"2130*") -> 445208000 | F7: =C7+D7-E7 -> 372400000 | G7: =SUMIFS(Int_Glosas!$E$5:$E$39,Int_Glosas!$A$5:$A$39,A7) -> 0 | H7: =COUNTIFS(Int_Glosas!$A$5:$A$39,A7,Int_Glosas!$F$5:$F$39,"Sin dato") -> 0 | I7: =D7+G7 -> 586251750 | J7: =IFERROR(INDEX(Tablas_Amortizacion!$S$8:$S$44,MATCH(A7,Tablas_Amortizacion!$A$8:$A$44,0)),"Sin tabla") -> 639243750 | K7: =IF(ISNUMBER(J7),I7-J7,"N/A") -> -52992000 | L7: =SUMIFS(Pruebas_Auditoria!$I$213:$I$235,Pruebas_Auditoria!$A$213:$A$235,A7) -> 4.0145817e+08 | M7: =L7-F7 -> 29058173
A8: DAV-607691 | B8: BANCO DAVIVIENDA | C8: =SUMIFS(Mayor_Dic25!$G$5:$G$200,Mayor_Dic25!$J$5:$J$200,A8,Mayor_Dic25!$C$5:$C$200,"2130*") -> 206586600 | D8: =SUMIFS(Mayor_Mov!$F$5:$F$445,Mayor_Mov!$N$5:$N$445,A8,Mayor_Mov!$B$5:$B$445,"2130*") -> 309646400 | E8: =SUMIFS(Mayor_Mov!$E$5:$E$445,Mayor_Mov!$N$5:$N$445,A8,Mayor_Mov!$B$5:$B$445,"2130*") -> 516233000 | F8: =C8+D8-E8 -> 0 | G8: =SUMIFS(Int_Glosas!$E$5:$E$39,Int_Glosas!$A$5:$A$39,A8) -> 0 | H8: =COUNTIFS(Int_Glosas!$A$5:$A$39,A8,Int_Glosas!$F$5:$F$39,"Sin dato") -> 0 | I8: =D8+G8 -> 309646400 | J8: =IFERROR(INDEX(Tablas_Amortizacion!$S$8:$S$44,MATCH(A8,Tablas_Amortizacion!$A$8:$A$44,0)),"Sin tabla") -> 346760700 | K8: =IF(ISNUMBER(J8),I8-J8,"N/A") -> -37114300 | L8: =SUMIFS(Pruebas_Auditoria!$I$213:$I$235,Pruebas_Auditoria!$A$213:$A$235,A8) -> 4839280.6 | M8: =L8-F8 -> 4839280.6
A9: DAV-L1019441 | B9: BANCO DAVIVIENDA | C9: =SUMIFS(Mayor_Dic25!$G$5:$G$200,Mayor_Dic25!$J$5:$J$200,A9,Mayor_Dic25!$C$5:$C$200,"2130*") -> 0 | D9: =SUMIFS(Mayor_Mov!$F$5:$F$445,Mayor_Mov!$N$5:$N$445,A9,Mayor_Mov!$B$5:$B$445,"2130*") -> 0 | E9: =SUMIFS(Mayor_Mov!$E$5:$E$445,Mayor_Mov!$N$5:$N$445,A9,Mayor_Mov!$B$5:$B$445,"2130*") -> 0 | F9: =C9+D9-E9 -> 0 | G9: =SUMIFS(Int_Glosas!$E$5:$E$39,Int_Glosas!$A$5:$A$39,A9) -> 31222019 | H9: =COUNTIFS(Int_Glosas!$A$5:$A$39,A9,Int_Glosas!$F$5:$F$39,"Sin dato") -> 1 | I9: =D9+G9 -> 31222019 | J9: =IFERROR(INDEX(Tablas_Amortizacion!$S$8:$S$44,MATCH(A9,Tablas_Amortizacion!$A$8:$A$44,0)),"Sin tabla") -> 41709582 | K9: =IF(ISNUMBER(J9),I9-J9,"N/A") -> -10487563 | L9: =SUMIFS(Pruebas_Auditoria!$I$213:$I$235,Pruebas_Auditoria!$A$213:$A$235,A9) -> 2939106.3 | M9: =L9-F9 -> 2939106.3
A10: DAV-L1019448 | B10: BANCO DAVIVIENDA | C10: =SUMIFS(Mayor_Dic25!$G$5:$G$200,Mayor_Dic25!$J$5:$J$200,A10,Mayor_Dic25!$C$5:$C$200,"2130*") -> 0 | D10: =SUMIFS(Mayor_Mov!$F$5:$F$445,Mayor_Mov!$N$5:$N$445,A10,Mayor_Mov!$B$5:$B$445,"2130*") -> 0 | E10: =SUMIFS(Mayor_Mov!$E$5:$E$445,Mayor_Mov!$N$5:$N$445,A10,Mayor_Mov!$B$5:$B$445,"2130*") -> 0 | F10: =C10+D10-E10 -> 0 | G10: =SUMIFS(Int_Glosas!$E$5:$E$39,Int_Glosas!$A$5:$A$39,A10) -> 25643813 | H10: =COUNTIFS(Int_Glosas!$A$5:$A$39,A10,Int_Glosas!$F$5:$F$39,"Sin dato") -> 1 | I10: =D10+G10 -> 25643813 | J10: =IFERROR(INDEX(Tablas_Amortizacion!$S$8:$S$44,MATCH(A10,Tablas_Amortizacion!$A$8:$A$44,0)),"Sin tabla") -> 31864026 | K10: =IF(ISNUMBER(J10),I10-J10,"N/A") -> -6220212.6 | L10: =SUMIFS(Pruebas_Auditoria!$I$213:$I$235,Pruebas_Auditoria!$A$213:$A$235,A10) -> 3388544.1 | M10: =L10-F10 -> 3388544.1
A11: DAV-L1021275 | B11: BANCO DAVIVIENDA | C11: =SUMIFS(Mayor_Dic25!$G$5:$G$200,Mayor_Dic25!$J$5:$J$200,A11,Mayor_Dic25!$C$5:$C$200,"2130*") -> 34295624 | D11: =SUMIFS(Mayor_Mov!$F$5:$F$445,Mayor_Mov!$N$5:$N$445,A11,Mayor_Mov!$B$5:$B$445,"2130*") -> 138538864 | E11: =SUMIFS(Mayor_Mov!$E$5:$E$445,Mayor_Mov!$N$5:$N$445,A11,Mayor_Mov!$B$5:$B$445,"2130*") -> 172834488 | F11: =C11+D11-E11 -> 0 | G11: =SUMIFS(Int_Glosas!$E$5:$E$39,Int_Glosas!$A$5:$A$39,A11) -> 0 | H11: =COUNTIFS(Int_Glosas!$A$5:$A$39,A11,Int_Glosas!$F$5:$F$39,"Sin dato") -> 0 | I11: =D11+G11 -> 138538864 | J11: =IFERROR(INDEX(Tablas_Amortizacion!$S$8:$S$44,MATCH(A11,Tablas_Amortizacion!$A$8:$A$44,0)),"Sin tabla") -> 1.5442855e+08 | K11: =IF(ISNUMBER(J11),I11-J11,"N/A") -> -15889687 | L11: =SUMIFS(Pruebas_Auditoria!$I$213:$I$235,Pruebas_Auditoria!$A$213:$A$235,A11) -> 5545405.4 | M11: =L11-F11 -> 5545405.4
A12: DAV-LGECOLSA | B12: BANCO DAVIVIENDA | C12: =SUMIFS(Mayor_Dic25!$G$5:$G$200,Mayor_Dic25!$J$5:$J$200,A12,Mayor_Dic25!$C$5:$C$200,"2130*") -> 0 | D12: =SUMIFS(Mayor_Mov!$F$5:$F$445,Mayor_Mov!$N$5:$N$445,A12,Mayor_Mov!$B$5:$B$445,"2130*") -> 0 | E12: =SUMIFS(Mayor_Mov!$E$5:$E$445,Mayor_Mov!$N$5:$N$445,A12,Mayor_Mov!$B$5:$B$445,"2130*") -> 0 | F12: =C12+D12-E12 -> 0 | G12: =SUMIFS(Int_Glosas!$E$5:$E$39,Int_Glosas!$A$5:$A$39,A12) -> 0 | H12: =COUNTIFS(Int_Glosas!$A$5:$A$39,A12,Int_Glosas!$F$5:$F$39,"Sin dato") -> 0 | I12: =D12+G12 -> 0 | J12: =IFERROR(INDEX(Tablas_Amortizacion!$S$8:$S$44,MATCH(A12,Tablas_Amortizacion!$A$8:$A$44,0)),"Sin tabla") -> Sin tabla | K12: =IF(ISNUMBER(J12),I12-J12,"N/A") -> N/A | L12: =SUMIFS(Pruebas_Auditoria!$I$213:$I$235,Pruebas_Auditoria!$A$213:$A$235,A12) -> 0 | M12: =L12-F12 -> 0 | N12: Sin tabla ni extracto: intereses no identificados en 2026 (PEND-12).
A13: BOG-453436746 | B13: BANCO DE BOGOTA | C13: =SUMIFS(Mayor_Dic25!$G$5:$G$200,Mayor_Dic25!$J$5:$J$200,A13,Mayor_Dic25!$C$5:$C$200,"2130*") -> 0 | D13: =SUMIFS(Mayor_Mov!$F$5:$F$445,Mayor_Mov!$N$5:$N$445,A13,Mayor_Mov!$B$5:$B$445,"2130*") -> 0 | E13: =SUMIFS(Mayor_Mov!$E$5:$E$445,Mayor_Mov!$N$5:$N$445,A13,Mayor_Mov!$B$5:$B$445,"2130*") -> 0 | F13: =C13+D13-E13 -> 0 | G13: =SUMIFS(Int_Glosas!$E$5:$E$39,Int_Glosas!$A$5:$A$39,A13) -> 2.3229766e+08 | H13: =COUNTIFS(Int_Glosas!$A$5:$A$39,A13,Int_Glosas!$F$5:$F$39,"Sin dato") -> 1 | I13: =D13+G13 -> 2.3229766e+08 | J13: =IFERROR(INDEX(Tablas_Amortizacion!$S$8:$S$44,MATCH(A13,Tablas_Amortizacion!$A$8:$A$44,0)),"Sin tabla") -> 2.8421922e+08 | K13: =IF(ISNUMBER(J13),I13-J13,"N/A") -> -51921555 | L13: =SUMIFS(Pruebas_Auditoria!$I$213:$I$235,Pruebas_Auditoria!$A$213:$A$235,A13) -> 17704418 | M13: =L13-F13 -> 17704418 | N13: Paga mensual; el cliente no causa entre cuotas.
